Workbook
Name ava: 'Average Total Assets'!$F:$F
Name kode: 'Average Total Assets'!$B:$B
Name th: 'Average Total Assets'!$C:$C

Sheet Average Total Assets
A1: No | B1: Kode Emiten | C1: Tahun | D1: Beginning Total Asset | E1: End Total Assets | F1: Average Total Assets
A2: 1 | B2: ASTJ | C2: 2017 | D2: 427094000000 | E2: 446108163202 | F2: =(D2+E2)/2 -> 436601081601
A3: 2 | B3: ASTJ | C3: 2018 | D3: 446108163202 | E3: 478439333039 | F3: =(D3+E3)/2 -> 4.6227375e+11
A4: 3 | B4: ASTJ | C4: 2019 | D4: 478439333039 | E4: 447670324778 | F4: =(D4+E4)/2 -> 4.6305483e+11
A5: 4 | B5: ASTJ | C5: 2020 | D5: 447670324778 | E5: 365763908254 | F5: =(D5+E5)/2 -> 406717116516
A6: 5 | B6: ASTJ | C6: 2021 | D6: 365763908254 | E6: 527852244647 | F6: =(D6+E6)/2 -> 4.4680808e+11
A7: 6 | B7: ASMI | C7: 2017 | D7: 617651155745 | E7: 858490283480 | F7: =(D7+E7)/2 -> 7.3807072e+11
A8: 7 | B8: ASMI | C8: 2018 | D8: 858490283480 | E8: 969866560976 | F8: =(D8+E8)/2 -> 914178422228
A9: 8 | B9: ASMI | C9: 2019 | D9: 969866560976 | E9: 975687462693 | F9: =(D9+E9)/2 -> 9.7277701e+11
A10: 9 | B10: ASMI | C10: 2020 | D10: 975687462693 | E10: 990991744064 | F10: =(D10+E10)/2 -> 9.833396e+11
A11: 10 | B11: ASMI | C11: 2021 | D11: 990991744064 | E11: 981089572950 | F11: =(D11+E11)/2 -> 986040658507
A12: 11 | B12: BBNI | C12: 2017 | D12: 603031880000000 | E12: 709330084000000 | F12: =(D12+E12)/2 -> 656180982000000
A13: 12 | B13: BBNI | C13: 2018 | D13: 709330084000000 | E13: 808572011000000 | F13: =(D13+E13)/2 -> 758951047500000
... A102: 101 | B102: ASDM | C102: 2017 | D102: 1063856088000 | E102: 1076575416000 | F102: =(D102+E102)/2 -> 1070215752000
A103: 102 | C103: 2018 | D103: =E102 -> 1076575416000 | E103: 1061398832000 | F103: =(D103+E103)/2 -> 1068987124000
A104: 103 | C104: 2019 | D104: =E103 -> 1061398832000 | E104: 1158038755000 | F104: =(D104+E104)/2 -> 1109718793500
A105: 104 | C105: 2020 | D105: =E104 -> 1158038755000 | E105: 859876511000 | F105: =(D105+E105)/2 -> 1008957633000
A106: 105 | C106: 2021 | D106: =E105 -> 859876511000 | E106: 822740369000 | F106: =(D106+E106)/2 -> 841308440000
A107: 106 | B107: BBKP | C107: 2017 | D107: 105406002000000 | E107: 106442999000000 | F107: =(D107+E107)/2 -> 105924500500000
A108: 107 | C108: 2018 | D108: =E107 -> 106442999000000 | E108: 95643923000000 | F108: =(D108+E108)/2 -> 101043461000000
A109: 108 | C109: 2019 | D109: =E108 -> 95643923000000 | E109: 100264248000000 | F109: =(D109+E109)/2 -> 97954085500000
A110: 109 | C110: 2020 | D110: =E109 -> 100264248000000 | E110: 79938578000000 | F110: =(D110+E110)/2 -> 90101413000000
A111: 110 | C111: 2021 | D111: =E110 -> 79938578000000 | E111: 89215674000000 | F111: =(D111+E111)/2 -> 84577126000000
A112: 111 | B112: BBMD | C112: 2017 | D112: 10588224193569 | E112: 11817844456356 | F112: =(D112+E112)/2 -> 1.1203034e+13
A113: 112 | C113: 2018 | D113: =E112 -> 11817844456356 | E113: 12093079368934 | F113: =(D113+E113)/2 -> 11955461912645
A114: 113 | C114: 2019 | D114: =E113 -> 12093079368934 | E114: 12900218775263 | F114: =(D114+E114)/2 -> 1.2496649e+13
A115: 114 | C115: 2020 | D115: =E114 -> 12900218775263 | E115: 14159755232533 | F115: =(D115+E115)/2 -> 13529987003898
A116: 115 | C116: 2021 | D116: =E115 -> 14159755232533 | E116: 15983152301240 | F116: =(D116+E116)/2 -> 1.5071454e+13
A117: 116 | B117: BBRI | C117: 2017 | D117: 878426312000000 | E117: 1.1274475e+15 | F117: =(D117+E117)/2 -> 1.0029369e+15
A118: 117 | C118: 2018 | D118: =E117 -> 1.1274475e+15 | E118: 1.2968983e+15 | F118: =(D118+E118)/2 -> 1.2121729e+15
A119: 118 | C119: 2019 | D119: =E118 -> 1.2968983e+15 | E119: 1.4167588e+15 | F119: =(D119+E119)/2 -> 1.3568286e+15
A120: 119 | C120: 2020 | D120: =E119 -> 1.4167588e+15 | E120: 1.6100653e+15 | F120: =(D120+E120)/2 -> 1.5134121e+15
A121: 120 | C121: 2021 | D121: =E120 -> 1.6100653e+15 | E121: 1.6780977e+15 | F121: =(D121+E121)/2 -> 1.6440815e+15
A122: 121 | B122: BBYB | C122: 2017 | D122: 4846528413826 | E122: 5004795018159 | F122: =(D122+E122)/2 -> 4.9256617e+12
A123: 122 | C123: 2018 | D123: =E122 -> 5004795018159 | E123: 4533729146622 | F123: =(D123+E123)/2 -> 4.7692621e+12
A124: 123 | C124: 2019 | D124: =E123 -> 4533729146622 | E124: 5123734649117 | F124: =(D124+E124)/2 -> 4.8287319e+12
A125: 124 | C125: 2020 | D125: =E124 -> 5123734649117 | E125: 5421324398438 | F125: =(D125+E125)/2 -> 5.2725295e+12
A126: 125 | C126: 2021 | D126: =E125 -> 5421324398438 | E126: 11337808684383 | F126: =(D126+E126)/2 -> 8.3795665e+12
A127: 126 | B127: BINA | C127: 2017 | D127: 2359089000000 | E127: 3123345000000 | F127: =(D127+E127)/2 -> 2741217000000
A128: 127 | C128: 2018 | D128: =E127 -> 3123345000000 | E128: 3854174000000 | F128: =(D128+E128)/2 -> 3488759500000
A129: 128 | C129: 2019 | D129: =E128 -> 3854174000000 | E129: 5262429000000 | F129: =(D129+E129)/2 -> 4558301500000
A130: 129 | C130: 2020 | D130: =E129 -> 5262429000000 | E130: 8437685000000 | F130: =(D130+E130)/2 -> 6850057000000
A131: 130 | C131: 2021 | D131: =E130 -> 8437685000000 | E131: 15055850000000 | F131: =(D131+E131)/2 -> 11746767500000
A132: 131 | B132: BJTM | C132: 2017 | D132: 43032950000000 | E132: 51518581000000 | F132: =(D132+E132)/2 -> 47275765500000
A133: 132 | C133: 2018 | D133: =E132 -> 51518581000000 | E133: 62689118000000 | F133: =(D133+E133)/2 -> 57103849500000
A134: 133 | C134: 2019 | D134: =E133 -> 62689118000000 | E134: 76756313000000 | F134: =(D134+E134)/2 -> 69722715500000
A135: 134 | C135: 2020 | D135: =E134 -> 76756313000000 | E135: 83619452000000 | F135: =(D135+E135)/2 -> 80187882500000
A136: 135 | C136: 2021 | D136: =E135 -> 83619452000000 | E136: 100723330000000 | F136: =(D136+E136)/2 -> 92171391000000
A137: 136 | B137: BMRI | C137: 2017 | D137: 1.038706e+15 | E137: 1.1247008e+15 | F137: =(D137+E137)/2 -> 1.0817034e+15
A138: 137 | C138: 2018 | D138: =E137 -> 1.1247008e+15 | E138: 1.2022521e+15 | F138: =(D138+E138)/2 -> 1.1634765e+15
A139: 138 | C139: 2019 | D139: =E138 -> 1.2022521e+15 | E139: 1.3182463e+15 | F139: =(D139+E139)/2 -> 1.2602492e+15
A140: 139 | C140: 2020 | D140: =E139 -> 1.3182463e+15 | E140: 1.4293345e+15 | F140: =(D140+E140)/2 -> 1.3737904e+15
A141: 140 | C141: 2021 | D141: =E140 -> 1.4293345e+15 | E141: 1.7256111e+15 | F141: =(D141+E141)/2 -> 1.5774728e+15
A142: 141 | B142: BNBA | C142: 2017 | D142: 7121173332944 | E142: 7014677335611 | F142: =(D142+E142)/2 -> 7.0679253e+12
A143: 142 | C143: 2018 | D143: =E142 -> 7014677335611 | E143: 7297273467260 | F143: =(D143+E143)/2 -> 7.1559754e+12
A144: 143 | C144: 2019 | D144: =E143 -> 7297273467260 | E144: 7607653715376 | F144: =(D144+E144)/2 -> 7452463591318
A145: 144 | C145: 2020 | D145: =E144 -> 7607653715376 | E145: 7637524325854 | F145: =(D145+E145)/2 -> 7622589020615
A146: 145 | C146: 2021 | D146: =E145 -> 7637524325854 | E146: 8666525828600 | F146: =(D146+E146)/2 -> 8152025077227
A147: 146 | B147: AGRO | C147: 2017 | D147: 11377960721000 | E147: 16322593372000 | F147: =(D147+E147)/2 -> 13850277046500
A148: 147 | C148: 2018 | D148: =E147 -> 16322593372000 | E148: 23313671252000 | F148: =(D148+E148)/2 -> 19818132312000
A149: 148 | C149: 2019 | D149: =E148 -> 23313671252000 | E149: 27067922912000 | F149: =(D149+E149)/2 -> 25190797082000
A150: 149 | C150: 2020 | D150: =E149 -> 27067922912000 | E150: 28015492262000 | F150: =(D150+E150)/2 -> 27541707587000
A151: 150 | C151: 2021 | D151: =E150 -> 28015492262000 | E151: 16866522655000 | F151: =(D151+E151)/2 -> 22441007458500
A152: 151 | B152: BSIM | C152: 2017 | D152: 31192626000000 | E152: 30404078000000 | F152: =(D152+E152)/2 -> 30798352000000
A153: 152 | C153: 2018 | D153: =E152 -> 30404078000000 | E153: 30748742000000 | F153: =(D153+E153)/2 -> 30576410000000
A154: 153 | C154: 2019 | D154: =E153 -> 30748742000000 | E154: 36559556000000 | F154: =(D154+E154)/2 -> 33654149000000
A155: 154 | C155: 2020 | D155: =E154 -> 36559556000000 | E155: 44612045000000 | F155: =(D155+E155)/2 -> 40585800500000
A156: 155 | C156: 2021 | D156: =E155 -> 44612045000000 | E156: 52267198100000 | F156: =(D156+E156)/2 -> 48439621550000
A157: 156 | B157: INPC | C157: 2017 | D157: 26219938000000 | E157: 27727008000000 | F157: =(D157+E157)/2 -> 26973473000000
A158: 157 | C158: 2018 | D158: =E157 -> 27727008000000 | E158: 26025188000000 | F158: =(D158+E158)/2 -> 26876098000000
A159: 158 | C159: 2019 | D159: =E158 -> 26025188000000 | E159: 25532041000000 | F159: =(D159+E159)/2 -> 25778614500000
A160: 159 | C160: 2020 | D160: =E159 -> 25532041000000 | E160: 30526965000000 | F160: =(D160+E160)/2 -> 28029503000000
A161: 160 | C161: 2021 | D161: =E160 -> 30526965000000 | E161: 26127820000000 | F161: =(D161+E161)/2 -> 28327392500000
A162: 161 | B162: MEGA | C162: 2017 | D162: 70531682000000 | E162: 82297010000000 | F162: =(D162+E162)/2 -> 76414346000000
A163: 162 | C163: 2018 | D163: =E162 -> 82297010000000 | E163: 83761946000000 | F163: =(D163+E163)/2 -> 83029478000000
A164: 163 | C164: 2019 | D164: =E163 -> 83761946000000 | E164: 100803831000000 | F164: =(D164+E164)/2 -> 92282888500000
A165: 164 | C165: 2020 | D165: =E164 -> 100803831000000 | E165: 112202653000000 | F165: =(D165+E165)/2 -> 106503242000000
A166: 165 | C166: 2021 | D166: =E165 -> 112202653000000 | E166: 132879390000000 | F166: =(D166+E166)/2 -> 122541021500000
A167: 166 | B167: TRIM | C167: 2017 | D167: 1570230748000 | E167: 3034342412000 | F167: =(D167+E167)/2 -> 2302286580000
A168: 167 | C168: 2018 | D168: =E167 -> 3034342412000 | E168: 2468609628000 | F168: =(D168+E168)/2 -> 2751476020000
A169: 168 | C169: 2019 | D169: =E168 -> 2468609628000 | E169: 3050556600000 | F169: =(D169+E169)/2 -> 2759583114000
A170: 169 | C170: 2020 | D170: =E169 -> 3050556600000 | E170: 2676388593000 | F170: =(D170+E170)/2 -> 2863472596500
A171: 170 | C171: 2021 | D171: =E170 -> 2676388593000 | E171: 1819841840000 | F171: =(D171+E171)/2 -> 2248115216500
A172: 171 | B172: NISP | C172: 2017 | D172: 138196341000000 | E172: 153773957000000 | F172: =(D172+E172)/2 -> 145985149000000
A173: 172 | C173: 2018 | D173: =E172 -> 153773957000000 | E173: 173582894000000 | F173: =(D173+E173)/2 -> 163678425500000
A174: 173 | C174: 2019 | D174: =E173 -> 173582894000000 | E174: 180706987000000 | F174: =(D174+E174)/2 -> 177144940500000
A175: 174 | C175: 2020 | D175: =E174 -> 180706987000000 | E175: 206297200000000 | F175: =(D175+E175)/2 -> 193502093500000
A176: 175 | C176: 2021 | D176: =E175 -> 206297200000000 | E176: 214395608000000 | F176: =(D176+E176)/2 -> 210346404000000

Sheet ch receivable
A1: No | B1: Kode Emiten | C1: Tahun | D1: Receivable | E1: ∆Receivable | F1: Average Total Assets | G1: CH Rec
A2: 1 | B2: ASTJ | C2: 2017 | D2: =76508107097+14346522792+751105407+13696137698 -> 105301872994 | E2: 0 | F2: 0 | G2: =E2/F2 -> #DIV/0!
A3: 2 | B3: ASTJ | C3: 2018 | D3: =83935111290+13126436678+903019323+11339863183 -> 109304430474 | E3: =D3-D2 -> 4002557480 | F3: 4.6227375e+11 | G3: =E3/F3 -> 0.008658414
A4: 3 | B4: ASTJ | C4: 2019 | D4: =6105094632+62107180919+24373745095+861805626+5970752073+1924322503 -> 101342900848 | E4: =D4-D3 -> -7961529626 | F4: 4.6305483e+11 | G4: =E4/F4 -> -0.017193492
A5: 4 | B5: ASTJ | C5: 2020 | D5: =10909190618+42582398713+43449304553+5670752073+3984951463 -> 106596597420 | E5: =D5-D4 -> 5253696572 | F5: 406717116516 | G5: =E5/F5 -> 0.012917324
A6: 5 | B6: ASTJ | C6: 2021 | D6: =16585607499+52452053623+51368504280+732763300+4928158953+6746881380 -> 132813969035 | E6: =D6-D5 -> 26217371615 | F6: 4.4680808e+11 | G6: =E6/F6 -> 0.058677032
A7: 6 | B7: ASMI | C7: 2017 | D7: =21755720+113476086563+13986354548+12174889005 -> 139659085836 | G7: =E7/F7 -> #DIV/0!
A8: 7 | B8: ASMI | C8: 2018 | D8: =5695950+141393596454+26280788985+12864574994 -> 180544656383 | E8: =D8-D7 -> 40885570547 | F8: 914178422228 | G8: =E8/F8 -> 0.044723841
A9: 8 | B9: ASMI | C9: 2019 | D9: =11736375+107397784947+60102707851+8281893868 -> 175794123041 | E9: =D9-D8 -> -4750533342 | F9: 9.7277701e+11 | G9: =E9/F9 -> -0.0048834762
A10: 9 | B10: ASMI | C10: 2020 | D10: =10035000+106128409949+148962330950+7680263492 -> 262781039391 | E10: =D10-D9 -> 86986916350 | F10: 9.833396e+11 | G10: =E10/F10 -> 0.088460707
A11: 10 | B11: ASMI | C11: 2021 | D11: =65234343420+132635142107+5243671084 -> 203113156611 | E11: =D11-D10 -> -59667882780 | F11: 986040658507 | G11: =E11/F11 -> -0.060512599
A12: 11 | B12: BBNI | C12: 2017 | D12: =3254353000000+2813466000000+2766507000000+71388000000+18106412000000+216884000000+426789981000000 -> 454018991000000 | G12: =E12/F12 -> #DIV/0!
A13: 12 | B13: BBNI | C13: 2018 | D13: =4253128000000+3429531000000+17000000+20295277000000+605248000000+497886888000000 -> 526470089000000 | E13: =D13-D12 -> 72451098000000 | F13: 758951047500000 | G13: =E13/F13 -> 0.095462149
A14: 13 | B14: BBNI | C14: 2019 | D14: =3220178000000+3785287000000+2571286000000+18558276000000+312266000000+539862076000000 -> 568309369000000 | E14: =D14-D13 -> 41839280000000 | F14: 827088609500000 | G14: =E14/F14 -> 0.050586212
A15: 14 | B15: BBNI | C15: 2020 | D15: =3908683000000+3874790000000+2382329000000+20575666000000+140614000000+541978801000000 -> 572860883000000 | E15: =D15-D14 -> 4551514000000 | F15: 868471316500000 | G15: =E15/F15 -> 0.005240834
A16: 15 | B16: BBNI | C16: 2021 | D16: =3333395000000+3057796000000+2051031000000+20542767000000+494183000000+532141344000000 -> 561620516000000 | E16: =D16-D15 -> -11240367000000 | F16: 928087558500000 | G16: =E16/F16 -> -0.012111322
A17: 16 | B17: BBTN | C17: 2017 | D17: =196634594000000+8081000000 -> 196642675000000 | G17: =E17/F17 -> #DIV/0!
A18: 17 | B18: BBTN | C18: 2018 | D18: =234459542000000+528148000000 -> 234987690000000 | E18: =D18-D17 -> 38345015000000 | F18: 283900730500000 | G18: =E18/F18 -> 0.13506487
A19: 18 | B19: BBTN | C19: 2019 | D19: =249708993000000+487052000000 -> 250196045000000 | E19: =D19-D18 -> 15208355000000 | F19: 309106511000000 | G19: =E19/F19 -> 0.049201018
A20: 19 | B20: BBTN | C20: 2020 | D20: =247053220000000+194678000000+70366000000 -> 247318264000000 | E20: =D20-D19 -> -2877781000000 | F20: 336492617000000 | G20: =E20/F20 -> -0.0085522857
A21: 20 | B21: BBTN | C21: 2021 | D21: =260399531000000+31017000000+453517000000 -> 260884065000000 | E21: =D21-D20 -> 13565801000000 | F21: 366538358500000 | G21: =E21/F21 -> 0.03701059
A22: 21 | B22: BCAP | C22: 2017 | D22: =237072000000+811042000000+184885000000+2640852000000-22184000000+555000000+305296000000-2714000000+169120000000-247000000 -> 4323677000000 | G22: =E22/F22 -> #DIV/0!
A23: 22 | B23: BCAP | C23: 2018 | D23: =119242000000+383410000000+369483000000+1917798000000-21885000000+519000000+135696000000-120000000+85125000000-2136000000 -> 2987132000000 | E23: =D23-D22 -> -1336545000000 | F23: 19322993500000 | G23: =E23/F23 -> -0.069168631
A24: 23 | B24: BCAP | C24: 2019 | D24: =169859000000+411428000000+191148000000+1763073000000-22167000000+8965000000+28439000000-1092000000+50897000000-2792000000 -> 2597758000000 | E24: =D24-D23 -> -389374000000 | F24: 18573864500000 | G24: =E24/F24 -> -0.020963543
A25: 24 | B25: BCAP | C25: 2020 | D25: =340136000000+680541000000+180993000000+1390494000000-15447000000+4768000000+89000000-12000000+13316000000-324000000 -> 2594554000000 | E25: =D25-D24 -> -3204000000 | F25: 18743275500000 | G25: =E25/F25 -> -0.00017094131
A26: 25 | B26: BCAP | C26: 2021 | D26: =291740000000+474897000000+208289000000+1317356000000-13338000000+1654000000+3674000000+21610000000-7000000 -> 2305875000000 | E26: =D26-D25 -> -288679000000 | F26: 20377757000000 | G26: =E26/F26 -> -0.014166378
A27: 26 | B27: BDMN | C27: 2017 | D27: =413000000+103493000000+26080060000000+369488000000+1465000000+251502000000+2468000000+1483472000000+71783000000+93973723000000 -> 122337867000000 | G27: =E27/F27 -> #DIV/0!
A28: 27 | B28: BDMN | C28: 2018 | D28: =54553000000+394538000000+28262631000000+240623000000+1679176000000+71783000000+93973723000000 -> 124677027000000 | E28: =D28-D27 -> 2339160000000 | F28: 182509640500000 | G28: =E28/F28 -> 0.012816638
A29: 28 | B29: BDMN | C29: 2019 | D29: =159123000000+29624404000000+290517000000+862696000000+69720000000+106795782000000 -> 137802242000000 | E29: =D29-D28 -> 13125215000000 | F29: 190148079500000 | G29: =E29/F29 -> 0.069026282
A30: 29 | B30: BDMN | C30: 2020 | D30: =362482000000+22605362000000+246644000000+1592400000000+41365000000+103895653000000 -> 128743906000000 | E30: =D30-D29 -> -9058336000000 | F30: 197212019000000 | G30: =E30/F30 -> -0.045931967
A31: 30 | B31: BDMN | C31: 2021 | D31: =187297000000+19958199000000+280613000000+2058574000000+30506000000+99935455000000 -> 122450644000000 | E31: =D31-D30 -> -6293262000000 | F31: 196564883000000 | G31: =E31/F31 -> -0.032016207
A32: 31 | B32: BFIN | C32: 2017 | D32: =9435315000000+5739410000000+414127000000 -> 15588852000000 | G32: =E32/F32 -> #DIV/0!
A33: 32 | B33: BFIN | C33: 2018 | D33: =11357670000000+5922788000000+105000000+198271000000 -> 17478834000000 | E33: =D33-D32 -> 1889982000000 | F33: 17800289000000 | G33: =E33/F33 -> 0.10617704
A34: 33 | B34: BFIN | C34: 2019 | D34: =17395920000000+2105000000+153494000000 -> 17551519000000 | E34: =D34-D33 -> 72685000000 | F34: 19103469000000 | G34: =E34/F34 -> 0.0038048063
A35: 34 | B35: BFIN | C35: 2020 | D35: =12678444000000+586000000+154904000000 -> 12833934000000 | E35: =D35-D34 -> -4717585000000 | F35: 17145082000000 | G35: =E35/F35 -> -0.27515675
A36: 35 | B36: BFIN | C36: 2021 | D36: =13676190000000+941000000+87089000000 -> 13764220000000 | E36: =D36-D35 -> 930286000000 | F36: 15418135000000 | G36: =E36/F36 -> 0.060337129
A37: 36 | B37: BNGA | C37: 2017 | D37: =280293000000+181405722000000+3710084000000+10936000000+4184965000000 -> 189592000000000 | G37: =E37/F37 -> #DIV/0!
A38: 37 | B38: BNGA | C38: 2018 | D38: =1084759000000+180311277000000+2052802000000+1180000000+4462483000000 -> 187912501000000 | E38: =D38-D37 -> -1679499000000 | F38: 266543476500000 | G38: =E38/F38 -> -0.0063010321
A39: 38 | B39: BNGA | C39: 2019 | D39: =725478000000+184998140000000+3179370000000+3767071000000 -> 192670059000000 | E39: =D39-D38 -> 4757558000000 | F39: 270624362500000 | G39: =E39/F39 -> 0.017579932
A40: 39 | B40: BNGA | C40: 2020 | D40: =1359286000000+159851784000000+2977849000000+2022665000000 -> 166211584000000 | E40: =D40-D39 -> -26458475000000 | F40: 277705416000000 | G40: =E40/F40 -> -0.095275329
A41: 40 | B41: BNGA | C41: 2021 | D41: =909081000000+164089257000000+4388529000000+2564041000000 -> 171950908000000 | E41: =D41-D40 -> 5739324000000 | F41: 295865282500000 | G41: =E41/F41 -> 0.019398437
A42: 41 | B42: BNII | C42: 2017 | D42: =200049000000+111809451000000+11488651000000+2747132000000 -> 126245283000000 | G42: =E42/F42 -> #DIV/0!
A43: 42 | B43: BNII | C43: 2018 | D43: =1289978000000+119909785000000+11161919000000+2813730000000 -> 135175412000000 | E43: =D43-D42 -> 8930129000000 | F43: 175393174500000 | G43: =E43/F43 -> 0.050914917
A44: 43 | B44: BNII | C44: 2019 | D44: =748480000000+10839431000000+109179337000000+1740388000000 -> 122507636000000 | E44: =D44-D43 -> -12667776000000 | F44: 173307844000000 | G44: =E44/F44 -> -0.073094072
A45: 44 | B45: BNII | C45: 2020 | D45: =1247872000000+93979899000000+8061654000000+1113285000000 -> 104402710000000 | E45: =D45-D44 -> -18104926000000 | F45: 171153621000000 | G45: =E45/F45 -> -0.10578173
A46: 45 | B46: BNII | C46: 2021 | D46: =560650000000+90675892000000+7826992000000+1664127000000 -> 100727661000000 | E46: =D46-D45 -> -3675049000000 | F46: 170991444000000 | G46: =E46/F46 -> -0.02149259
A47: 46 | B47: BNLI | C47: 2017 | D47: =3569686000000+60174000000+89703197000000+317788000000 -> 93650845000000 | G47: =E47/F47 -> #DIV/0!
A48: 47 | B48: BNLI | C48: 2018 | D48: =2730307000000+23084000000+98912371000000+297230000000 -> 101962992000000 | E48: =D48-D47 -> 8312147000000 | F48: 150610618000000 | G48: =E48/F48 -> 0.055189648
A49: 48 | B49: BNLI | C49: 2019 | D49: =1693465000000+104325105000000+757139000000 -> 106775709000000 | E49: =D49-D48 -> 4812717000000 | F49: 157172062500000 | G49: =E49/F49 -> 0.03062069
A50: 49 | B50: BNLI | C50: 2020 | D50: =1434917000000+110698468000000+112440000000 -> 112245825000000 | E50: =D50-D49 -> 5470116000000 | F50: 179588678000000 | G50: =E50/F50 -> 0.030459136
A51: 50 | B51: BNLI | C51: 2021 | D51: =1927008000000+116875286000000+110592000000 -> 118912886000000 | E51: =D51-D50 -> 6667061000000 | F51: 216052569500000 | G51: =E51/F51 -> 0.030858513
A52: 51 | B52: ADMF | C52: 2017 | D52: =16939102000000+8579855000000+370051000000+9571000000+204225000000+51533000000+85680000000 -> 26240017000000 | G52: =E52/F52 -> #DIV/0!
A53: 52 | B53: ADMF | C53: 2018 | D53: =23258706000000+1698000000+4370502000000+240637000000+241000000+141036000000+55376000000 -> 28068196000000 | E53: =D53-D52 -> 1828179000000 | F53: 30494687000000 | G53: =E53/F53 -> 0.059950738
A54: 53 | B54: ADMF | C54: 2019 | D54: =26799715000000+2479000000+2822205000000+290520000000+33000000+121222000000+345788000000 -> 30381962000000 | E54: =D54-D53 -> 2313766000000 | F54: 33306647000000 | G54: =E54/F54 -> 0.069468596
A55: 54 | B55: ADMF | C55: 2020 | D55: =20151991000000+2449818000000+296000000+246644000000+153970000000+245768000000+1849000000 -> 23250336000000 | E55: =D55-D54 -> -7131626000000 | F55: 32173683000000 | G55: =E55/F55 -> -0.22166023
A56: 55 | B56: ADMF | C56: 2021 | D56: =16904868000000+2006000000+3051084000000+242000000+280613000000+99517000000+256444000000 -> 20594774000000 | E56: =D56-D55 -> -2655562000000 | F56: 26478199000000 | G56: =E56/F56 -> -0.1002924
A57: 56 | B57: BVIC | C57: 2017 | D57: =15576687733000+117881394000 -> 15694569127000 | G57: =E57/F57 -> #DIV/0!
A58: 57 | B58: BVIC | C58: 2018 | D58: =16102771560000+164546909000 -> 16267318469000 | E58: =D58-D57 -> 572749342000 | F58: 29498961992500 | G58: =E58/F58 -> 0.019415915
A59: 58 | B59: BVIC | C59: 2019 | D59: =17054738234000+66543426000 -> 17121281660000 | E59: =D59-D58 -> 853963191000 | F59: 30314387069500 | G59: =E59/F59 -> 0.028170228
A60: 59 | B60: BVIC | C60: 2020 | D60: =14245976032000 -> 14245976032000 | E60: =D60-D59 -> -2875305628000 | F60: 28338933137000 | G60: =E60/F60 -> -0.10146132
A61: 60 | B61: BVIC | C61: 2021 | D61: =14786800658000 -> 14786800658000 | E61: =D61-D60 -> 540824626000 | F61: 25584275258500 | G61: =E61/F61 -> 0.021138947
A62: 61 | B62: CFIN | C62: 2017 | D62: =2713270788000+5716045944000+1139565087000+50722720000 -> 9619604539000 | G62: =E62/F62 -> #DIV/0!
A63: 62 | B63: CFIN | C63: 2018 | D63: =1369068419000+8163519402000+736038827000+463999782000 -> 10732626430000 | E63: =D63-D62 -> 1113021891000 | F63: 10497063221500 | G63: =E63/F63 -> 0.10603174
A64: 63 | B64: CFIN | C64: 2019 | D64: =741211620000+9846112210000+695030908000+437440382000 -> 11719795120000 | E64: =D64-D63 -> 987168690000 | F64: 11610378593000 | G64: =E64/F64 -> 0.085024677
A65: 64 | B65: CFIN | C65: 2020 | D65: =433448957000+7175723377000+671273001000+438906799000 -> 8719352134000 | E65: =D65-D64 -> -3000442986000 | F65: 11517467142500 | G65: =E65/F65 -> -0.2605124
A66: 65 | B66: CFIN | C66: 2021 | D66: =202613282000+5661194488000+82252189000+462366165000 -> 6408426124000 | E66: =D66-D65 -> -2310926010000 | F66: 9020680117500 | G66: =E66/F66 -> -0.25618091
A67: 66 | B67: HDFA | C67: 2017 | D67: =3585278352000+45783117000+5282704000 -> 3636344173000 | G67: =E67/F67 -> #DIV/0!
A68: 67 | B68: HDFA | C68: 2018 | D68: =1567514959000+32912364000+4780126000+11530914000 -> 1616738363000 | E68: =D68-D67 -> -2019605810000 | F68: 3055761564500 | G68: =E68/F68 -> -0.66091734
A69: 68 | B69: HDFA | C69: 2019 | D69: =502697630000+49933215000+1139727000+69589000 -> 553840161000 | E69: =D69-D68 -> -1062898202000 | F69: 1726090971500 | G69: =E69/F69 -> -0.61578342
A70: 69 | B70: HDFA | C70: 2020 | D70: =285098091000+45060540000+143563000+6792416000 -> 337094610000 | E70: =D70-D69 -> -216745551000 | F70: 981752011500 | G70: =E70/F70 -> -0.22077424
A71: 70 | B71: HDFA | C71: 2021 | D71: =980271775000+33803415000+405658000+11634137000 -> 1026114985000 | E71: =D71-D70 -> 689020375000 | F71: 1025994461500 | G71: =E71/F71 -> 0.67156344
A72: 71 | B72: MAYA | C72: 2017 | D72: =55348547000000+36000000 -> 55348583000000 | G72: =E72/F72 -> #DIV/0!
A73: 72 | B73: MAYA | C73: 2018 | D73: =63586749000000 -> 63586749000000 | E73: =D73-D72 -> 8238166000000 | F73: 80858731500000 | G73: =E73/F73 -> 0.10188344
A74: 73 | B74: MAYA | C74: 2019 | D74: =69067509000000 -> 69067509000000 | E74: =D74-D73 -> 5480760000000 | F74: 90190362000000 | G74: =E74/F74 -> 0.060768799
A75: 74 | B75: MAYA | C75: 2020 | D75: 53905027000000 | E75: =D75-D74 -> -15162482000000 | F75: 92963428000000 | G75: =E75/F75 -> -0.16310158
A76: 75 | B76: MAYA | C76: 2021 | D76: =69529675000000+31622000000 -> 69561297000000 | E76: =D76-D75 -> 15656270000000 | F76: 105811105000000 | G76: =E76/F76 -> 0.14796434
A77: 76 | B77: PADI | C77: 2017 | D77: =3285281920+30733477830+1545878134+2667907025 -> 38232544909 | G77: =E77/F77 -> #DIV/0!
A78: 77 | B78: PADI | C78: 2018 | D78: =7193233188+12154104114+25007486+2281592270 -> 21653937058 | E78: =D78-D77 -> -16578607851 | F78: 5.2562413e+11 | G78: =E78/F78 -> -0.031540805
A79: 78 | B79: PADI | C79: 2019 | D79: =1648099099+10186825883+6706700+1279072820 -> 13120704502 | E79: =D79-D78 -> -8533232556 | F79: 480864783071 | G79: =E79/F79 -> -0.017745597
A80: 79 | B80: PADI | C80: 2020 | D80: =10066241244+10853868920+315047836+943953898 -> 22179111898 | E80: =D80-D79 -> 9058407396 | F80: 376502006661 | G80: =E80/F80 -> 0.024059387
A81: 80 | B81: PADI | C81: 2021 | D81: =4796274213+3811048583+13961026+325168967 -> 8946452789 | E81: =D81-D80 -> -13232659109 | F81: 300598582653 | G81: =E81/F81 -> -0.04402103
A82: 81 | B82: PNLF | C82: 2017 | D82: =83334000000+39616000000+10927000000 -> 133877000000 | G82: =E82/F82 -> #DIV/0!
A83: 82 | B83: PNLF | C83: 2018 | D83: =93329000000+73791000000+6227000000 -> 173347000000 | E83: =D83-D82 -> 39470000000 | F83: 27362022500000 | G83: =E83/F83 -> 0.0014425103
A84: 83 | B84: PNLF | C84: 2019 | D84: =90249000000+113506000000+18926000000 -> 222681000000 | E84: =D84-D83 -> 49334000000 | F84: 29271055500000 | G84: =E84/F84 -> 0.0016854192
A85: 84 | B85: PNLF | C85: 2020 | D85: =88197000000+196420000000+35719000000 -> 320336000000 | E85: =D85-D84 -> 97655000000 | F85: 31335553500000 | G85: =E85/F85 -> 0.0031164281
A86: 85 | B86: PNLF | C86: 2021 | D86: =45881000000+89495000000+190295000000+20527000000 -> 346198000000 | E86: =D86-D85 -> 25862000000 | F86: 32787151000000 | G86: =E86/F86 -> 0.00078878461
A87: 86 | B87: SDRA | C87: 2017 | D87: =18649664000000+53211000000 -> 18702875000000 | G87: =E87/F87 -> #DIV/0!
A88: 87 | B88: SDRA | C88: 2018 | D88: =22294572000000+314239000000 -> 22608811000000 | E88: =D88-D87 -> 3905936000000 | F88: 28359098500000 | G88: =E88/F88 -> 0.13773132
A89: 88 | B89: SDRA | C89: 2019 | D89: =26429707000000+640049000000 -> 27069756000000 | E89: =D89-D88 -> 4460945000000 | F89: 33286064500000 | G89: =E89/F89 -> 0.1340184
A90: 89 | B90: SDRA | C90: 2020 | D90: =29579069000000+666193000000 -> 30245262000000 | E90: =D90-D89 -> 3175506000000 | F90: 37497187500000 | G90: =E90/F90 -> 0.084686511
A91: 90 | B91: SDRA | C91: 2021 | D91: =33429580000000+331593000000 -> 33761173000000 | E91: =D91-D90 -> 3515911000000 | F91: 40927755000000 | G91: =E91/F91 -> 0.085905298
A92: 91 | B92: SMMA | C92: 2017 | D92: =1520255000000+3567000000+3979434000000+726170000000+18365482000000+185015000000+475422000000+845229000000 -> 26100574000000 | G92: =E92/F92 -> #DIV/0!
A93: 92 | B93: SMMA | C93: 2018 | D93: =1735809000000+2295000000+4415833000000+960829000000+19214056000000+243250000000+1058913000000+1241709000000 -> 28872694000000 | E93: =D93-D92 -> 2772120000000 | F93: 94875119500000 | G93: =E93/F93 -> 0.029218619
A94: 93 | B94: SMMA | C94: 2019 | D94: =2783341000000+922000000+3996536000000+1118050000000+21314497000000+265212000000+503637000000+1785782000000 -> 31767977000000 | E94: =D94-D93 -> 2895283000000 | F94: 100144154000000 | G94: =E94/F94 -> 0.028911153
A95: 94 | B95: SMMA | C95: 2020 | D95: =2229745000000+526000000+3700987000000+1013362000000+18878373000000+153577000000+976673000000+1476148000000 -> 28429391000000 | E95: =D95-D94 -> -3338586000000 | F95: 104040542000000 | G95: =E95/F95 -> -0.032089279
A96: 95 | B96: SMMA | C96: 2021 | D96: =2042898000000+300613000000+2816748000000+1889817000000+16067805000000+247165000000+385163000000+1569255000000 -> 25319464000000 | E96: =D96-D95 -> -3109927000000 | F96: 112983113000000 | G96: =E96/F96 -> -0.027525591
A97: 96 | B97: WOMF | C97: 2017 | D97: =6796231000000+57981000000 -> 6854212000000 | G97: =E97/F97 -> #DIV/0!
A98: 97 | B98: WOMF | C98: 2018 | D98: =7243068000000+72344000000 -> 7315412000000 | E98: =D98-D97 -> 461200000000 | F98: 8286519500000 | G98: =E98/F98 -> 0.05565666
A99: 98 | B99: WOMF | C99: 2019 | D99: =7205215000000+46574000000 -> 7251789000000 | E99: =D99-D98 -> -63623000000 | F99: 8549238500000 | G99: =E99/F99 -> -0.0074419494
A100: 99 | B100: WOMF | C100: 2020 | D100: =4280120000000+15070000000+23371000000+42988000000 -> 4361549000000 | E100: =D100-D99 -> -2890240000000 | F100: 6777436000000 | G100: =E100/F100 -> -0.42645036
...

Sheet ch in cash sales
C1: No | D1: Kode Emiten | E1: Tahun | F1: Sales/Pendapatan | G1: ∆Sales | H1: Receivable(t) | I1: ∆Receivable | J1: Ch in Sales
C2: 1 | D2: ASTJ | E2: 2017 | F2: 174285978503 | G2: 0 | H2: =76508107097+14346522792+751105407+13696137698 -> 105301872994 | I2: 0 | J2: =(G2/F2)-(I2/H2) -> 0
C3: 2 | D3: ASTJ | E3: 2018 | F3: =163165384062 -> 163165384062 | G3: =F3-F2 -> -11120594441 | H3: =83935111290+13126436678+903019323+11339863183 -> 109304430474 | I3: =H3-H2 -> 4002557480 | J3: =(G3/F3)-(I3/H3) -> -0.10477379
C4: 3 | D4: ASTJ | E4: 2019 | F4: 152809529035 | G4: =F4-F3 -> -10355855027 | H4: =6105094632+62107180919+24373745095+861805626+5970752073+1924322503 -> 101342900848 | I4: =H4-H3 -> -7961529626 | J4: =(G4/F4)-(I4/H4) -> 0.010790615
C5: 4 | D5: ASTJ | E5: 2020 | F5: 107091468350 | G5: =F5-F4 -> -45718060685 | H5: =10909190618+42582398713+43449304553+5670752073+3984951463 -> 106596597420 | I5: =H5-H4 -> 5253696572 | J5: =(G5/F5)-(I5/H5) -> -0.47619244
C6: 5 | D6: ASTJ | E6: 2021 | F6: 115490756693 | G6: =F6-F5 -> 8399288343 | H6: =16585607499+52452053623+51368504280+732763300+4928158953+6746881380 -> 132813969035 | I6: =H6-H5 -> 26217371615 | J6: =(G6/F6)-(I6/H6) -> -0.12467227
C7: 6 | D7: ASMI | E7: 2017 | F7: 58790955548 | H7: =21755720+113476086563+13986354548+12174889005 -> 139659085836 | J7: =(G7/F7)-(I7/H7) -> 0
C8: 7 | D8: ASMI | E8: 2018 | F8: 67042246193 | G8: =F8-F7 -> 8251290645 | H8: =5695950+141393596454+26280788985+12864574994 -> 180544656383 | I8: =H8-H7 -> 40885570547 | J8: =(G8/F8)-(I8/H8) -> -0.10338084
C9: 8 | D9: ASMI | E9: 2019 | F9: 73219691954 | G9: =F9-F8 -> 6177445761 | H9: =11736375+107397784947+60102707851+8281893868 -> 175794123041 | I9: =H9-H8 -> -4750533342 | J9: =(G9/F9)-(I9/H9) -> 0.11139192
C10: 9 | D10: ASMI | E10: 2020 | F10: 63829169140 | G10: =F10-F9 -> -9390522814 | H10: =10035000+106128409949+148962330950+7680263492 -> 262781039391 | I10: =H10-H9 -> 86986916350 | J10: =(G10/F10)-(I10/H10) -> -0.47814394
C11: 10 | D11: ASMI | E11: 2021 | F11: 27094983645 | G11: =-(F11-F10) -> 36734185495 | H11: =65234343420+132635142107+5243671084 -> 203113156611 | I11: =H11-H10 -> -59667882780 | J11: =(G11/F11)-(I11/H11) -> 1.6495227
C12: 11 | D12: BBNI | E12: 2017 | F12: =48177849000000+31937763000000+1767568000000+11040059000000 -> 92923239000000 | H12: =3254353000000+2813466000000+2766507000000+71388000000+18106412000000+216884000000+426789981000000 -> 454018991000000 | J12: =(G12/F12)-(I12/H12) -> 0
C13: 12 | D13: BBNI | E13: 2018 | F13: =54138613000000+35446315000000+1711857000000+11612599000000 -> 102909384000000 | G13: =F13-F12 -> 9986145000000 | H13: =4253128000000+3429531000000+17000000+20295277000000+605248000000+497886888000000 -> 526470089000000 | I13: =H13-H12 -> 72451098000000 | J13: =(G13/F13)-(I13/H13) -> -0.040578506
C14: 13 | D14: BBNI | E14: 2019 | F14: =58532373000000+36602374000000+1696928000000+13712398000000 -> 110544073000000 | G14: =F14-F13 -> 7634689000000 | H14: =3220178000000+3785287000000+2571286000000+18558276000000+312266000000+539862076000000 -> 568309369000000 | I14: =H14-H13 -> 41839280000000 | J14: =(G14/F14)-(I14/H14) -> -0.0045559441
C15: 14 | D15: BBNI | E15: 2020 | F15: =56172871000000+37151966000000+1471088000000+13412581000000 -> 108208506000000 | G15: =F15-F14 -> -2335567000000 | H15: =3908683000000+3874790000000+2382329000000+20575666000000+140614000000+541978801000000 -> 572860883000000 | I15: =H15-H14 -> 4551514000000 | J15: =(G15/F15)-(I15/H15) -> -0.029529185
C16: 15 | D16: BBNI | E16: 2021 | F16: =50025887000000+38246731000000+1398957000000+16219699000000 -> 105891274000000 | G16: =F16-F15 -> -2317232000000 | H16: =3333395000000+3057796000000+2051031000000+20542767000000+494183000000+532141344000000 -> 561620516000000 | I16: =H16-H15 -> -11240367000000 | J16: =(G16/F16)-(I16/H16) -> -0.0018689578
C17: 16 | D17: BBTN | E17: 2017 | F17: =22851758000000+1605931000000 -> 24457689000000 | H17: =196634594000000+8081000000 -> 196642675000000 | J17: =(G17/F17)-(I17/H17) -> 0
C18: 17 | D18: BBTN | E18: 2018 | F18: =22851758000000+2071594000000 -> 24923352000000 | G18: =F18-F17 -> 465663000000 | H18: =234459542000000+528148000000 -> 234987690000000 | I18: =H18-H17 -> 38345015000000 | J18: =(G18/F18)-(I18/H18) -> -0.14449502
C19: 18 | D19: BBTN | E19: 2019 | F19: =25719874000000+2109852000000 -> 27829726000000 | G19: =F19-F18 -> 2906374000000 | H19: =249708993000000+487052000000 -> 250196045000000 | I19: =H19-H18 -> 15208355000000 | J19: =(G19/F19)-(I19/H19) -> 0.043648405
C20: 19 | D20: BBTN | E20: 2020 | F20: =25105780000000+2514607000000 -> 27620387000000 | G20: =F20-F19 -> -209339000000 | H20: =247053220000000+194678000000+70366000000 -> 247318264000000 | I20: =H20-H19 -> -2877781000000 | J20: =(G20/F20)-(I20/H20) -> 0.0040567941
C21: 20 | D21: BBTN | E21: 2021 | F21: =25794958000000+2362567000000 -> 28157525000000 | G21: =F21-F20 -> 537138000000 | H21: =260399531000000+31017000000+453517000000 -> 260884065000000 | I21: =H21-H20 -> 13565801000000 | J21: =(G21/F21)-(I21/H21) -> -0.032923167
C22: 21 | D22: BCAP | E22: 2017 | F22: 2386245000000 | H22: =237072000000+811042000000+184885000000+2640852000000-22184000000+555000000+305296000000-2714000000+169120000000-247000000 -> 4323677000000 | J22: =(G22/F22)-(I22/H22) -> 0
C23: 22 | D23: BCAP | E23: 2018 | F23: 2661759000000 | G23: =F23-F22 -> 275514000000 | H23: =119242000000+383410000000+369483000000+1917798000000-21885000000+519000000+135696000000-120000000+85125000000-2136000000 -> 2987132000000 | I23: =H23-H22 -> -1336545000000 | J23: =(G23/F23)-(I23/H23) -> 0.55094244
C24: 23 | D24: BCAP | E24: 2019 | F24: 2737029000000 | G24: =F24-F23 -> 75270000000 | H24: =169859000000+411428000000+191148000000+1763073000000-22167000000+8965000000+28439000000-1092000000+50897000000-2792000000 -> 2597758000000 | I24: =H24-H23 -> -389374000000 | J24: =(G24/F24)-(I24/H24) -> 0.1773891
C25: 24 | D25: BCAP | E25: 2020 | F25: 2657232000000 | G25: =F25-F24 -> -79797000000 | H25: =340136000000+680541000000+180993000000+1390494000000-15447000000+4768000000+89000000-12000000+13316000000-324000000 -> 2594554000000 | I25: =H25-H24 -> -3204000000 | J25: =(G25/F25)-(I25/H25) -> -0.028795227
C26: 25 | D26: BCAP | E26: 2021 | F26: 2735142000000 | G26: =F26-F25 -> 77910000000 | H26: =291740000000+474897000000+208289000000+1317356000000-13338000000+1654000000+3674000000+21610000000-7000000 -> 2305875000000 | I26: =H26-H25 -> -288679000000 | J26: =(G26/F26)-(I26/H26) -> 0.15367763
C27: 26 | D27: BDMN | E27: 2017 | F27: =13979824000000+5110441000000 -> 19090265000000 | H27: =413000000+103493000000+26080060000000+369488000000+1465000000+251502000000+2468000000+1483472000000+71783000000+93973723000000 -> 122337867000000 | J27: =(G27/F27)-(I27/H27) -> 0
C28: 27 | D28: BDMN | E28: 2018 | F28: =14241084000000+5158037000000 -> 19399121000000 | G28: =F28-F27 -> 308856000000 | H28: =54553000000+394538000000+28262631000000+240623000000+1679176000000+71783000000+93973723000000 -> 124677027000000 | I28: =H28-H27 -> 2339160000000 | J28: =(G28/F28)-(I28/H28) -> -0.0028406226
C29: 28 | D29: BDMN | E29: 2019 | F29: =14579398000000+3273414000000 -> 17852812000000 | G29: =F29-F28 -> -1546309000000 | H29: =159123000000+29624404000000+290517000000+862696000000+69720000000+106795782000000 -> 137802242000000 | I29: =H29-H28 -> 13125215000000 | J29: =(G29/F29)-(I29/H29) -> -0.18186106
C30: 29 | D30: BDMN | E30: 2020 | F30: =13723663000000+2271140000000 -> 15994803000000 | G30: =F30-F29 -> -1858009000000 | H30: =362482000000+22605362000000+246644000000+1592400000000+41365000000+103895653000000 -> 128743906000000 | I30: =H30-H29 -> -9058336000000 | J30: =(G30/F30)-(I30/H30) -> -0.045803956
C31: 30 | D31: BDMN | E31: 2021 | F31: =13747222000000+2413819000000 -> 16161041000000 | G31: =F31-F30 -> 166238000000 | H31: =187297000000+19958199000000+280613000000+2058574000000+30506000000+99935455000000 -> 122450644000000 | I31: =H31-H30 -> -6293262000000 | J31: =(G31/F31)-(I31/H31) -> 0.061680617
C32: 31 | D32: BFIN | E32: 2017 | F32: 4042317000000 | H32: =9435315000000+5739410000000+414127000000 -> 15588852000000 | J32: =(G32/F32)-(I32/H32) -> 0
C33: 32 | D33: BFIN | E33: 2018 | F33: 5018243000000 | G33: =F33-F32 -> 975926000000 | H33: =11357670000000+5922788000000+105000000+198271000000 -> 17478834000000 | I33: =H33-H32 -> 1889982000000 | J33: =(G33/F33)-(I33/H33) -> 0.086345883
C34: 33 | D34: BFIN | E34: 2019 | F34: 5240729000000 | G34: =F34-F33 -> 222486000000 | H34: =17395920000000+2105000000+153494000000 -> 17551519000000 | I34: =H34-H33 -> 72685000000 | J34: =(G34/F34)-(I34/H34) -> 0.038312017
C35: 34 | D35: BFIN | E35: 2020 | F35: 4569778000000 | G35: =F35-F34 -> -670951000000 | H35: =12678444000000+586000000+154904000000 -> 12833934000000 | I35: =H35-H34 -> -4717585000000 | J35: =(G35/F35)-(I35/H35) -> 0.22076328
C36: 35 | D36: BFIN | E36: 2021 | F36: 4122555000000 | G36: =F36-F35 -> -447223000000 | H36: =13676190000000+941000000+87089000000 -> 13764220000000 | I36: =H36-H35 -> 930286000000 | J36: =(G36/F36)-(I36/H36) -> -0.17606926
C37: 36 | D37: BNGA | E37: 2017 | F37: =12403379000000+4106571000000 -> 16509950000000 | H37: =280293000000+181405722000000+3710084000000+10936000000+4184965000000 -> 189592000000000 | J37: =(G37/F37)-(I37/H37) -> 0
C38: 37 | D38: BNGA | E38: 2018 | F38: =12011731000000+4794343000000 -> 16806074000000 | G38: =F38-F37 -> 296124000000 | H38: =1084759000000+180311277000000+2052802000000+1180000000+4462483000000 -> 187912501000000 | I38: =H38-H37 -> -1679499000000 | J38: =(G38/F38)-(I38/H38) -> 0.026557723
C39: 38 | D39: BNGA | E39: 2019 | F39: =12568018000000+4933747000000 -> 17501765000000 | G39: =F39-F38 -> 695691000000 | H39: =725478000000+184998140000000+3179370000000+3767071000000 -> 192670059000000 | I39: =H39-H38 -> 4757558000000 | J39: =(G39/F39)-(I39/H39) -> 0.01505699
C40: 39 | D40: BNGA | E40: 2020 | F40: =12470518000000+2853855000000 -> 15324373000000 | G40: =F40-F39 -> -2177392000000 | H40: =1359286000000+159851784000000+2977849000000+2022665000000 -> 166211584000000 | I40: =H40-H39 -> -26458475000000 | J40: =(G40/F40)-(I40/H40) -> 0.017098648
C41: 40 | D41: BNGA | E41: 2021 | F41: =13088860000000+5118392000000 -> 18207252000000 | G41: =F41-F40 -> 2882879000000 | H41: =909081000000+164089257000000+4388529000000+2564041000000 -> 171950908000000 | I41: =H41-H40 -> 5739324000000 | J41: =(G41/F41)-(I41/H41) -> 0.12495916
C42: 41 | D42: BNII | E42: 2017 | F42: 2729339000000 | H42: =200049000000+111809451000000+11488651000000+2747132000000 -> 126245283000000 | J42: =(G42/F42)-(I42/H42) -> 0
C43: 42 | D43: BNII | E43: 2018 | F43: 2266716000000 | G43: =F43-F42 -> -462623000000 | H43: =1289978000000+119909785000000+11161919000000+2813730000000 -> 135175412000000 | I43: =H43-H42 -> 8930129000000 | J43: =(G43/F43)-(I43/H43) -> -0.2701572
C44: 43 | D44: BNII | E44: 2019 | F44: 2580258000000 | G44: =F44-F43 -> 313542000000 | H44: =748480000000+10839431000000+109179337000000+1740388000000 -> 122507636000000 | I44: =H44-H43 -> -12667776000000 | J44: =(G44/F44)-(I44/H44) -> 0.22491973
C45: 44 | D45: BNII | E45: 2020 | F45: 2384529000000 | G45: =F45-F44 -> -195729000000 | H45: =1247872000000+93979899000000+8061654000000+1113285000000 -> 104402710000000 | I45: =H45-H44 -> -18104926000000 | J45: =(G45/F45)-(I45/H45) -> 0.091331453
C46: 45 | D46: BNII | E46: 2021 | F46: 2092225000000 | G46: =F46-F45 -> -292304000000 | H46: =560650000000+90675892000000+7826992000000+1664127000000 -> 100727661000000 | I46: =H46-H45 -> -3675049000000 | J46: =(G46/F46)-(I46/H46) -> -0.10322464
C47: 46 | D47: BNLI | E47: 2017 | F47: 8580185000000 | H47: =3569686000000+60174000000+89703197000000+317788000000 -> 93650845000000 | J47: =(G47/F47)-(I47/H47) -> 0
C48: 47 | D48: BNLI | E48: 2018 | F48: 7361481000000 | G48: =F48-F47 -> -1218704000000 | H48: =2730307000000+23084000000+98912371000000+297230000000 -> 101962992000000 | I48: =H48-H47 -> 8312147000000 | J48: =(G48/F48)-(I48/H48) -> -0.24707268
C49: 48 | D49: BNLI | E49: 2019 | F49: 7834473000000 | G49: =F49-F48 -> 472992000000 | H49: =1693465000000+104325105000000+757139000000 -> 106775709000000 | I49: =H49-H48 -> 4812717000000 | J49: =(G49/F49)-(I49/H49) -> 0.015300029
C50: 49 | D50: BNLI | E50: 2020 | F50: 8850419000000 | G50: =F50-F49 -> 1015946000000 | H50: =1434917000000+110698468000000+112440000000 -> 112245825000000 | I50: =H50-H49 -> 5470116000000 | J50: =(G50/F50)-(I50/H50) -> 0.066057365
C51: 50 | D51: BNLI | E51: 2021 | F51: 9848400000000 | G51: =F51-F50 -> 997981000000 | H51: =1927008000000+116875286000000+110592000000 -> 118912886000000 | I51: =H51-H50 -> 6667061000000 | J51: =(G51/F51)-(I51/H51) -> 0.045267562
C52: 51 | D52: ADMF | E52: 2017 | F52: 9136869000000 | H52: =16939102000000+8579855000000+370051000000+9571000000+204225000000+51533000000+85680000000 -> 26240017000000 | J52: =(G52/F52)-(I52/H52) -> 0
C53: 52 | D53: ADMF | E53: 2018 | F53: 10183755000000 | G53: =F53-F52 -> 1046886000000 | H53: =23258706000000+1698000000+4370502000000+240637000000+241000000+141036000000+55376000000 -> 28068196000000 | I53: =H53-H52 -> 1828179000000 | J53: =(G53/F53)-(I53/H53) -> 0.037666136
C54: 53 | D54: ADMF | E54: 2019 | F54: 11337726000000 | G54: =F54-F53 -> 1153971000000 | H54: =26799715000000+2479000000+2822205000000+290520000000+33000000+121222000000+345788000000 -> 30381962000000 | I54: =H54-H53 -> 2313766000000 | J54: =(G54/F54)-(I54/H54) -> 0.02562561
C55: 54 | D55: ADMF | E55: 2020 | F55: 9434745000000 | G55: =F55-F54 -> -1902981000000 | H55: =20151991000000+2449818000000+296000000+246644000000+153970000000+245768000000+1849000000 -> 23250336000000 | I55: =H55-H54 -> -7131626000000 | J55: =(G55/F55)-(I55/H55) -> 0.10503292
C56: 55 | D56: ADMF | E56: 2021 | F56: 8653143000000 | G56: =F56-F55 -> -781602000000 | H56: =16904868000000+2006000000+3051084000000+242000000+280613000000+99517000000+256444000000 -> 20594774000000 | I56: =H56-H55 -> -2655562000000 | J56: =(G56/F56)-(I56/H56) -> 0.038617696
C57: 56 | D57: BVIC | E57: 2017 | F57: =457677104000+416596112000 -> 874273216000 | H57: =15576687733000+117881394000 -> 15694569127000 | J57: =(G57/F57)-(I57/H57) -> 0
C58: 57 | D58: BVIC | E58: 2018 | F58: =459330574000+277296497000 -> 736627071000 | G58: =F58-F57 -> -137646145000 | H58: =16102771560000+164546909000 -> 16267318469000 | I58: =H58-H57 -> 572749342000 | J58: =(G58/F58)-(I58/H58) -> -0.2220686
C59: 58 | D59: BVIC | E59: 2019 | F59: =269148219000+362154830000 -> 631303049000 | G59: =F59-F58 -> -105324022000 | H59: =17054738234000+66543426000 -> 17121281660000 | I59: =H59-H58 -> 853963191000 | J59: =(G59/F59)-(I59/H59) -> -0.21671321
C60: 59 | D60: BVIC | E60: 2020 | F60: =189658449000+491005287000 -> 680663736000 | G60: =F60-F59 -> 49360687000 | H60: =14245976032000 -> 14245976032000 | I60: =H60-H59 -> -2875305628000 | J60: =(G60/F60)-(I60/H60) -> 0.27435129
C61: 60 | D61: BVIC | E61: 2021 | F61: =463654216000+453929343000 -> 917583559000 | G61: =F61-F60 -> 236919823000 | H61: =14786800658000 -> 14786800658000 | I61: =H61-H60 -> 540824626000 | J61: =(G61/F61)-(I61/H61) -> 0.2216249
C62: 61 | D62: CFIN | E62: 2017 | F62: 1399103951000 | H62: =2713270788000+5716045944000+1139565087000+50722720000 -> 9619604539000 | J62: =(G62/F62)-(I62/H62) -> 0
C63: 62 | D63: CFIN | E63: 2018 | F63: 1933912294000 | G63: =F63-F62 -> 534808343000 | H63: =1369068419000+8163519402000+736038827000+463999782000 -> 10732626430000 | I63: =H63-H62 -> 1113021891000 | J63: =(G63/F63)-(I63/H63) -> 0.17283767
C64: 63 | D64: CFIN | E64: 2019 | F64: 2164662845000 | G64: =F64-F63 -> 230750551000 | H64: =741211620000+9846112210000+695030908000+437440382000 -> 11719795120000 | I64: =H64-H63 -> 987168690000 | J64: =(G64/F64)-(I64/H64) -> 0.022367958
C65: 64 | D65: CFIN | E65: 2020 | F65: 1847954148000 | G65: =F65-F64 -> -316708697000 | H65: =433448957000+7175723377000+671273001000+438906799000 -> 8719352134000 | I65: =H65-H64 -> -3000442986000 | J65: =(G65/F65)-(I65/H65) -> 0.17272965
C66: 65 | D66: CFIN | E66: 2021 | F66: 1473648210000 | G66: =F66-F65 -> -374305938000 | H66: =202613282000+5661194488000+82252189000+462366165000 -> 6408426124000 | I66: =H66-H65 -> -2310926010000 | J66: =(G66/F66)-(I66/H66) -> 0.1066079
C67: 66 | D67: HDFA | E67: 2017 | F67: =897831573000 -> 897831573000 | H67: =3585278352000+45783117000+5282704000 -> 3636344173000 | J67: =(G67/F67)-(I67/H67) -> 0
C68: 67 | D68: HDFA | E68: 2018 | F68: 392508513000 | G68: =F68-F67 -> -505323060000 | H68: =1567514959000+32912364000+4780126000+11530914000 -> 1616738363000 | I68: =H68-H67 -> -2019605810000 | J68: =(G68/F68)-(I68/H68) -> -0.038234056
C69: 68 | D69: HDFA | E69: 2019 | F69: 263594827000 | G69: =F69-F68 -> -128913686000 | H69: =502697630000+49933215000+1139727000+69589000 -> 553840161000 | I69: =H69-H68 -> -1062898202000 | J69: =(G69/F69)-(I69/H69) -> 1.4300825
C70: 69 | D70: HDFA | E70: 2020 | F70: 100848335000 | G70: =F70-F69 -> -162746492000 | H70: =285098091000+45060540000+143563000+6792416000 -> 337094610000 | I70: =H70-H69 -> -216745551000 | J70: =(G70/F70)-(I70/H70) -> -0.97079334
C71: 70 | D71: HDFA | E71: 2021 | F71: 155080774000 | G71: =F71-F70 -> 54232439000 | H71: =980271775000+33803415000+405658000+11634137000 -> 1026114985000 | I71: =H71-H70 -> 689020375000 | J71: =(G71/F71)-(I71/H71) -> -0.3217801
C72: 71 | D72: MAYA | E72: 2017 | F72: =2600101000000+49025000000 -> 2649126000000 | H72: =55348547000000+36000000 -> 55348583000000 | J72: =(G72/F72)-(I72/H72) -> 0
C73: 72 | D73: MAYA | E73: 2018 | F73: =2969576000000+65932000000 -> 3035508000000 | G73: =F73-F72 -> 386382000000 | H73: =63586749000000 -> 63586749000000 | I73: =H73-H72 -> 8238166000000 | J73: =(G73/F73)-(I73/H73) -> -0.0022704792
C74: 73 | D74: MAYA | E74: 2019 | F74: =2919822000000+70296000000 -> 2990118000000 | G74: =F74-F73 -> -45390000000 | H74: =69067509000000 -> 69067509000000 | I74: =H74-H73 -> 5480760000000 | J74: =(G74/F74)-(I74/H74) -> -0.094533668
C75: 74 | D75: MAYA | E75: 2020 | F75: =170632000000+1478177000000 -> 1648809000000 | G75: =F75-F74 -> -1341309000000 | H75: 53905027000000 | I75: =H75-H74 -> -15162482000000 | J75: =(G75/F75)-(I75/H75) -> -0.53222034
C76: 75 | D76: MAYA | E76: 2021 | F76: =405803000000+1052597000000 -> 1458400000000 | G76: =F76-F75 -> -190409000000 | H76: =69529675000000+31622000000 -> 69561297000000 | I76: =H76-H75 -> 15656270000000 | J76: =(G76/F76)-(I76/H76) -> -0.35563177
C77: 76 | D77: PADI | E77: 2017 | F77: 72428138539 | H77: =3285281920+30733477830+1545878134+2667907025 -> 38232544909 | J77: =(G77/F77)-(I77/H77) -> 0
C78: 77 | D78: PADI | E78: 2018 | F78: 21821973059 | G78: =F78-F77 -> -50606165480 | H78: =7193233188+12154104114+25007486+2281592270 -> 21653937058 | I78: =H78-H77 -> -16578607851 | J78: =(G78/F78)-(I78/H78) -> -1.55343
C79: 78 | D79: PADI | E79: 2019 | F79: -88952931905 | G79: =F79-F78 -> -110774904964 | H79: =1648099099+10186825883+6706700+1279072820 -> 13120704502 | I79: =H79-H78 -> -8533232556 | J79: =(G79/F79)-(I79/H79) -> 1.8956843
C80: 79 | D80: PADI | E80: 2020 | F80: -61000620281 | G80: =F80-F79 -> 27952311624 | H80: =10066241244+10853868920+315047836+943953898 -> 22179111898 | I80: =H80-H79 -> 9058407396 | J80: =(G80/F80)-(I80/H80) -> -0.86665061
C81: 80 | D81: PADI | E81: 2021 | F81: -40817337259 | G81: =F81-F80 -> 20183283022 | H81: =4796274213+3811048583+13961026+325168967 -> 8946452789 | I81: =H81-H80 -> -13232659109 | J81: =(G81/F81)-(I81/H81) -> 0.98461743
C82: 81 | D82: PNLF | E82: 2017 | F82: 5103554000000 | H82: =83334000000+39616000000+10927000000 -> 133877000000 | J82: =(G82/F82)-(I82/H82) -> 0
C83: 82 | D83: PNLF | E83: 2018 | F83: 4404305000000 | G83: =F83-F82 -> -699249000000 | H83: =93329000000+73791000000+6227000000 -> 173347000000 | I83: =H83-H82 -> 39470000000 | J83: =(G83/F83)-(I83/H83) -> -0.38645848
C84: 83 | D84: PNLF | E84: 2019 | F84: 4519546000000 | G84: =F84-F83 -> 115241000000 | H84: =90249000000+113506000000+18926000000 -> 222681000000 | I84: =H84-H83 -> 49334000000 | J84: =(G84/F84)-(I84/H84) -> -0.19604726
C85: 84 | D85: PNLF | E85: 2020 | F85: 2981118000000 | G85: =F85-F84 -> -1538428000000 | H85: =88197000000+196420000000+35719000000 -> 320336000000 | I85: =H85-H84 -> 97655000000 | J85: =(G85/F85)-(I85/H85) -> -0.82090918
C86: 85 | D86: PNLF | E86: 2021 | F86: 2854892000000 | G86: =F86-F85 -> -126226000000 | H86: =45881000000+89495000000+190295000000+20527000000 -> 346198000000 | I86: =H86-H85 -> 25862000000 | J86: =(G86/F86)-(I86/H86) -> -0.11891685
C87: 86 | D87: SDRA | E87: 2017 | F87: =1086555000000+237560000000 -> 1324115000000 | H87: =18649664000000+53211000000 -> 18702875000000 | J87: =(G87/F87)-(I87/H87) -> 0
C88: 87 | D88: SDRA | E88: 2018 | F88: =1289827000000+257664000000 -> 1547491000000 | G88: =F88-F87 -> 223376000000 | H88: =22294572000000+314239000000 -> 22608811000000 | I88: =H88-H87 -> 3905936000000 | J88: =(G88/F88)-(I88/H88) -> -0.028414468
C89: 88 | D89: SDRA | E89: 2019 | F89: =1113085000000+331824000000 -> 1444909000000 | G89: =F89-F88 -> -102582000000 | H89: =26429707000000+640049000000 -> 27069756000000 | I89: =H89-H88 -> 4460945000000 | J89: =(G89/F89)-(I89/H89) -> -0.2357899
C90: 89 | D90: SDRA | E90: 2020 | F90: =1247061000000+256382000000 -> 1503443000000 | G90: =F90-F89 -> 58534000000 | H90: =29579069000000+666193000000 -> 30245262000000 | I90: =H90-H89 -> 3175506000000 | J90: =(G90/F90)-(I90/H90) -> -0.066058548
C91: 90 | D91: SDRA | E91: 2021 | F91: =1513182000000+227773000000 -> 1740955000000 | G91: =F91-F90 -> 237512000000 | H91: =33429580000000+331593000000 -> 33761173000000 | I91: =H91-H90 -> 3515911000000 | J91: =(G91/F91)-(I91/H91) -> 0.032285607
C92: 91 | D92: SMMA | E92: 2017 | F92: 32883257000000 | H92: =1520255000000+3567000000+3979434000000+726170000000+18365482000000+185015000000+475422000000+845229000000 -> 26100574000000 | J92: =(G92/F92)-(I92/H92) -> 0
C93: 92 | D93: SMMA | E93: 2018 | F93: 37377268000000 | G93: =F93-F92 -> 4494011000000 | H93: =1735809000000+2295000000+4415833000000+960829000000+19214056000000+243250000000+1058913000000+1241709000000 -> 28872694000000 | I93: =H93-H92 -> 2772120000000 | J93: =(G93/F93)-(I93/H93) -> 0.024221977
C94: 93 | D94: SMMA | E94: 2019 | F94: 41919335000000 | G94: =F94-F93 -> 4542067000000 | H94: =2783341000000+922000000+3996536000000+1118050000000+21314497000000+265212000000+503637000000+1785782000000 -> 31767977000000 | I94: =H94-H93 -> 2895283000000 | J94: =(G94/F94)-(I94/H94) -> 0.017214141
C95: 94 | D95: SMMA | E95: 2020 | F95: 38259352000000 | G95: =F95-F94 -> -3659983000000 | H95: =2229745000000+526000000+3700987000000+1013362000000+18878373000000+153577000000+976673000000+1476148000000 -> 28429391000000 | I95: =H95-H94 -> -3338586000000 | J95: =(G95/F95)-(I95/H95) -> 0.021771872
C96: 95 | D96: SMMA | E96: 2021 | F96: 38533098000000 | G96: =F96-F95 -> 273746000000 | H96: =2042898000000+300613000000+2816748000000+1889817000000+16067805000000+247165000000+385163000000+1569255000000 -> 25319464000000 | I96: =H96-H95 -> -3109927000000 | J96: =(G96/F96)-(I96/H96) -> 0.1299317
C97: 96 | D97: WOMF | E97: 2017 | F97: 2154431000000 | H97: =6796231000000+57981000000 -> 6854212000000 | J97: =(G97/F97)-(I97/H97) -> 0
C98: 97 | D98: WOMF | E98: 2018 | F98: 2616144000000 | G98: =F98-F97 -> 461713000000 | H98: =7243068000000+72344000000 -> 7315412000000 | I98: =H98-H97 -> 461200000000 | J98: =(G98/F98)-(I98/H98) -> 0.1134411
C99: 98 | D99: WOMF | E99: 2019 | F99: 2643687000000 | G99: =F99-F98 -> 27543000000 | H99: =7205215000000+46574000000 -> 7251789000000 | I99: =H99-H98 -> -63623000000 | J99: =(G99/F99)-(I99/H99) -> 0.019191826
C100: 99 | D100: WOMF | E100: 2020 | F100: 2000850000000 | G100: =F100-F99 -> -642837000000 | H100: =4280120000000+15070000000+23371000000+42988000000 -> 4361549000000 | I100: =H100-H99 -> -2890240000000 | J100: =(G100/F100)-(I100/H100) -> 0.3413817
...

Sheet Ch In earning
A1: No | B1: Kode Emiten | C1: Tahun | D1: Earning(t) | E1: Earning(t-1) | F1: Average Total Asset(t-1) | G1: Average Total Aset | H1: Ch in Earning
A2: 1 | B2: ASTJ | C2: 2017 | D2: 35616934582 | G2: 436601081601 | H2: =(D2/G2)-(E2/F2) -> #DIV/0!
A3: 2 | B3: ASTJ | C3: 2018 | D3: 10084095926 | E3: =D2 -> 35616934582 | F3: =G2 -> 436601081601 | G3: 4.6227375e+11 | H3: =(D3/G3)-(E3/F3) -> -0.05976363
A4: 3 | B4: ASTJ | C4: 2019 | D4: 2872717734 | E4: =D3 -> 10084095926 | F4: =G3 -> 4.6227375e+11 | G4: 4.6305483e+11 | H4: =(D4/G4)-(E4/F4) -> -0.015610283
A5: 4 | B5: ASTJ | C5: 2020 | D5: 171517965 | E5: =D4 -> 2872717734 | F5: =G4 -> 4.6305483e+11 | G5: 406717116516 | H5: =(D5/G5)-(E5/F5) -> -0.0057821261
A6: 5 | B6: ASTJ | C6: 2021 | D6: 718774542 | E6: =D5 -> 171517965 | F6: =G5 -> 406717116516 | G6: 4.4680808e+11 | H6: =(D6/G6)-(E6/F6) -> 0.0011869743
A7: 6 | B7: ASMI | C7: 2017 | D7: 61141112373 | G7: 7.3807072e+11 | H7: =(D7/G7)-(E7/F7) -> #DIV/0!
A8: 7 | B8: ASMI | C8: 2018 | D8: 64625986348 | E8: =D7 -> 61141112373 | F8: =G7 -> 7.3807072e+11 | G8: 914178422228 | H8: =(D8/G8)-(E8/F8) -> -0.012146129
A9: 8 | B9: ASMI | C9: 2019 | D9: 10700535196 | E9: =D8 -> 64625986348 | F9: =G8 -> 914178422228 | G9: 9.7277701e+11 | H9: =(D9/G9)-(E9/F9) -> -0.059692981
A10: 9 | B10: ASMI | C10: 2020 | D10: -86844513059 | E10: =D9 -> 10700535196 | F10: =G9 -> 9.7277701e+11 | G10: 9.833396e+11 | H10: =(D10/G10)-(E10/F10) -> -0.099315879
A11: 10 | B11: ASMI | C11: 2021 | D11: 19429664571 | E11: =D10 -> -86844513059 | F11: =G10 -> 9.833396e+11 | G11: 986040658507 | H11: =(D11/G11)-(E11/F11) -> 0.10802062
A12: 11 | B12: BBNI | C12: 2017 | D12: 15617639000000 | G12: 656180982000000 | H12: =(D12/G12)-(E12/F12) -> #DIV/0!
A13: 12 | B13: BBNI | C13: 2018 | D13: 14236252000000 | E13: =D12 -> 15617639000000 | F13: =G12 -> 656180982000000 | G13: 758951047500000 | H13: =(D13/G13)-(E13/F13) -> -0.0050430101
A14: 13 | B14: BBNI | C14: 2019 | D14: 18383939000000 | E14: =D13 -> 14236252000000 | F14: =G13 -> 758951047500000 | G14: 827088609500000 | H14: =(D14/G14)-(E14/F14) -> 0.0034694907
A15: 14 | B15: BBNI | C15: 2020 | D15: 4192722000000 | E15: =D14 -> 18383939000000 | F15: =G14 -> 827088609500000 | G15: 868471316500000 | H15: =(D15/G15)-(E15/F15) -> -0.017399587
A16: 15 | B16: BBNI | C16: 2021 | D16: 11722436000000 | E16: =D15 -> 4192722000000 | F16: =G15 -> 868471316500000 | G16: 928087558500000 | H16: =(D16/G16)-(E16/F16) -> 0.0078030401
A17: 16 | B17: BBTN | C17: 2017 | D17: 3056679000000 | G17: 237766873000000 | H17: =(D17/G17)-(E17/F17) -> #DIV/0!
A18: 17 | B18: BBTN | C18: 2018 | D18: 2782507000000 | E18: =D17 -> 3056679000000 | F18: =G17 -> 237766873000000 | G18: 283900730500000 | H18: =(D18/G18)-(E18/F18) -> -0.0030547959
A19: 18 | B19: BBTN | C19: 2019 | D19: 557332000000 | E19: =D18 -> 2782507000000 | F19: =G18 -> 283900730500000 | G19: 309106511000000 | H19: =(D19/G19)-(E19/F19) -> -0.0079979438
A20: 19 | B20: BBTN | C20: 2020 | D20: 2352711000000 | E20: =D19 -> 557332000000 | F20: =G19 -> 309106511000000 | G20: 336492617000000 | H20: =(D20/G20)-(E20/F20) -> 0.0051888232
A21: 20 | B21: BBTN | C21: 2021 | D21: 1418802000000 | E21: =D20 -> 2352711000000 | F21: =G20 -> 336492617000000 | G21: 366538358500000 | H21: =(D21/G21)-(E21/F21) -> -0.0031210506
A22: 21 | B22: BCAP | C22: 2017 | D22: -779107000000 | G22: 21049641000000 | H22: =(D22/G22)-(E22/F22) -> #DIV/0!
A23: 22 | B23: BCAP | C23: 2018 | D23: 103545000000 | E23: =D22 -> -779107000000 | F23: =G22 -> 21049641000000 | G23: 19322993500000 | H23: =(D23/G23)-(E23/F23) -> 0.042371482
A24: 23 | B24: BCAP | C24: 2019 | D24: 93737000000 | E24: =D23 -> 103545000000 | F24: =G23 -> 19322993500000 | G24: 18573864500000 | H24: =(D24/G24)-(E24/F24) -> -0.0003119268
A25: 24 | B25: BCAP | C25: 2020 | D25: 63228000000 | E25: =D24 -> 93737000000 | F25: =G24 -> 18573864500000 | G25: 18743275500000 | H25: =(D25/G25)-(E25/F25) -> -0.0016733451
A26: 25 | B26: BCAP | C26: 2021 | D26: 143486000000 | E26: =D25 -> 63228000000 | F26: =G25 -> 18743275500000 | G26: 20377757000000 | H26: =(D26/G26)-(E26/F26) -> 0.0036679351
A27: 26 | B27: BDMN | C27: 2017 | D27: 3708950000000 | G27: 176346806500000 | H27: =(D27/G27)-(E27/F27) -> #DIV/0!
A28: 27 | B28: BDMN | C28: 2018 | D28: 4126533000000 | E28: =D27 -> 3708950000000 | F28: =G27 -> 176346806500000 | G28: 182509640500000 | H28: =(D28/G28)-(E28/F28) -> 0.0015778095
A29: 28 | B29: BDMN | C29: 2019 | D29: 4330487000000 | E29: =D28 -> 4126533000000 | F29: =G28 -> 182509640500000 | G29: 190148079500000 | H29: =(D29/G29)-(E29/F29) -> 0.00016434198
A30: 29 | B30: BDMN | C30: 2020 | D30: 1382263000000 | E30: =D29 -> 4330487000000 | F30: =G29 -> 190148079500000 | G30: 197212019000000 | H30: =(D30/G30)-(E30/F30) -> -0.015765267
A31: 30 | B31: BDMN | C31: 2021 | D31: =1892628000000 -> 1892628000000 | E31: =D30 -> 1382263000000 | F31: =G30 -> 197212019000000 | G31: 196564883000000 | H31: =(D31/G31)-(E31/F31) -> 0.0026194953
A32: 31 | B32: BFIN | C32: 2017 | D32: 1158370000000 | G32: 14479764500000 | H32: =(D32/G32)-(E32/F32) -> #DIV/0!
A33: 32 | B33: BFIN | C33: 2018 | D33: 1538957000000 | E33: =D32 -> 1158370000000 | F33: =G32 -> 14479764500000 | G33: 17800289000000 | H33: =(D33/G33)-(E33/F33) -> 0.0064576254
A34: 33 | B34: BFIN | C34: 2019 | D34: 609633000000 | E34: =D33 -> 1538957000000 | F34: =G33 -> 17800289000000 | G34: 19103469000000 | H34: =(D34/G34)-(E34/F34) -> -0.054544693
A35: 34 | B35: BFIN | C35: 2020 | D35: 827932000000 | E35: =D34 -> 609633000000 | F35: =G34 -> 19103469000000 | G35: 17145082000000 | H35: =(D35/G35)-(E35/F35) -> 0.016377604
A36: 35 | B36: BFIN | C36: 2021 | D36: 1197691000000 | E36: =D35 -> 827932000000 | F36: =G35 -> 17145082000000 | G36: 15418135000000 | H36: =(D36/G36)-(E36/F36) -> 0.0293909
A37: 36 | B37: BNGA | C37: 2017 | D37: 2966276000000 | G37: 253938591500000 | H37: =(D37/G37)-(E37/F37) -> #DIV/0!
A38: 37 | B38: BNGA | C38: 2018 | D38: 3202980000000 | E38: =D37 -> 2966276000000 | F38: =G37 -> 253938591500000 | G38: 266543476500000 | H38: =(D38/G38)-(E38/F38) -> 0.00033565023
A39: 38 | B39: BNGA | C39: 2019 | D39: 4387474000000 | E39: =D38 -> 3202980000000 | F39: =G38 -> 266543476500000 | G39: 270624362500000 | H39: =(D39/G39)-(E39/F39) -> 0.004195687
A40: 39 | B40: BNGA | C40: 2020 | D40: 3289807000000 | E40: =D39 -> 4387474000000 | F40: =G39 -> 270624362500000 | G40: 277705416000000 | H40: =(D40/G40)-(E40/F40) -> -0.004366022
A41: 40 | B41: BNGA | C41: 2021 | D41: 3415074000000 | E41: =D40 -> 3289807000000 | F41: =G40 -> 277705416000000 | G41: 295865282500000 | H41: =(D41/G41)-(E41/F41) -> -0.00030372568
A42: 41 | B42: BNII | C42: 2017 | D42: 1892096000000 | G42: 169966196500000 | H42: =(D42/G42)-(E42/F42) -> #DIV/0!
A43: 42 | B43: BNII | C43: 2018 | D43: 2701100000000 | E43: =D42 -> 1892096000000 | F43: =G42 -> 169966196500000 | G43: 175393174500000 | H43: =(D43/G43)-(E43/F43) -> 0.0042680672
A44: 43 | B44: BNII | C44: 2019 | D44: 2163127000000 | E44: =D43 -> 2701100000000 | F44: =G43 -> 175393174500000 | G44: 173307844000000 | H44: =(D44/G44)-(E44/F44) -> -0.0029188429
A45: 44 | B45: BNII | C45: 2020 | D45: 1613692000000 | E45: =D44 -> 2163127000000 | F45: =G44 -> 173307844000000 | G45: 171153621000000 | H45: =(D45/G45)-(E45/F45) -> -0.0030530891
A46: 45 | B46: BNII | C46: 2021 | D46: 1754762000000 | E46: =D45 -> 1613692000000 | F46: =G45 -> 171153621000000 | G46: 170991444000000 | H46: =(D46/G46)-(E46/F46) -> 0.00083395434
A47: 46 | B47: BNLI | C47: 2017 | D47: 725686000000 | G47: 156927941000000 | H47: =(D47/G47)-(E47/F47) -> #DIV/0!
A48: 47 | B48: BNLI | C48: 2018 | D48: 941322000000 | E48: =D47 -> 725686000000 | F48: =G47 -> 156927941000000 | G48: 150610618000000 | H48: =(D48/G48)-(E48/F48) -> 0.0016257112
A49: 48 | B49: BNLI | C49: 2019 | D49: 1585415000000 | E49: =D48 -> 941322000000 | F49: =G48 -> 150610618000000 | G49: 157172062500000 | H49: =(D49/G49)-(E49/F49) -> 0.0038370924
A50: 49 | B50: BNLI | C50: 2020 | D50: 1215517000000 | E50: =D49 -> 1585415000000 | F50: =G49 -> 157172062500000 | G50: 179588678000000 | H50: =(D50/G50)-(E50/F50) -> -0.0033187911
A51: 50 | B51: BNLI | C51: 2021 | D51: 1407057000000 | E51: =D50 -> 1215517000000 | F51: =G50 -> 179588678000000 | G51: 216052569500000 | H51: =(D51/G51)-(E51/F51) -> -0.00025577094
A52: 51 | B52: ADMF | C52: 2017 | D52: 1266466000000 | G52: 28568018500000 | H52: =(D52/G52)-(E52/F52) -> #DIV/0!
A53: 52 | B53: ADMF | C53: 2018 | D53: 1987284000000 | E53: =D52 -> 1266466000000 | F53: =G52 -> 28568018500000 | G53: 30494687000000 | H53: =(D53/G53)-(E53/F53) -> 0.020836603
A54: 53 | B54: ADMF | C54: 2019 | D54: 1958596000000 | E54: =D53 -> 1987284000000 | F54: =G53 -> 30494687000000 | G54: 33306647000000 | H54: =(D54/G54)-(E54/F54) -> -0.0063632459
A55: 54 | B55: ADMF | C55: 2020 | D55: 1015111000000 | E55: =D54 -> 1958596000000 | F55: =G54 -> 33306647000000 | G55: 32173683000000 | H55: =(D55/G55)-(E55/F55) -> -0.027253986
A56: 55 | B56: ADMF | C56: 2021 | D56: 1474731000000 | E56: =D55 -> 1015111000000 | F56: =G55 -> 32173683000000 | G56: 26478199000000 | H56: =(D56/G56)-(E56/F56) -> 0.024145074
A57: 56 | B57: BVIC | C57: 2017 | D57: 220075054000 | G57: 27412794965500 | H57: =(D57/G57)-(E57/F57) -> #DIV/0!
A58: 57 | B58: BVIC | C58: 2018 | D58: -40335898000 | E58: =D57 -> 220075054000 | F58: =G57 -> 27412794965500 | G58: 29498961992500 | H58: =(D58/G58)-(E58/F58) -> -0.009395554
A59: 58 | B59: BVIC | C59: 2019 | D59: 81245098000 | E59: =D58 -> -40335898000 | F59: =G58 -> 29498961992500 | G59: 30314387069500 | H59: =(D59/G59)-(E59/F59) -> 0.0040474505
A60: 59 | B60: BVIC | C60: 2020 | D60: -152008563000 | E60: =D59 -> 81245098000 | F60: =G59 -> 30314387069500 | G60: 28338933137000 | H60: =(D60/G60)-(E60/F60) -> -0.0080440318
A61: 60 | B61: BVIC | C61: 2021 | D61: -186479141000 | E61: =D60 -> -152008563000 | F61: =G60 -> 28338933137000 | G61: 25584275258500 | H61: =(D61/G61)-(E61/F61) -> -0.0019248706
A62: 61 | B62: CFIN | C62: 2017 | D62: 230599795000 | G62: 8317518837000 | H62: =(D62/G62)-(E62/F62) -> #DIV/0!
A63: 62 | B63: CFIN | C63: 2018 | D63: 317594433000 | E63: =D62 -> 230599795000 | F63: =G62 -> 8317518837000 | G63: 10497063221500 | H63: =(D63/G63)-(E63/F63) -> 0.0025309617
A64: 63 | B64: CFIN | C64: 2019 | D64: 358556894000 | E64: =D63 -> 317594433000 | F64: =G63 -> 10497063221500 | G64: 11610378593000 | H64: =(D64/G64)-(E64/F64) -> 0.00062689522
A65: 64 | B65: CFIN | C65: 2020 | D65: 51999536000 | E65: =D64 -> 358556894000 | F65: =G64 -> 11610378593000 | G65: 11517467142500 | H65: =(D65/G65)-(E65/F65) -> -0.026367605
A66: 65 | B66: CFIN | C66: 2021 | D66: 60930309000 | E66: =D65 -> 51999536000 | F66: =G65 -> 11517467142500 | G66: 9020680117500 | H66: =(D66/G66)-(E66/F66) -> 0.0022396726
A67: 66 | B67: HDFA | C67: 2017 | D67: 11425651000 | G67: 3727293518000 | H67: =(D67/G67)-(E67/F67) -> #DIV/0!
A68: 67 | B68: HDFA | C68: 2018 | D68: -292565818000 | E68: =D67 -> 11425651000 | F68: =G67 -> 3727293518000 | G68: 3055761564500 | H68: =(D68/G68)-(E68/F68) -> -0.09880776
A69: 68 | B69: HDFA | C69: 2019 | D69: -198213285000 | E69: =D68 -> -292565818000 | F69: =G68 -> 3055761564500 | G69: 1726090971500 | H69: =(D69/G69)-(E69/F69) -> -0.019091268
A70: 69 | B70: HDFA | C70: 2020 | D70: -84433201000 | E70: =D69 -> -198213285000 | F70: =G69 -> 1726090971500 | G70: 981752011500 | H70: =(D70/G70)-(E70/F70) -> 0.028831051
A71: 70 | B71: HDFA | C71: 2021 | D71: 34775555000 | E71: =D70 -> -84433201000 | F71: =G70 -> 981752011500 | G71: 711383640000 | H71: =(D71/G71)-(E71/F71) -> 0.13488696
A72: 71 | B72: MAYA | C72: 2017 | D72: 689658000000 | G72: 67792336189000 | H72: =(D72/G72)-(E72/F72) -> #DIV/0!
A73: 72 | B73: MAYA | C73: 2018 | D73: 517896000000 | E73: =D72 -> 689658000000 | F73: =G72 -> 67792336189000 | G73: 80858731500000 | H73: =(D73/G73)-(E73/F73) -> -0.0037681485
A74: 73 | B74: MAYA | C74: 2019 | D74: 556056000000 | E74: =D73 -> 517896000000 | F74: =G73 -> 80858731500000 | G74: 90190362000000 | H74: =(D74/G74)-(E74/F74) -> -0.00023958892
A75: 74 | B75: MAYA | C75: 2020 | D75: 224838000000 | E75: =D74 -> 556056000000 | F75: =G74 -> 90190362000000 | G75: 92963428000000 | H75: =(D75/G75)-(E75/F75) -> -0.0037467954
A76: 75 | B76: MAYA | C76: 2021 | D76: 78069000000 | E76: =D75 -> 224838000000 | F76: =G75 -> 92963428000000 | G76: 105811105000000 | H76: =(D76/G76)-(E76/F76) -> -0.0016807492
A77: 76 | B77: PADI | C77: 2017 | D77: 39557537456 | G77: 4.8990097e+11 | H77: =(D77/G77)-(E77/F77) -> #DIV/0!
A78: 77 | B78: PADI | C78: 2018 | D78: 38907989105 | E78: =D77 -> 39557537456 | F78: =G77 -> 4.8990097e+11 | G78: 5.2562413e+11 | H78: =(D78/G78)-(E78/F78) -> -0.0067235307
A79: 78 | B79: PADI | C79: 2019 | D79: -141377648692 | E79: =D78 -> 38907989105 | F79: =G78 -> 5.2562413e+11 | G79: 480864783071 | H79: =(D79/G79)-(E79/F79) -> -0.36802953
A80: 79 | B80: PADI | C80: 2020 | D80: -87861108382 | E80: =D79 -> -141377648692 | F80: =G79 -> 480864783071 | G80: 376502006661 | H80: =(D80/G80)-(E80/F80) -> 0.060645482
A81: 80 | B81: PADI | C81: 2021 | D81: -52857656404 | E81: =D80 -> -87861108382 | F81: =G80 -> 376502006661 | G81: 300598582653 | H81: =(D81/G81)-(E81/F81) -> 0.057520258
A82: 81 | B82: PNLF | C82: 2017 | D82: 1683031000000 | G82: 25722439000000 | H82: =(D82/G82)-(E82/F82) -> #DIV/0!
A83: 82 | B83: PNLF | C83: 2018 | D83: 1957051000000 | E83: =D82 -> 1683031000000 | F83: =G82 -> 25722439000000 | G83: 27362022500000 | H83: =(D83/G83)-(E83/F83) -> 0.0060938952
A84: 83 | B84: PNLF | C84: 2019 | D84: 2286628000000 | E84: =D83 -> 1957051000000 | F84: =G83 -> 27362022500000 | G84: 29271055500000 | H84: =(D84/G84)-(E84/F84) -> 0.0065947279
A85: 84 | B85: PNLF | C85: 2020 | D85: 2956963000000 | E85: =D84 -> 2286628000000 | F85: =G84 -> 29271055500000 | G85: 31335553500000 | H85: =(D85/G85)-(E85/F85) -> 0.016245391
A86: 85 | B86: PNLF | C86: 2021 | D86: 1079187000000 | E86: =D85 -> 2956963000000 | F86: =G85 -> 31335553500000 | G86: 32787151000000 | H86: =(D86/G86)-(E86/F86) -> -0.061449537
A87: 86 | B87: SDRA | C87: 2017 | D87: 431708000000 | G87: 24858569000000 | H87: =(D87/G87)-(E87/F87) -> #DIV/0!
A88: 87 | B88: SDRA | C88: 2018 | D88: 542184000000 | E88: =D87 -> 431708000000 | F88: =G87 -> 24858569000000 | G88: 28359098500000 | H88: =(D88/G88)-(E88/F88) -> 0.0017519535
A89: 88 | B89: SDRA | C89: 2019 | D89: 483836000000 | E89: =D88 -> 542184000000 | F89: =G88 -> 28359098500000 | G89: 33286064500000 | H89: =(D89/G89)-(E89/F89) -> -0.0045828277
A90: 89 | B90: SDRA | C90: 2020 | D90: 541826000000 | E90: =D89 -> 483836000000 | F90: =G89 -> 33286064500000 | G90: 37497187500000 | H90: =(D90/G90)-(E90/F90) -> -8.591549e-05
A91: 90 | B91: SDRA | C91: 2021 | D91: 627223000000 | E91: =D90 -> 541826000000 | F91: =G90 -> 37497187500000 | G91: 40927755000000 | H91: =(D91/G91)-(E91/F91) -> 0.00087534888
A92: 91 | B92: SMMA | C92: 2017 | D92: 2743483000000 | G92: 81540954500000 | H92: =(D92/G92)-(E92/F92) -> #DIV/0!
A93: 92 | B93: SMMA | C93: 2018 | D93: 2150833000000 | E93: =D92 -> 2743483000000 | F93: =G92 -> 81540954500000 | G93: 94875119500000 | H93: =(D93/G93)-(E93/F93) -> -0.010975313
A94: 93 | B94: SMMA | C94: 2019 | D94: 3731875000000 | E94: =D93 -> 2150833000000 | F94: =G93 -> 94875119500000 | G94: 100144154000000 | H94: =(D94/G94)-(E94/F94) -> 0.014594883
A95: 94 | B95: SMMA | C95: 2020 | D95: 157949000000 | E95: =D94 -> 3731875000000 | F95: =G94 -> 100144154000000 | G95: 104040542000000 | H95: =(D95/G95)-(E95/F95) -> -0.035746882
A96: 95 | B96: SMMA | C96: 2021 | D96: 559660000000 | E96: =D95 -> 157949000000 | F96: =G95 -> 104040542000000 | G96: 112983113000000 | H96: =(D96/G96)-(E96/F96) -> 0.0034353351
A97: 96 | B97: WOMF | C97: 2017 | D97: 174513000000 | G97: 7208324000000 | H97: =(D97/G97)-(E97/F97) -> #DIV/0!
A98: 97 | B98: WOMF | C98: 2018 | D98: 235812000000 | E98: =D97 -> 174513000000 | F98: =G97 -> 7208324000000 | G98: 8286519500000 | H98: =(D98/G98)-(E98/F98) -> 0.0042473762
A99: 98 | B99: WOMF | C99: 2019 | D99: 263323000000 | E99: =D98 -> 235812000000 | F99: =G98 -> 8286519500000 | G99: 8549238500000 | H99: =(D99/G99)-(E99/F99) -> 0.0023434515
A100: 99 | B100: WOMF | C100: 2020 | D100: 74130000000 | E100: =D99 -> 263323000000 | F100: =G99 -> 8549238500000 | G100: 6777436000000 | H100: =(D100/G100)-(E100/F100) -> -0.01986299
...

Sheet Financial Performance
A1: No | B1: Kode Emiten | C1: Tahun | D1: Ch Receivable | E1: Ch in cash sales | F1: Ch in earning | G1: Financial Performance
A2: 1 | B2: ASTJ | C2: 2017 | D2: ='ch receivable'!G2 -> #DIV/0! | E2: ='ch in cash sales'!J2 -> 0 | F2: ='Ch In earning'!H2 -> #DIV/0! | G2: =D2+E2+F2 -> #DIV/0!
A3: 2 | B3: ASTJ | C3: 2018 | D3: ='ch receivable'!G3 -> 0.008658414 | E3: ='ch in cash sales'!J3 -> -0.10477379 | F3: ='Ch In earning'!H3 -> -0.05976363 | G3: =D3+E3+F3 -> -0.15587901
A4: 3 | B4: ASTJ | C4: 2019 | D4: ='ch receivable'!G4 -> -0.017193492 | E4: ='ch in cash sales'!J4 -> 0.010790615 | F4: ='Ch In earning'!H4 -> -0.015610283 | G4: =D4+E4+F4 -> -0.02201316
A5: 4 | B5: ASTJ | C5: 2020 | D5: ='ch receivable'!G5 -> 0.012917324 | E5: ='ch in cash sales'!J5 -> -0.47619244 | F5: ='Ch In earning'!H5 -> -0.0057821261 | G5: =D5+E5+F5 -> -0.46905724
A6: 5 | B6: ASTJ | C6: 2021 | D6: ='ch receivable'!G6 -> 0.058677032 | E6: ='ch in cash sales'!J6 -> -0.12467227 | F6: ='Ch In earning'!H6 -> 0.0011869743 | G6: =D6+E6+F6 -> -0.064808266
A7: 6 | B7: ASMI | C7: 2017 | D7: ='ch receivable'!G7 -> #DIV/0! | E7: ='ch in cash sales'!J7 -> 0 | F7: ='Ch In earning'!H7 -> #DIV/0! | G7: =D7+E7+F7 -> #DIV/0!
A8: 7 | B8: ASMI | C8: 2018 | D8: ='ch receivable'!G8 -> 0.044723841 | E8: ='ch in cash sales'!J8 -> -0.10338084 | F8: ='Ch In earning'!H8 -> -0.012146129 | G8: =D8+E8+F8 -> -0.070803131
A9: 8 | B9: ASMI | C9: 2019 | D9: ='ch receivable'!G9 -> -0.0048834762 | E9: ='ch in cash sales'!J9 -> 0.11139192 | F9: ='Ch In earning'!H9 -> -0.059692981 | G9: =D9+E9+F9 -> 0.04681546
A10: 9 | B10: ASMI | C10: 2020 | D10: ='ch receivable'!G10 -> 0.088460707 | E10: ='ch in cash sales'!J10 -> -0.47814394 | F10: ='Ch In earning'!H10 -> -0.099315879 | G10: =D10+E10+F10 -> -0.48899911
A11: 10 | B11: ASMI | C11: 2021 | D11: ='ch receivable'!G11 -> -0.060512599 | E11: ='ch in cash sales'!J11 -> 1.6495227 | F11: ='Ch In earning'!H11 -> 0.10802062 | G11: =D11+E11+F11 -> 1.6970307
A12: 11 | B12: BBNI | C12: 2017 | D12: ='ch receivable'!G12 -> #DIV/0! | E12: ='ch in cash sales'!J12 -> 0 | F12: ='Ch In earning'!H12 -> #DIV/0! | G12: =D12+E12+F12 -> #DIV/0!
A13: 12 | B13: BBNI | C13: 2018 | D13: ='ch receivable'!G13 -> 0.095462149 | E13: ='ch in cash sales'!J13 -> -0.040578506 | F13: ='Ch In earning'!H13 -> -0.0050430101 | G13: =D13+E13+F13 -> 0.049840633
... A67: 66 | B67: HDFA | C67: 2017 | D67: ='ch receivable'!G67 -> #DIV/0! | E67: ='ch in cash sales'!J67 -> 0 | F67: ='Ch In earning'!H67 -> #DIV/0! | G67: =D67+E67+F67 -> #DIV/0!
A68: 67 | B68: HDFA | C68: 2018 | D68: =-'ch receivable'!G68 -> 0.66091734 | E68: =-'ch in cash sales'!J68 -> 0.038234056 | F68: =-'Ch In earning'!H68 -> 0.09880776 | G68: =D68+E68+F68 -> 0.79795916
A69: 68 | B69: HDFA | C69: 2019 | D69: =-'ch receivable'!G69 -> 0.61578342 | E69: ='ch in cash sales'!J69 -> 1.4300825 | F69: ='Ch In earning'!H69 -> -0.019091268 | G69: =D69+E69+F69 -> 2.0267747
A70: 69 | B70: HDFA | C70: 2020 | D70: =-'ch receivable'!G70 -> 0.22077424 | E70: =-'ch in cash sales'!J70 -> 0.97079334 | F70: ='Ch In earning'!H70 -> 0.028831051 | G70: =D70+E70+F70 -> 1.2203986
A71: 70 | B71: HDFA | C71: 2021 | D71: ='ch receivable'!G71 -> 0.67156344 | E71: =-'ch in cash sales'!J71 -> 0.3217801 | F71: ='Ch In earning'!H71 -> 0.13488696 | G71: =D71+E71+F71 -> 1.1282305
A72: 71 | B72: MAYA | C72: 2017 | D72: ='ch receivable'!G72 -> #DIV/0! | E72: ='ch in cash sales'!J72 -> 0 | F72: ='Ch In earning'!H72 -> #DIV/0! | G72: =D72+E72+F72 -> #DIV/0!
A73: 72 | B73: MAYA | C73: 2018 | D73: ='ch receivable'!G73 -> 0.10188344 | E73: ='ch in cash sales'!J73 -> -0.0022704792 | F73: ='Ch In earning'!H73 -> -0.0037681485 | G73: =D73+E73+F73 -> 0.095844816
A74: 73 | B74: MAYA | C74: 2019 | D74: ='ch receivable'!G74 -> 0.060768799 | E74: ='ch in cash sales'!J74 -> -0.094533668 | F74: ='Ch In earning'!H74 -> -0.00023958892 | G74: =D74+E74+F74 -> -0.034004458
A75: 74 | B75: MAYA | C75: 2020 | D75: =-'ch receivable'!G75 -> 0.16310158 | E75: =-'ch in cash sales'!J75 -> 0.53222034 | F75: ='Ch In earning'!H75 -> -0.0037467954 | G75: =D75+E75+F75 -> 0.69157512
A76: 75 | B76: MAYA | C76: 2021 | D76: ='ch receivable'!G76 -> 0.14796434 | E76: ='ch in cash sales'!J76 -> -0.35563177 | F76: ='Ch In earning'!H76 -> -0.0016807492 | G76: =D76+E76+F76 -> -0.20934818
A77: 76 | B77: PADI | C77: 2017 | D77: ='ch receivable'!G77 -> #DIV/0! | E77: ='ch in cash sales'!J77 -> 0 | F77: ='Ch In earning'!H77 -> #DIV/0! | G77: =D77+E77+F77 -> #DIV/0!
A78: 77 | B78: PADI | C78: 2018 | D78: =-'ch receivable'!G78 -> 0.031540805 | E78: =-'ch in cash sales'!J78 -> 1.55343 | F78: ='Ch In earning'!H78 -> -0.0067235307 | G78: =D78+E78+F78 -> 1.5782472
A79: 78 | B79: PADI | C79: 2019 | D79: ='ch receivable'!G79 -> -0.017745597 | E79: ='ch in cash sales'!J79 -> 1.8956843 | F79: ='Ch In earning'!H79 -> -0.36802953 | G79: =D79+E79+F79 -> 1.5099092
A80: 79 | B80: PADI | C80: 2020 | D80: ='ch receivable'!G80 -> 0.024059387 | E80: =-'ch in cash sales'!J80 -> 0.86665061 | F80: ='Ch In earning'!H80 -> 0.060645482 | G80: =D80+E80+F80 -> 0.95135548
A81: 80 | B81: PADI | C81: 2021 | D81: =-'ch receivable'!G81 -> 0.04402103 | E81: ='ch in cash sales'!J81 -> 0.98461743 | F81: ='Ch In earning'!H81 -> 0.057520258 | G81: =D81+E81+F81 -> 1.0861587
A82: 81 | B82: PNLF | C82: 2017 | D82: ='ch receivable'!G82 -> #DIV/0! | E82: ='ch in cash sales'!J82 -> 0 | F82: ='Ch In earning'!H82 -> #DIV/0! | G82: =D82+E82+F82 -> #DIV/0!
A83: 82 | B83: PNLF | C83: 2018 | D83: ='ch receivable'!G83 -> 0.0014425103 | E83: ='ch in cash sales'!J83 -> -0.38645848 | F83: ='Ch In earning'!H83 -> 0.0060938952 | G83: =D83+E83+F83 -> -0.37892207
A84: 83 | B84: PNLF | C84: 2019 | D84: ='ch receivable'!G84 -> 0.0016854192 | E84: ='ch in cash sales'!J84 -> -0.19604726 | F84: ='Ch In earning'!H84 -> 0.0065947279 | G84: =D84+E84+F84 -> -0.18776711
A85: 84 | B85: PNLF | C85: 2020 | D85: ='ch receivable'!G85 -> 0.0031164281 | E85: ='ch in cash sales'!J85 -> -0.82090918 | F85: ='Ch In earning'!H85 -> 0.016245391 | G85: =D85+E85+F85 -> -0.80154736
A86: 85 | B86: PNLF | C86: 2021 | D86: ='ch receivable'!G86 -> 0.00078878461 | E86: ='ch in cash sales'!J86 -> -0.11891685 | F86: ='Ch In earning'!H86 -> -0.061449537 | G86: =D86+E86+F86 -> -0.1795776
A87: 86 | B87: SDRA | C87: 2017 | D87: ='ch receivable'!G87 -> #DIV/0! | E87: ='ch in cash sales'!J87 -> 0 | F87: ='Ch In earning'!H87 -> #DIV/0! | G87: =D87+E87+F87 -> #DIV/0!
A88: 87 | B88: SDRA | C88: 2018 | D88: ='ch receivable'!G88 -> 0.13773132 | E88: ='ch in cash sales'!J88 -> -0.028414468 | F88: ='Ch In earning'!H88 -> 0.0017519535 | G88: =D88+E88+F88 -> 0.1110688
A89: 88 | B89: SDRA | C89: 2019 | D89: ='ch receivable'!G89 -> 0.1340184 | E89: ='ch in cash sales'!J89 -> -0.2357899 | F89: ='Ch In earning'!H89 -> -0.0045828277 | G89: =D89+E89+F89 -> -0.10635434
A90: 89 | B90: SDRA | C90: 2020 | D90: ='ch receivable'!G90 -> 0.084686511 | E90: ='ch in cash sales'!J90 -> -0.066058548 | F90: ='Ch In earning'!H90 -> -8.591549e-05 | G90: =D90+E90+F90 -> 0.018542048
A91: 90 | B91: SDRA | C91: 2021 | D91: ='ch receivable'!G91 -> 0.085905298 | E91: ='ch in cash sales'!J91 -> 0.032285607 | F91: ='Ch In earning'!H91 -> 0.00087534888 | G91: =D91+E91+F91 -> 0.11906625
A92: 91 | B92: SMMA | C92: 2017 | D92: ='ch receivable'!G92 -> #DIV/0! | E92: ='ch in cash sales'!J92 -> 0 | F92: ='Ch In earning'!H92 -> #DIV/0! | G92: =D92+E92+F92 -> #DIV/0!
A93: 92 | B93: SMMA | C93: 2018 | D93: ='ch receivable'!G93 -> 0.029218619 | E93: ='ch in cash sales'!J93 -> 0.024221977 | F93: ='Ch In earning'!H93 -> -0.010975313 | G93: =D93+E93+F93 -> 0.042465284
... A102: 101 | B102: ASDM | C102: 2017 | D102: ='ch receivable'!G102 -> 0 | E102: ='ch in cash sales'!J102 -> 0 | F102: ='Ch In earning'!H102 -> #DIV/0! | G102: =D102+E102+F102 -> #DIV/0!
A103: 102 | C103: 2018 | D103: ='ch receivable'!G103 -> -0.034972875 | E103: ='ch in cash sales'!J103 -> 0.042795982 | F103: ='Ch In earning'!H103 -> -0.00068719559 | G103: =D103+E103+F103 -> 0.0071359116
A104: 103 | C104: 2019 | D104: ='ch receivable'!G104 -> 0.030966639 | E104: ='ch in cash sales'!J104 -> -0.022023578 | F104: ='Ch In earning'!H104 -> -0.015544199 | G104: =D104+E104+F104 -> -0.0066011385
A105: 104 | C105: 2020 | D105: ='ch receivable'!G105 -> -0.24519379 | E105: ='ch in cash sales'!J105 -> 0.41696225 | F105: ='Ch In earning'!H105 -> 0.00046485653 | G105: =D105+E105+F105 -> 0.17223331
A106: 105 | C106: 2021 | D106: ='ch receivable'!G106 -> -0.053937947 | E106: ='ch in cash sales'!J106 -> 0.057044725 | F106: ='Ch In earning'!H106 -> -0.0036401796 | G106: =D106+E106+F106 -> -0.00053340135
A107: 106 | B107: BBKP | C107: 2017 | D107: ='ch receivable'!G107 -> 0 | E107: ='ch in cash sales'!J107 -> 0 | F107: ='Ch In earning'!H107 -> #DIV/0! | G107: =D107+E107+F107 -> #DIV/0!
A108: 107 | C108: 2018 | D108: ='ch receivable'!G108 -> -0.060897686 | E108: ='ch in cash sales'!J108 -> -0.059775291 | F108: ='Ch In earning'!H108 -> 0.00099095442 | G108: =D108+E108+F108 -> -0.11968202
A109: 108 | C109: 2019 | D109: ='ch receivable'!G109 -> 0.035187496 | E109: ='ch in cash sales'!J109 -> -0.25738557 | F109: ='Ch In earning'!H109 -> -0.00077512457 | G109: =D109+E109+F109 -> -0.2229732
A110: 109 | C110: 2020 | D110: ='ch receivable'!G110 -> -0.12885637 | E110: ='ch in cash sales'!J110 -> -0.56192855 | F110: ='Ch In earning'!H110 -> -0.044904259 | G110: =D110+E110+F110 -> -0.73568918
A111: 110 | C111: 2021 | D111: ='ch receivable'!G111 -> -0.029221021 | E111: ='ch in cash sales'!J111 -> -0.56810246 | F111: ='Ch In earning'!H111 -> 0.0063649068 | G111: =D111+E111+F111 -> -0.59095857
A112: 111 | B112: BBMD | C112: 2017 | D112: ='ch receivable'!G112 -> 0 | E112: ='ch in cash sales'!J112 -> 0 | F112: ='Ch In earning'!H112 -> #DIV/0! | G112: =D112+E112+F112 -> #DIV/0!
A113: 112 | C113: 2018 | D113: ='ch receivable'!G113 -> 0.035934415 | E113: ='ch in cash sales'!J113 -> -0.086345687 | F113: ='Ch In earning'!H113 -> -0.0018209934 | G113: =D113+E113+F113 -> -0.052232265
A114: 113 | C114: 2019 | D114: ='ch receivable'!G114 -> 0.040907644 | E114: ='ch in cash sales'!J114 -> -0.042545071 | F114: ='Ch In earning'!H114 -> -0.003270503 | G114: =D114+E114+F114 -> -0.0049079296
A115: 114 | C115: 2020 | D115: ='ch receivable'!G115 -> -0.053278711 | E115: ='ch in cash sales'!J115 -> 0.23394761 | F115: ='Ch In earning'!H115 -> 0.004571415 | G115: =D115+E115+F115 -> 0.18524032
A116: 115 | C116: 2021 | D116: ='ch receivable'!G116 -> 0.050749107 | E116: ='ch in cash sales'!J116 -> 0.030356746 | F116: ='Ch In earning'!H116 -> 0.013120776 | G116: =D116+E116+F116 -> 0.094226629
A117: 116 | B117: BBRI | C117: 2017 | D117: ='ch receivable'!G117 -> 0 | E117: ='ch in cash sales'!J117 -> 0 | F117: ='Ch In earning'!H117 -> #DIV/0! | G117: =D117+E117+F117 -> #DIV/0!
A118: 117 | C118: 2018 | D118: ='ch receivable'!G118 -> 0.10519715 | E118: ='ch in cash sales'!J118 -> -0.058698478 | F118: ='Ch In earning'!H118 -> -0.0022766786 | G118: =D118+E118+F118 -> 0.044221996
A119: 118 | C119: 2019 | D119: ='ch receivable'!G119 -> 0.047439707 | E119: ='ch in cash sales'!J119 -> 0.011464609 | F119: ='Ch In earning'!H119 -> -0.0024625195 | G119: =D119+E119+F119 -> 0.056441796
A120: 119 | C120: 2020 | D120: ='ch receivable'!G120 -> -0.0017669556 | E120: ='ch in cash sales'!J120 -> -0.011679513 | F120: ='Ch In earning'!H120 -> -0.014301191 | G120: =D120+E120+F120 -> -0.027747659
A121: 120 | C121: 2021 | D121: ='ch receivable'!G121 -> 0.051150625 | E121: ='ch in cash sales'!J121 -> 0.21465042 | F121: ='Ch In earning'!H121 -> 0.0072744386 | G121: =D121+E121+F121 -> 0.27307548
A122: 121 | B122: BBYB | C122: 2017 | D122: ='ch receivable'!G122 -> 0 | E122: ='ch in cash sales'!J122 -> 0 | F122: ='Ch In earning'!H122 -> #DIV/0! | G122: =D122+E122+F122 -> #DIV/0!
A123: 122 | C123: 2018 | D123: ='ch receivable'!G123 -> -0.022406965 | E123: ='ch in cash sales'!J123 -> -0.05277748 | F123: ='Ch In earning'!H123 -> -0.033074694 | G123: =D123+E123+F123 -> -0.10825914
A124: 123 | C124: 2019 | D124: ='ch receivable'!G124 -> -0.0042966641 | E124: ='ch in cash sales'!J124 -> 0.25382566 | F124: ='Ch In earning'!H124 -> 0.032701795 | G124: =D124+E124+F124 -> 0.28223079
A125: 124 | C125: 2020 | D125: ='ch receivable'!G125 -> -0.018631458 | E125: ='ch in cash sales'!J125 -> -0.59978543 | F125: ='Ch In earning'!H125 -> -0.0006965111 | G125: =D125+E125+F125 -> -0.6191134
A126: 125 | C126: 2021 | D126: ='ch receivable'!G126 -> 0.073095025 | E126: ='ch in cash sales'!J126 -> 0.30144513 | F126: ='Ch In earning'!H126 -> -0.12119657 | G126: =D126+E126+F126 -> 0.25334358
A127: 126 | B127: BINA | C127: 2017 | D127: ='ch receivable'!G127 -> 0 | E127: ='ch in cash sales'!J127 -> 0 | F127: ='Ch In earning'!H127 -> #DIV/0! | G127: =D127+E127+F127 -> #DIV/0!
A128: 127 | C128: 2018 | D128: ='ch receivable'!G128 -> 0.085944302 | E128: ='ch in cash sales'!J128 -> -0.060089989 | F128: ='Ch In earning'!H128 -> -0.0039762235 | G128: =D128+E128+F128 -> 0.021878089
A129: 128 | C129: 2019 | D129: ='ch receivable'!G129 -> 0.16118526 | E129: ='ch in cash sales'!J129 -> -0.18507047 | F129: ='Ch In earning'!H129 -> -0.0026735241 | G129: =D129+E129+F129 -> -0.026558739
A130: 129 | C130: 2020 | D130: ='ch receivable'!G130 -> 0.057367552 | E130: ='ch in cash sales'!J130 -> 0.15987133 | F130: ='Ch In earning'!H130 -> 0.0019975766 | G130: =D130+E130+F130 -> 0.21923646
A131: 130 | C131: 2021 | D131: ='ch receivable'!G131 -> 0.066838217 | E131: ='ch in cash sales'!J131 -> 0.0021994746 | F131: ='Ch In earning'!H131 -> 9.3344704e-05 | G131: =D131+E131+F131 -> 0.069131037
A132: 131 | B132: BJTM | C132: 2017 | D132: ='ch receivable'!G132 -> 0 | E132: ='ch in cash sales'!J132 -> 0 | F132: ='Ch In earning'!H132 -> #DIV/0! | G132: =D132+E132+F132 -> #DIV/0!
A133: 132 | C133: 2018 | D133: ='ch receivable'!G133 -> 0.040764712 | E133: ='ch in cash sales'!J133 -> -0.011308919 | F133: ='Ch In earning'!H133 -> -0.012554917 | G133: =D133+E133+F133 -> 0.016900877
A134: 133 | C134: 2019 | D134: ='ch receivable'!G134 -> 0.15148858 | E134: ='ch in cash sales'!J134 -> -0.16071876 | F134: ='Ch In earning'!H134 -> 0.0046659237 | G134: =D134+E134+F134 -> -0.0045642548
A135: 134 | C135: 2020 | D135: ='ch receivable'!G135 -> 0.1177244 | E135: ='ch in cash sales'!J135 -> -0.17875494 | F135: ='Ch In earning'!H135 -> -0.0079384398 | G135: =D135+E135+F135 -> -0.06896898
A136: 135 | C136: 2021 | D136: ='ch receivable'!G136 -> -0.088554322 | E136: ='ch in cash sales'!J136 -> 0.36710606 | F136: ='Ch In earning'!H136 -> 0.002227825 | G136: =D136+E136+F136 -> 0.28077957
A137: 136 | B137: BMRI | C137: 2017 | D137: ='ch receivable'!G137 -> 0 | E137: ='ch in cash sales'!J137 -> 0 | F137: ='Ch In earning'!H137 -> #DIV/0! | G137: =D137+E137+F137 -> #DIV/0!
A138: 137 | C138: 2018 | D138: ='ch receivable'!G138 -> 0.080778743 | E138: ='ch in cash sales'!J138 -> -0.063488714 | F138: ='Ch In earning'!H138 -> 0.0040242384 | G138: =D138+E138+F138 -> 0.021314267
A139: 138 | C139: 2019 | D139: ='ch receivable'!G139 -> 0.071340575 | E139: ='ch in cash sales'!J139 -> -0.034098201 | F139: ='Ch In earning'!H139 -> -0.00022574013 | G139: =D139+E139+F139 -> 0.037016633
A140: 139 | C140: 2020 | D140: ='ch receivable'!G140 -> -0.0031206827 | E140: ='ch in cash sales'!J140 -> -0.05089888 | F140: ='Ch In earning'!H140 -> -0.01195711 | G140: =D140+E140+F140 -> -0.065976673
A141: 140 | C141: 2021 | D141: ='ch receivable'!G141 -> 0.076431166 | E141: ='ch in cash sales'!J141 -> 0.10812138 | F141: ='Ch In earning'!H141 -> 0.0073574268 | G141: =D141+E141+F141 -> 0.19190998
A142: 141 | B142: BNBA | C142: 2017 | D142: ='ch receivable'!G142 -> 0 | E142: ='ch in cash sales'!J142 -> 0 | F142: ='Ch In earning'!H142 -> #DIV/0! | G142: =D142+E142+F142 -> #DIV/0!
A143: 142 | C143: 2018 | D143: ='ch receivable'!G143 -> 0.034982133 | E143: ='ch in cash sales'!J143 -> -0.068378823 | F143: ='Ch In earning'!H143 -> 0.00036589057 | G143: =D143+E143+F143 -> -0.033030799
A144: 143 | C144: 2019 | D144: ='ch receivable'!G144 -> 0.052724536 | E144: ='ch in cash sales'!J144 -> -0.1823768 | F144: ='Ch In earning'!H144 -> -0.0081765627 | G144: =D144+E144+F144 -> -0.13782883
A145: 144 | C145: 2020 | D145: ='ch receivable'!G145 -> -0.080465852 | E145: ='ch in cash sales'!J145 -> 0.050729456 | F145: ='Ch In earning'!H145 -> -0.002489267 | G145: =D145+E145+F145 -> -0.032225663
A146: 145 | C146: 2021 | D146: ='ch receivable'!G146 -> -0.075561625 | E146: ='ch in cash sales'!J146 -> 0.16060291 | F146: ='Ch In earning'!H146 -> 0.00023153419 | G146: =D146+E146+F146 -> 0.085272819
A147: 146 | B147: AGRO | C147: 2017 | D147: ='ch receivable'!G147 -> 0 | E147: ='ch in cash sales'!J147 -> 0 | F147: ='Ch In earning'!H147 -> #DIV/0! | G147: =D147+E147+F147 -> #DIV/0!
A148: 147 | C148: 2018 | D148: ='ch receivable'!G148 -> 0.23226994 | E148: ='ch in cash sales'!J148 -> -0.073068655 | F148: ='Ch In earning'!H148 -> 0.00077925705 | G148: =D148+E148+F148 -> 0.15998054
A149: 148 | C149: 2019 | D149: ='ch receivable'!G149 -> 0.12915162 | E149: ='ch in cash sales'!J149 -> -0.12350554 | F149: ='Ch In earning'!H149 -> -0.011814244 | G149: =D149+E149+F149 -> -0.0061681699
A150: 149 | C150: 2020 | D150: ='ch receivable'!G150 -> -0.00084992109 | E150: ='ch in cash sales'!J150 -> -0.10088327 | F150: ='Ch In earning'!H150 -> -0.00061908643 | G150: =D150+E150+F150 -> -0.10235228
A151: 150 | C151: 2021 | D151: ='ch receivable'!G151 -> -0.38696577 | E151: ='ch in cash sales'!J151 -> 1.1767562 | F151: ='Ch In earning'!H151 -> -0.14951811 | G151: =D151+E151+F151 -> 0.64027236
A152: 151 | B152: BSIM | C152: 2017 | D152: ='ch receivable'!G152 -> 0 | E152: ='ch in cash sales'!J152 -> 0 | F152: ='Ch In earning'!H152 -> #DIV/0! | G152: =D152+E152+F152 -> #DIV/0!
A153: 152 | C153: 2018 | D153: ='ch receivable'!G153 -> 0.029657144 | E153: ='ch in cash sales'!J153 -> 0.074685309 | F153: ='Ch In earning'!H153 -> -0.0107488 | G153: =D153+E153+F153 -> 0.093593652
A154: 153 | C154: 2019 | D154: ='ch receivable'!G154 -> 0.072524431 | E154: ='ch in cash sales'!J154 -> 0.11359558 | F154: ='Ch In earning'!H154 -> -4.7725618e-05 | G154: =D154+E154+F154 -> 0.18607228
A155: 154 | C155: 2020 | D155: ='ch receivable'!G155 -> -0.070618393 | E155: ='ch in cash sales'!J155 -> 0.087411568 | F155: ='Ch In earning'!H155 -> 0.00043955586 | G155: =D155+E155+F155 -> 0.017232731
A156: 155 | C156: 2021 | D156: ='ch receivable'!G156 -> -0.051010225 | E156: ='ch in cash sales'!J156 -> 0.095845282 | F156: ='Ch In earning'!H156 -> 0.00042020464 | G156: =D156+E156+F156 -> 0.045255261
A157: 156 | B157: INPC | C157: 2017 | D157: ='ch receivable'!G157 -> 0 | E157: ='ch in cash sales'!J157 -> 0 | F157: ='Ch In earning'!H157 -> #DIV/0! | G157: =D157+E157+F157 -> #DIV/0!
A158: 157 | C158: 2018 | D158: ='ch receivable'!G158 -> -0.11201072 | E158: ='ch in cash sales'!J158 -> 0.19613338 | F158: ='Ch In earning'!H158 -> -0.00045676998 | G158: =D158+E158+F158 -> 0.083665889
A159: 158 | C159: 2019 | D159: ='ch receivable'!G159 -> -0.061915779 | E159: ='ch in cash sales'!J159 -> -0.11333641 | F159: ='Ch In earning'!H159 -> -0.0057272083 | G159: =D159+E159+F159 -> -0.1809794
A160: 159 | C160: 2020 | D160: ='ch receivable'!G160 -> -0.043794961 | E160: ='ch in cash sales'!J160 -> -0.28372866 | F160: ='Ch In earning'!H160 -> 0.004046687 | G160: =D160+E160+F160 -> -0.32347694
A161: 160 | C161: 2021 | D161: ='ch receivable'!G161 -> -0.035149476 | E161: ='ch in cash sales'!J161 -> 0.39133711 | F161: ='Ch In earning'!H161 -> -0.0082678035 | G161: =D161+E161+F161 -> 0.34791983
...

Sheet WC
A1: No | B1: Kode Emiten | C1: Tahun | D1: Current Assets | E1: Current Liabilities | F1: WC | G1: ∆WC
A2: 1 | B2: ASTJ | C2: 2017 | D2: =14519676151+713988211+'ch receivable'!D2+36882660220+30928753278 -> 188346950854 | E2: =234663726530-6310038845-15163595819 -> 213190091866 | F2: =D2-E2 -> -24843141012
A3: 2 | B3: ASTJ | C3: 2018 | D3: =11675712902+'ch receivable'!D3+713988216+64633898000+32186974591 -> 218515004183 | E3: =258813437264-5755573881-11221131258 -> 241836732125 | F3: =D3-E3 -> -23321727942 | G3: =F3-F2 -> 1521413070
A4: 3 | B4: ASTJ | C4: 2019 | D4: =9180911925+'ch receivable'!D4+68040900929+28371905434 -> 206936619136 | E4: =238307219450-1559666255-5816748324 -> 230930804871 | F4: =D4-E4 -> -23994185735 | G4: =F4-F3 -> -672457793
A5: 4 | B5: ASTJ | C5: 2020 | D5: =10218012106+'ch receivable'!D5+25044323082+14134896380 -> 155993828988 | E5: =156229284960-8520962475-10964575454 -> 136743747031 | F5: =D5-E5 -> 19250081957 | G5: =F5-F4 -> 43244267692
A6: 5 | B6: ASTJ | C6: 2021 | D6: =8301695852+'ch receivable'!D6+29453865309+65587930418 -> 236157460614 | E6: =219398368810-3324384530-24080932611 -> 191993051669 | F6: =D6-E6 -> 44164408945 | G6: =F6-F5 -> 24914326988
A7: 6 | B7: ASMI | C7: 2017 | D7: =3063169002+'ch receivable'!D7+123016373814 -> 265738628652 | E7: =403521972950-36619253244-14642983000-233483356743-18898350616 -> 99878029347 | F7: =D7-E7 -> 165860599305
A8: 7 | B8: ASMI | C8: 2018 | D8: =5853410707+'ch receivable'!D8+133703082559 -> 320101149649 | E8: =1113802274+89246619825+21790129723+545482187+12089534682 -> 124785568691 | F8: =D8-E8 -> 195315580958 | G8: =F8-F7 -> 29454981653
A9: 8 | B9: ASMI | C9: 2019 | D9: =10327839284+'ch receivable'!D9+130941453733 -> 317063416058 | E9: =1534991608+71566715136+15627966323+617272865+5147113476 -> 94494059408 | F9: =D9-E9 -> 222569356650 | G9: =F9-F8 -> 27253775692
A10: 9 | B10: ASMI | C10: 2020 | D10: =27753266725+'ch receivable'!D10+237751180761 -> 528285486877 | E10: =460283470+36757191276+22406237281+391760750+1230443792 -> 61245916569 | F10: =D10-E10 -> 467039570308 | G10: =F10-F9 -> 244470213658
A11: 10 | B11: ASMI | C11: 2021 | D11: =27286512817+'ch receivable'!D11+188451309212 -> 418850978640 | E11: =3237593569+3491647273+31148406534+633605432+4987600229 -> 43498853037 | F11: =D11-E11 -> 375352125603 | G11: =F11-F10 -> -91687444705
A12: 11 | B12: BBNI | C12: 2017 | D12: =11577664+32700717000000+21335150000000+28592738000000+'ch receivable'!D12 -> 536647607577664 | E12: =4867547000000+492747948000000+11734207000000+971479000000+80425000000+4093855000000 -> 514495461000000 | F12: =D12-E12 -> 22152146577664
A13: 12 | B13: BBNI | C13: 2018 | D13: =14043846000000+35591243000000+13133828000000+39324445000000+'ch receivable'!D13 -> 628563451000000 | E13: =671237546000000-99953000000-52024506000000-2987464-14608465000000-177519000000-4416613000000-21524329000000-322028000000 -> 578064130012536 | F13: =D13-E13 -> 50499320987464 | G13: =F13-F12 -> 28347174409800
A14: 13 | B14: BBNI | C14: 2019 | D14: =15361703000000+37104091000000+14962793000000+47776809000000+'ch receivable'!D14 -> 683514765000000 | E14: =688489442000000-99965000000-57235500000000-2985052000000-14900956000000-185019000000-5341440000000-203054000000-2183403000000 -> 605355053000000 | F14: =D14-E14 -> 78159712000000 | G14: =F14-F13 -> 27660391012536
A15: 14 | B15: BBNI | C15: 2020 | D15: =17324047000000+35065701000000+16107788000000+61329259000000+'ch receivable'!D14 -> 698136164000000 | E15: =746235663000000-99979000000-44114314000000-2985011000000-18280485000000-1421914000000-5500360000000-2590268000000-414280000000 -> 670829052000000 | F15: =D15-E15 -> 27307112000000 | G15: =F15-F14 -> -50852600000000
A16: 15 | B16: BBNI | C16: 2021 | D16: =13683598000000+48682431000000+19569891000000+92290210000000+'ch receivable'!D16 -> 735846646000000 | E16: =838317715000000-15764682000000-32457936000000-2986530000000-20542001000000-2276397000000-5588069000000-1828652000000-109948000000 -> 756763500000000 | F16: =D16-E16 -> -20916854000000 | G16: =F16-F15 -> -48223966000000
A17: 16 | B17: BBTN | C17: 2017 | D17: =1027554000000+12554585000000+556301000000+24697503000000+'ch receivable'!D17 -> 235478618000000 | E17: =223937463000000-2999319000000-5612462000000-7991053000000-20480459000000-8081000000-1385000000000-85481932000000 -> 99979157000000 | F17: =D17-E17 -> 135499461000000
A18: 17 | B18: BBTN | C18: 2018 | D18: =1243615000000+15417862000000+1587051000000+26464760000000+'ch receivable'!D18 -> 279700978000000 | E18: =263784017000000-2999519000000-6217814000000-15499493000000-20644760000000-528148000000-935000000000-115462283000000 -> 101497000000000 | F18: =D18-E18 -> 178203978000000 | G18: =F18-F17 -> 42704517000000
A19: 18 | B19: BBTN | C19: 2019 | D19: =1369167000000+1551239000000+747869000000+11097193000000+'ch receivable'!D19 -> 264961513000000 | E19: =269451682000000-5999669000000-5736637000000-19783552000000-22465657000000-487052000000-935000000000-113929798000000 -> 100114317000000 | F19: =D19-E19 -> 164847196000000 | G19: =F19-F18 -> -13356782000000
A20: 19 | B20: BBTN | C20: 2020 | D20: =1429426000000+11107672000000+3215321000000+19830433000000+'ch receivable'!D20 -> 282901116000000 | E20: =321376142000000-10194432000000-6666875000000-6489000000-15810466000000-23807138000000-22787000000-196071000000-147858608000000 -> 116813276000000 | F20: =D20-E20 -> 166087840000000 | G20: =F20-F19 -> 1240644000000
A21: 20 | B21: BBTN | C21: 2021 | D21: =1539577000000+10692484000000+1095100000000+27901048000000+'ch receivable'!D21 -> 302112274000000 | E21: =327693592000000-8759744000000-6618300000000-3644000000-12371708000000-22062291000000-17741000000-454140000000-146520589000000 -> 130885435000000 | F21: =D21-E21 -> 171226839000000 | G21: =F21-F20 -> 5138999000000
A22: 21 | B22: BCAP | C22: 2017 | D22: =1780674000000+34993000000+424687000000-10577000000+'ch receivable'!D22 -> 6553454000000 | E22: =533534000000+8443515000000+197257000000+14726000000+172534000000+27056000000 -> 9388622000000 | F22: =D22-E22 -> -2835168000000
A23: 22 | B23: BCAP | C23: 2018 | D23: =1927704000000+38316000000+309360000000-16490000000+'ch receivable'!D23 -> 5246022000000 | E23: =823273000000+7604794000000+740092000000+37937000000+113873000000+22277000000 -> 9342246000000 | F23: =D23-E23 -> -4096224000000 | G23: =(F23-F22) -> -1261056000000
A24: 23 | B24: BCAP | C24: 2019 | D24: =1177395000000+39229000000+342371000000-25108000000+'ch receivable'!D24 -> 4131645000000 | E24: =409096000000+7895637000000+393715000000+48486000000+201472000000+313175000000+32272000000 -> 9293853000000 | F24: =D24-E24 -> -5162208000000 | G24: =(F24-F23) -> -1065984000000
A25: 24 | B25: BCAP | C25: 2020 | D25: =1758171000000+43458000000+310482000000-34031000000+'ch receivable'!D25 -> 4672634000000 | E25: =753682000000+8315127000000+490103000000+173797000000+421663000000+498855000000+25398000000 -> 10678625000000 | F25: =D25-E25 -> -6005991000000 | G25: =(F25-F24) -> -843783000000
A26: 25 | B26: BCAP | C26: 2021 | D26: =2827492000000+28473000000+304095000000-34781000000+'ch receivable'!D26 -> 5431154000000 | E26: =11123446000000+130675000000+69299000000+385506000000+347083000000+29696000000 -> 12085705000000 | F26: =D26-E26 -> -6654551000000 | G26: =(F26-F25) -> -648560000000
A27: 26 | B27: BDMN | C27: 2017 | D27: =2546414000000+7555916000000+221082000000+1810940000000+5198885000000+'ch receivable'!D27+697170000000 -> 140368274000000 | E27: =129971000000+101766847000000+4634513000000+116526000000 -> 106647857000000 | F27: =D27-E27 -> 33720417000000
A28: 27 | B28: BDMN | C28: 2018 | D28: =2823776000000+6459517000000+112282000000+1274889000000+8576062000000+'ch receivable'!D28 -> 143923553000000 | E28: =118980000000+107576816000000+3152422000000+87011000000 -> 110935229000000 | F28: =D28-E28 -> 32988324000000 | G28: =F28-F27 -> -732093000000
A29: 28 | B29: BDMN | C29: 2019 | D29: =2950563000000+5403446000000+15945000000+2599729000000+189886000000+5400836000000+'ch receivable'!D29 -> 154362647000000 | E29: =590957000000+109200953000000+266031000000+4215474000000+473076000000 -> 114746491000000 | F29: =D29-E29 -> 39616156000000 | G29: =F29-F28 -> 6627832000000
A30: 29 | B30: BDMN | C30: 2020 | D30: =2838127000000+2185998000000+5208000000+4411865000000+7303551000000+'ch receivable'!D30 -> 145488655000000 | E30: =298081000000+123435123000000+78494000000+2399231000000+300857000000 -> 126511786000000 | F30: =D30-E30 -> 18976869000000 | G30: =F30-F29 -> -20639287000000
A31: 30 | B31: BDMN | C31: 2021 | D31: =2789555000000+3060014000000+176550000000+2801084000000+9888484000000+'ch receivable'!D31 -> 141166331000000 | E31: =962547000000+120106770000000+65813000000+2218774000000+212184000000 -> 123566088000000 | F31: =D31-E31 -> 17600243000000 | G31: =F31-F30 -> -1376626000000
A32: 31 | B32: BFIN | C32: 2017 | D32: =225203000000+'ch receivable'!D32 -> 15814055000000 | E32: =6819052000000+140151000000+293527000000+199716000000 -> 7452446000000 | F32: =D32-E32 -> 8361609000000
A33: 32 | B33: BFIN | C33: 2018 | D33: =755247000000+'ch receivable'!D33 -> 18234081000000 | E33: =6899860000000+67063000000+287878000000+202498000000 -> 7457299000000 | F33: =D33-E33 -> 10776782000000 | G33: =F33-F32 -> 2415173000000
A34: 33 | B34: BFIN | C34: 2019 | D34: =660032000000+'ch receivable'!D34 -> 18211551000000 | E34: =7730021000000+73271000000+796709000000+258337000000 -> 8858338000000 | F34: =D34-E34 -> 9353213000000 | G34: =F34-F33 -> -1423569000000
A35: 34 | B35: BFIN | C35: 2020 | D35: =1414691000000+'ch receivable'!D35 -> 14248625000000 | E35: =4794844000000+101719000000+194038000000+154211000000 -> 5244812000000 | F35: =D35-E35 -> 9003813000000 | G35: =F35-F34 -> -349400000000
A36: 35 | B36: BFIN | C36: 2021 | D36: =969182000000+'ch receivable'!D36 -> 14733402000000 | E36: =4789422000000+120131000000+338442000000+115457000000 -> 5363452000000 | F36: =D36-E36 -> 9369950000000 | G36: =F36-F35 -> 366137000000
A37: 36 | B37: BNGA | C37: 2017 | D37: =3889241000000+11522696000000+3529272000000+13314199000000+'ch receivable'!D37 -> 221847408000000 | E37: =1946166000000+49281023000000+50214272000000+6884335000000+445502000000+2986666000000+1289985000000 -> 113047949000000 | F37: =D37-E37 -> 108799459000000
A38: 37 | B38: BNGA | C38: 2018 | D38: =4290614000000+10435254000000+3024143000000+9227275000000+'ch receivable'!D38 -> 214889787000000 | E38: =2240191000000+45857151000000+54495883000000+2928693000000+461141000000+3594738000000+930196000000 -> 110507993000000 | F38: =D38-E38 -> 104381794000000 | G38: =F38-F37 -> -4417665000000
A39: 38 | B39: BNGA | C39: 2019 | D39: =5691444000000+11395695000000+2138408000000+12104730000000+'ch receivable'!D39 -> 224000336000000 | E39: =1781962000000+48943913000000+59316069000000+1364586000000+498541000000+4038684000000+1131727000000 -> 117075482000000 | F39: =D39-E39 -> 106924854000000 | G39: =F39-F38 -> 2543060000000
A40: 39 | B40: BNGA | C40: 2020 | D40: =4777284000000+6221892000000+3697487000000+13334150000000+'ch receivable'!D40 -> 194242397000000 | E40: =3636684000000+55862547000000+67861369000000+2901556000000+301192000000+5151393000000+1098334000000 -> 136813075000000 | F40: =D40-E40 -> 57429322000000 | G40: =F40-F39 -> -49495532000000
A41: 40 | B41: BNGA | C41: 2021 | D41: =4548210000000+9291044000000+2822988000000+30345785000000+'ch receivable'!D41 -> 218958935000000 | E41: =3239391000000+75477306000000+72565133000000+3059451000000+584187000000+6082833000000+1355055000000 -> 162363356000000 | F41: =D41-E41 -> 56595579000000 | G41: =F41-F40 -> -833743000000
A42: 41 | B42: BNII | C42: 2017 | D42: =1327144000000+9135070000000+1760432000000+3777715000000+'ch receivable'!D42 -> 142245644000000 | E42: =1176239000000+121291560000000+3861373000000+198800000000+3781938000000 -> 130309910000000 | F42: =D42-E42 -> 11935734000000
A43: 42 | B43: BNII | C43: 2018 | D43: =1604849000000+8941078000000+2161790000000+4978245000000+'ch receivable'!D43 -> 152861374000000 | E43: =859282000000+116812388000000+4217922000000+168883000000+3870431000000 -> 125928906000000 | F43: =D43-E43 -> 26932468000000 | G43: =F43-F42 -> 14996734000000
A44: 43 | B44: BNII | C44: 2019 | D44: =1776134000000+7730335000000+3457531000000+5284323000000+'ch receivable'!D44 -> 140755959000000 | E44: =949936000000+110601006000000+3134059000000+193017000000+3283357000000 -> 118161375000000 | F44: =D44-E44 -> 22594584000000 | G44: =F44-F43 -> -4337884000000
A45: 44 | B45: BNII | C45: 2020 | D45: =1538167000000+5049530000000+5018118000000+13029798000000+'ch receivable'!D45 -> 129038323000000 | E45: =1172326000000+115003047000000+8236126000000+221494000000+3840214000000 -> 128473207000000 | F45: =D45-E45 -> 565116000000 | G45: =F45-F44 -> -22029468000000
A46: 45 | B46: BNII | C46: 2021 | D46: =1618419000000+4499947000000+3748918000000+14395316000000+'ch receivable'!D46 -> 124990261000000 | E46: =809999000000+114898775000000+5162363000000+222417000000+3642641000000 -> 124736195000000 | F46: =D46-E46 -> 254066000000 | G46: =F46-F45 -> -311050000000
A47: 46 | B47: BNLI | C47: 2017 | D47: =1940485000000+8541582000000+750212000000+426709000000+6294096000000+1104676000000+164000000+'ch receivable'!D47 -> 112708769000000 | E47: =384169000000+23481197000000+6553603000000+27393067000000+429648000000+2552273000000+145270000000+11338000000+610000000+1032000000+1184496000000+138159000000 -> 62274862000000 | F47: =D47-E47 -> 50433907000000
A48: 47 | B48: BNLI | C48: 2018 | D48: =2185074000000+8901492000000+929560000000+543070000000+11850858000000+1743827000000+671000000+'ch receivable'!D48 -> 128117544000000 | E48: =130440930000000-1068985000000-3715302000000-59465000000--621315000000-17740000000-2747942000000-54219868000000-7026154000000 -> 62206789000000 | F48: =D48-E48 -> 65910755000000 | G48: =F48-F47 -> 15476848000000
A49: 48 | B49: BNLI | C49: 2019 | D49: =2303932000000+8082615000000+1765592000000+424849000000+12426427000000+2484360000000+4000000+'ch receivable'!D49 -> 134263488000000 | E49: =137413908000000-992138000000-1286680000000-56017000000--562970000000-12881000000-1695446000000-19872000000-55010089000000-5890381000000 -> 73013374000000 | F49: =D49-E49 -> 61250114000000 | G49: =F49-F48 -> -4660641000000
A50: 49 | B50: BNLI | C50: 2020 | D50: =1794768000000+5013391000000+2557513000000+6003000000+18660681000000+2348378000000+'ch receivable'!D50 -> 142626559000000 | E50: =162654644000000-9106068000000-105197000000-609738000000-67667000000-1141112000000-8000000-1460535000000-71191551000000-63166000000 -> 78909602000000 | F50: =D50-E50 -> 63716957000000 | G50: =F50-F49 -> 2466843000000
A51: 50 | B51: BNLI | C51: 2021 | D51: =1978137000000+10627001000000+2971757000000+30716000000+32594007000000+855158000000+'ch receivable'!D51 -> 167969662000000 | E51: =197765327000000-9329879000000-67200000000-756454000000-1350000000-2011886000000-82778671000000-57224000000 -> 102762663000000 | F51: =D51-E51 -> 65206999000000 | G51: =F51-F50 -> 1490042000000
A52: 51 | B52: ADMF | C52: 2017 | D52: =220471000000+269991000000+1731256000000+'ch receivable'!D52 -> 28461735000000 | E52: =6697104000000+3847182000000+657757000000+72968000000+30178000000+967689000000 -> 12272878000000 | F52: =D52-E52 -> 16188857000000
A53: 52 | B53: ADMF | C53: 2018 | D53: =249599000000+180069000000+1259656000000+'ch receivable'!D53 -> 29757520000000 | E53: =11778092000000+793217000000+35451000000+30174000000+864883000000 -> 13501817000000 | F53: =D53-E53 -> 16255703000000 | G53: =F53-F52 -> 66846000000
A54: 53 | B54: ADMF | C54: 2019 | D54: =170881000000+1146708000000+1804903000000+'ch receivable'!D54 -> 33504454000000 | E54: =10350058000000+1500000000000+973379000000+38616000000+364455000000+1058152000000 -> 14284660000000 | F54: =D54-E54 -> 19219794000000 | G54: =F54-F53 -> 2964091000000
A55: 54 | B55: ADMF | C55: 2020 | D55: =76172000000+2934779000000+1216458000000+'ch receivable'!D55 -> 27477745000000 | E55: =8952441000000+187500000000+1012886000000+38330000000+185896000000+946096000000 -> 11323149000000 | F55: =D55-E55 -> 16154596000000 | G55: =F55-F54 -> -3065198000000
A56: 55 | B56: ADMF | C56: 2021 | D56: =153864000000+876000000+606931000000+'ch receivable'!D56 -> 21356445000000 | E56: =3608879000000+1345834000000+1034561000000+40461000000+173686000000+953468000000 -> 7156889000000 | F56: =D56-E56 -> 14199556000000 | G56: =F56-F55 -> -1955040000000
A57: 56 | B57: BVIC | C57: 2017 | D57: =72142423000+1768560694000+75230962000+2114572525000+'ch receivable'!D57 -> 19725075731000 | E57: =4494773000+20774972177000+2236882484000+41968503000+76384504000 -> 23134702441000 | F57: =D57-E57 -> -3409626710000
A58: 57 | B58: BVIC | C58: 2018 | D58: =57675937000+1551075080000+91961736000+2401787349000+'ch receivable'!D57 -> 19797069229000 | E58: =4393198000+20636380394000+1835799330000+65331129000+73621459000 -> 22615525510000 | F58: =D58-E58 -> -2818456281000 | G58: =F58-F57 -> 591170429000
A59: 58 | B59: BVIC | C59: 2019 | D59: =40655817000+1810636332000+125446536000+306638566000+'ch receivable'!D59 -> 19404658911000 | E59: =2077421000+21791637063000+909309808000+29976241000+65755469000 -> 22798756002000 | F59: =D59-E59 -> -3394097091000 | G59: =F59-F58 -> -575640810000
A60: 59 | B60: BVIC | C60: 2020 | D60: =61723223000+612623334000+184920912000+1692224733000+'ch receivable'!D60 -> 16797468234000 | E60: =22197849857000-1544029002-179217199000 -> 22017088628998 | F60: =D60-E60 -> -5219620394998 | G60: =F60-F59 -> -1825523303998
A61: 60 | B61: BVIC | C61: 2021 | D61: =53929444000+663113716000+405666998000+762366332000+'ch receivable'!D61 -> 16671877148000 | E61: =335926000+18084871983000+1037173068000+12584904000+43884161000 -> 19178850042000 | F61: =D61-E61 -> -2506972894000 | G61: =F61-F60 -> 2712647500998
A62: 61 | B62: CFIN | C62: 2017 | D62: =28547330000+'ch receivable'!D62 -> 9648151869000 | E62: =4777179002000+88531344000+39943197000+31438617000 -> 4937092160000 | F62: =D62-E62 -> 4711059709000
A63: 62 | B63: CFIN | C63: 2018 | D63: =53010796000+'ch receivable'!D63 -> 10785637226000 | E63: =4312284028000+53243540000+54418060000+40007144000 -> 4459952772000 | F63: =D63-E63 -> 6325684454000 | G63: =F63-F62 -> 1614624745000
A64: 63 | B64: CFIN | C64: 2019 | D64: =104364990000+'ch receivable'!D64 -> 11824160110000 | E64: =4956259274000+68766612000+57884367000+21524555000 -> 5104434808000 | F64: =D64-E64 -> 6719725302000 | G64: =F64-F63 -> 394040848000
A65: 64 | B65: CFIN | C65: 2020 | D65: =1924784701000+'ch receivable'!D65 -> 10644136835000 | E65: =3893526206000+17887435000+4029525000+61302666000 -> 3976745832000 | F65: =D65-E65 -> 6667391003000 | G65: =F65-F64 -> -52334299000
A66: 65 | B66: CFIN | C66: 2021 | D66: =126780101000+'ch receivable'!D66 -> 6535206225000 | E66: =1992299748000+55702975000+37155561000+38618480000 -> 2123776764000 | F66: =D66-E66 -> 4411429461000 | G66: =F66-F65 -> -2255961542000
A67: 66 | B67: HDFA | C67: 2017 | D67: =110112228000+13400000000+'ch receivable'!D67 -> 3759856401000 | E67: =2278431361000+5067916000+20732488000 -> 2304231765000 | F67: =D67-E67 -> 1455624636000
A68: 67 | B68: HDFA | C68: 2018 | D68: =313071246000+'ch receivable'!D68 -> 1929809609000 | E68: =1253447628000+996007000+20133766000 -> 1274577401000 | F68: =D68-E68 -> 655232208000 | G68: =F68-F67 -> -800392428000
A69: 68 | B69: HDFA | C69: 2019 | D69: =458031964000+5274544000+'ch receivable'!D69 -> 1017146669000 | E69: =474112492000+350266000+52854105000 -> 527316863000 | F69: =D69-E69 -> 489829806000 | G69: =F69-F68 -> -165402402000
A70: 69 | B70: HDFA | C70: 2020 | D70: =265588728000+22267157000+'ch receivable'!D70 -> 624950495000 | E70: =185543806000+15534000+204672000+24797857000 -> 210561869000 | F70: =D70-E70 -> 414388626000 | G70: =F70-F69 -> -75441180000
A71: 70 | B71: HDFA | C71: 2021 | D71: =90219758000+12250000+'ch receivable'!D71 -> 1116346993000 | E71: =545484500000+518376000+8398769000 -> 554401645000 | F71: =D71-E71 -> 561945348000 | G71: =F71-F70 -> 147556722000
A72: 71 | B72: MAYA | C72: 2017 | D72: =54985000000+7145888000000+'ch receivable'!D72 -> 62549456000000 | E72: =360322000000+1123803000000+61509693000000+4202000000+80831000000+301712000000 -> 63380563000000 | F72: =D72-E72 -> -831107000000
A73: 72 | B73: MAYA | C73: 2018 | D73: =63474000000+6664797000000+'ch receivable'!D73 -> 70315020000000 | E73: =379174000000+1413974000000+70096562000000+6167000000+128770000000+301433000000 -> 72326080000000 | F73: =D73-E73 -> -2011060000000 | G73: =F73-F72 -> -1179953000000
A74: 73 | B74: MAYA | C74: 2019 | D74: =230306000000+4948349000000+74330000000+3267323000000+'ch receivable'!D74 -> 77587817000000 | E74: =368475000000+77009109000000+2800000000+170402000000+366965000000 -> 77917751000000 | F74: =D74-E74 -> -329934000000 | G74: =F74-F73 -> 1681126000000
A75: 74 | B75: MAYA | C75: 2020 | D75: =291498000000+2169548000000+1020397000000+6982761000000+'ch receivable'!D75 -> 64369231000000 | E75: =319304000000+72357421000000+2769865000000+108617000000+447323000000 -> 76002530000000 | F75: =D75-E75 -> -11633299000000 | G75: =F75-F74 -> -11303365000000
A76: 75 | B76: MAYA | C76: 2021 | D76: =285992000000+3508714000000+913767000000+'ch receivable'!D76 -> 74269770000000 | E76: =334117000000+98720992000000+3459974000000+105401000000+385456000000 -> 103005940000000 | F76: =D76-E76 -> -28736170000000 | G76: =F76-F75 -> -17102871000000
A77: 76 | B77: PADI | C77: 2017 | D77: =31223978665+'ch receivable'!D77 -> 69456523574 | E77: 21883000000 | F77: =D77-E77 -> 47573523574
A78: 77 | B78: PADI | C78: 2018 | D78: =13789678117+'ch receivable'!D78 -> 35443615175 | E78: 18396000000 | F78: =D78-E78 -> 17047615175 | G78: =F78-F77 -> -30525908399
A79: 78 | B79: PADI | C79: 2019 | D79: =11064399913+'ch receivable'!D79 -> 24185104415 | E79: 11557000000 | F79: =D79-E79 -> 12628104415 | G79: =F79-F78 -> -4419510760
A80: 79 | B80: PADI | C80: 2020 | D80: =5645060299+'ch receivable'!D80 -> 27824172197 | E80: 19252000000 | F80: =D80-E80 -> 8572172197 | G80: =F80-F79 -> -4055932218
A81: 80 | B81: PADI | C81: 2021 | D81: =9312168150+'ch receivable'!D81 -> 18258620939 | E81: 8897000000 | F81: =D81-E81 -> 9361620939 | G81: =F81-F80 -> 789448742
A82: 81 | B82: PNLF | C82: 2017 | D82: =3473238000000+'ch receivable'!D82+25338000000+3369000000 -> 3635822000000 | E82: =132865000000+13973000000+55100000000+39604000000 -> 241542000000 | F82: =D82-E82 -> 3394280000000
A83: 82 | B83: PNLF | C83: 2018 | D83: =3791567000000+23105000000+67000000+'ch receivable'!D83 -> 3988086000000 | E83: =160354000000+3467000000+40448000000+45745000000+40236000000 -> 290250000000 | F83: =D83-E83 -> 3697836000000 | G83: =F83-F82 -> 303556000000
A84: 83 | B84: PNLF | C84: 2019 | D84: =39607000000+3869897000000+4000000+'ch receivable'!D84 -> 4132189000000 | E84: =206457000000+3596000000+52931000000+50325000000 -> 313309000000 | F84: =D84-E84 -> 3818880000000 | G84: =F84-F83 -> 121044000000
A85: 84 | B85: PNLF | C85: 2020 | D85: =5615213000000+68365000000+73000000+'ch receivable'!D85 -> 6003987000000 | E85: =301744000000+3477000000+53090000000+53328000000 -> 411639000000 | F85: =D85-E85 -> 5592348000000 | G85: =F85-F84 -> 1773468000000
A86: 85 | B86: PNLF | C86: 2021 | D86: =5988442000000+69001000000+116000000+'ch receivable'!D86 -> 6403757000000 | E86: =199177000000+4413000000+62717000000+43370000000 -> 309677000000 | F86: =D86-E86 -> 6094080000000 | G86: =F86-F85 -> 501732000000
A87: 86 | B87: SDRA | C87: 2017 | D87: =231509000000+2146912000000+148392000000+840996000000+'ch receivable'!D87 -> 22070684000000 | E87: =16928615000000+87126000000+42004000000+16888000000+2035125000000+50822000000+2035125000000 -> 21195705000000 | F87: =D87-E87 -> 874979000000
A88: 87 | B88: SDRA | C88: 2018 | D88: =317707000000+1787472000000+135408000000+'ch receivable'!D88 -> 24849398000000 | E88: =15391187000000+84576000000+1664000000+17828000000+4745400000000+45790000000 -> 20286445000000 | F88: =D88-E88 -> 4562953000000 | G88: =F88-F87 -> 3687974000000
A89: 88 | B89: SDRA | C89: 2019 | D89: =347521000000+2153248000000+450351000000+2375870000000+'ch receivable'!D89 -> 32396746000000 | E89: =19065370000000+153093000000+2285000000+24398000000+8024775000000+41440000000 -> 27311361000000 | F89: =D89-E89 -> 5085385000000 | G89: =F89-F88 -> 522432000000
A90: 89 | B90: SDRA | C90: 2020 | D90: =394228000000+1115558000000+328308000000+901236000000+'ch receivable'!D90 -> 32984592000000 | E90: =18492074000000+104339000000+31525000000+18104000000+10858500000000+47129000000 -> 29551671000000 | F90: =D90-E90 -> 3432921000000 | G90: =F90-F89 -> -1652464000000
A91: 90 | B91: SDRA | C91: 2021 | D91: =417810000000+1317798000000+222075000000+1960745000000+'ch receivable'!D91 -> 37679601000000 | E91: =23848020000000+66983000000+36120000000+17623000000+8941200000000+47129000000 -> 32957075000000 | F91: =D91-E91 -> 4722526000000 | G91: =F91-F90 -> 1289605000000
A92: 91 | B92: SMMA | C92: 2017 | D92: =4351508000000+845229000000+'ch receivable'!D92 -> 31297311000000 | E92: =23744668000000+152099000000+221840000000+2705859000000 -> 26824466000000 | F92: =D92-E92 -> 4472845000000
A93: 92 | B93: SMMA | C93: 2018 | D93: =3980657000000+1688695000000+'ch receivable'!D93 -> 34542046000000 | E93: =24457183000000+95891000000+194613000000+3090368000000 -> 27838055000000 | F93: =D93-E93 -> 6703991000000 | G93: =F93-F92 -> 2231146000000
A94: 93 | B94: SMMA | C94: 2019 | D94: =3563777000000+1785782000000+'ch receivable'!D94 -> 37117536000000 | E94: =28911530000000+98609000000+195530000000+3140301000000 -> 32345970000000 | F94: =D94-E94 -> 4771566000000 | G94: =F94-F93 -> -1932425000000
A95: 94 | B95: SMMA | C95: 2020 | D95: =2154135000000+4935948000000+'ch receivable'!D95 -> 35519474000000 | E95: =35177072000000+143900000000+253640000000+3013529000000 -> 38588141000000 | F95: =D95-E95 -> -3068667000000 | G95: =F95-F94 -> -7840233000000
A96: 95 | B96: SMMA | C96: 2021 | D96: =6413194000000+2820547000000+'ch receivable'!D96 -> 34553205000000 | E96: =42257556000000+119985000000+237008000000+3485895000000 -> 46100444000000 | F96: =D96-E96 -> -11547239000000 | G96: =F96-F95 -> -8478572000000
A97: 96 | B97: WOMF | C97: 2017 | D97: =684303000000+'ch receivable'!D97 -> 7538515000000 | E97: =3082884000000+69022000000+30000000+148307000000 -> 3300243000000 | F97: =D97-E97 -> 4238272000000
A98: 97 | B98: WOMF | C98: 2018 | D98: =1243576000000+'ch receivable'!D98 -> 8558988000000 | E98: =4559701000000+96114000000+3093000000+128944000000 -> 4787852000000 | F98: =D98-E98 -> 3771136000000 | G98: =F98-F97 -> -467136000000
A99: 98 | B99: WOMF | C99: 2019 | D99: =751561000000+'ch receivable'!D99 -> 8003350000000 | E99: =3622876000000+92563000000+39337000000+135970000000 -> 3890746000000 | F99: =D99-E99 -> 4112604000000 | G99: =F99-F98 -> 341468000000
A100: 99 | B100: WOMF | C100: 2020 | D100: =634520000000+'ch receivable'!D100 -> 4996069000000 | E100: =1743411000000+40470000000+2564000000+126636000000 -> 1913081000000 | F100: =D100-E100 -> 3082988000000 | G100: =F100-F99 -> -1029616000000
...

Sheet NCO
A1: No | B1: Kode Emiten | C1: Tahun | D1: Total Asset | E1: Current Assets | F1: Total Investment | G1: Advance | H1: Investment and advance | I1: Total Liabilities | J1: Current Liabilities | K1: Long Term Debt | L1: aset | M1: Liability | N1: NCO | O1: ∆NCO
A2: 1 | B2: ASTJ | C2: 2017 | D2: 446108163202 | E2: 188346950854 | F2: =103908836000+3234710450+61848752000+1620816770 -> 170613115220 | G2: 3610490079 | H2: =F2+G2 -> 174223605299 | I2: 234660000000 | J2: =234663726530-6310038845-15163595819 -> 213190091866 | K2: 15163595819 | L2: =(D2-E2-H2) -> 83537607049 | M2: =I2-J2-K2 -> 6306312315 | N2: =L2-M2 -> 77231294734
A3: 2 | B3: ASTJ | C3: 2018 | D3: 478439333039 | E3: 218515004183 | F3: =84331935000+3550789980+71177900000+1895208583 -> 160955833563 | G3: 3356888543 | H3: =F3+G3 -> 164312722106 | I3: 258810000000 | J3: =258813437264-5755573881-11221131258 -> 241836732125 | K3: 11221131258 | L3: =(D3-E3-H3) -> 95611606750 | M3: =I3-J3-K3 -> 5752136617 | N3: =L3-M3 -> 89859470133 | O3: =N3-N2 -> 12628175399
A4: 3 | B4: ASTJ | C4: 2019 | D4: 447670324778 | E4: 206936619136 | F4: =70658560550+3013810200+2091379533+1000000000 -> 76763750283 | G4: 8090524237 | H4: =F4+G4 -> 84854274520 | I4: 238310000000 | J4: =238307219450-1559666255-5816748324 -> 230930804871 | K4: 5816748324 | L4: =(D4-E4-H4) -> 155879431122 | M4: =I4-J4-K4 -> 1562446805 | N4: =L4-M4 -> 154316984317 | O4: =N4-N3 -> 64457514184
A5: 4 | B5: ASTJ | C5: 2020 | D5: 365763908254 | E5: 155993828988 | F5: =53165125250+3389308660+38807515000+2311324759+1000000000 -> 98673273669 | G5: 5338247012 | H5: =F5+G5 -> 104011520681 | I5: 156230000000 | J5: =156229284960-8520962475-10964575454 -> 136743747031 | K5: 10964575454 | L5: =(D5-E5-H5) -> 105758558585 | M5: =I5-J5-K5 -> 8521677515 | N5: =L5-M5 -> 97236881070 | O5: =N5-N4 -> -57080103247
A6: 5 | B6: ASTJ | C6: 2021 | D6: 527852244647 | E6: 236157460614 | F6: =122869225125+2252634930+56976096000+2184084778+1000000000 -> 185282040833 | G6: 8077944677 | H6: =F6+G6 -> 193359985510 | I6: 219400000000 | J6: =219398368810-3324384530-24080932611 -> 191993051669 | K6: 24080932611 | L6: =(D6-E6-H6) -> 98334798523 | M6: =I6-J6-K6 -> 3326015720 | N6: =L6-M6 -> 95008782803 | O6: =N6-N5 -> -2228098267
A7: 6 | B7: ASMI | C7: 2017 | D7: 858490283480 | E7: 265738628652 | F7: =203559267612+199781087636+120962510367+7313197000+1901731313 -> 533517793928 | G7: 2514688946 | H7: =F7+G7 -> 536032482874 | I7: 403521972590 | J7: =403521972950-36619253244-14642983000-233483356743-18898350616 -> 99878029347 | K7: 36619253244 | L7: =(D7-E7-H7) -> 56719171954 | M7: =I7-J7-K7 -> 267024689999 | N7: =L7-M7 -> -210305518045
A8: 7 | B8: ASMI | C8: 2018 | D8: 969866560976 | E8: 320101149649 | F8: =231082763503+229934584995+122306586000+7058080000+1901731313 -> 592283745811 | G8: 7717961287 | H8: =F8+G8 -> 600001707098 | I8: 450272263738 | J8: =1113802274+89246619825+21790129723+545482187+12089534682 -> 124785568691 | K8: 37067363957 | L8: =(D8-E8-H8) -> 49763704229 | M8: =I8-J8-K8 -> 288419331090 | N8: =L8-M8 -> -238655626861 | O8: =N8-N7 -> -28350108816
A9: 8 | B9: ASMI | C9: 2019 | D9: 975687462693 | E9: 317063416058 | F9: =216749320000+351654846593+18196797270+7268626000 -> 593869589863 | G9: 11190946006 | H9: =F9+G9 -> 605060535869 | I9: 445392630259 | J9: =1534991608+71566715136+15627966323+617272865+5147113476 -> 94494059408 | K9: 61784924599 | L9: =(D9-E9-H9) -> 53563510766 | M9: =I9-J9-K9 -> 289113646252 | N9: =L9-M9 -> -235550135486 | O9: =N9-N8 -> 3105491375
A10: 9 | B10: ASMI | C10: 2020 | D10: 990991744064 | E10: 528285486877 | F10: =61000000000+299816222397+18196797270+5416648000 -> 384429667667 | G10: 12967320338 | H10: =F10+G10 -> 397396988005 | I10: 547541424689 | J10: =460283470+36757191276+22406237281+391760750+1230443792 -> 61245916569 | K10: 56237287760 | L10: =(D10-E10-H10) -> 65309269182 | M10: =I10-J10-K10 -> 430058220360 | N10: =L10-M10 -> -364748951178 | O10: =N10-N9 -> -129198815692
A11: 10 | B11: ASMI | C11: 2021 | D11: 981089572950 | E11: 418850978640 | F11: =79736000000+323916974817+10377006750+47111957330 -> 461141938897 | G11: 25737796822 | H11: =F11+G11 -> 486879735719 | I11: 518209589004 | J11: =3237593569+3491647273+31148406534+633605432+4987600229 -> 43498853037 | K11: 27945351289 | L11: =(D11-E11-H11) -> 75358858591 | M11: =I11-J11-K11 -> 446765384678 | N11: =L11-M11 -> -371406526087 | O11: =N11-N10 -> -6657574909
A12: 11 | B12: BBNI | C12: 2017 | D12: 709330084000000 | E12: 536647607577664 | F12: =36049899000000+679122000000+79849452000000+713423000000 -> 117291896000000 | G12: 2318516000000 | H12: =F12+G12 -> 119610412000000 | I12: 584086818000000 | J12: =4867547000000+492747948000000+11734207000000+971479000000+80425000000+4093855000000 -> 514495461000000 | K12: =2390066000000+2986279000000+44670741000000 -> 50047086000000 | L12: =(D12-E12-H12) -> 53072064422336 | M12: =I12-J12-K12 -> 19544271000000 | N12: =L12-M12 -> 33527793422336
A13: 12 | B13: BBNI | C13: 2018 | D13: 808572011000000 | E13: 628563451000000 | F13: =32044270000000+86791402000000+603923000000 -> 119439595000000 | G13: 2337403000000 | H13: =F13+G13 -> 121776998000000 | I13: 671237546000000 | J13: =671237546000000-99953000000-52024506000000-2987464-14608465000000-177519000000-4416613000000-21524329000000-322028000000 -> 578064130012536 | K13: =21524329000000+2987464000000+52024506000000+99953000000 -> 76636252000000 | L13: =(D13-E13-H13) -> 58231562000000 | M13: =I13-J13-K13 -> 16537163987464 | N13: =L13-M13 -> 41694398012536 | O13: =N13-N12 -> 8166604590200
A14: 13 | B14: BBNI | C14: 2019 | D14: 845605208000000 | E14: 683514765000000 | F14: =27161751000000+411442000000+81029020000000+523103000000 -> 109125316000000 | G14: 2609259000000 | H14: =F14+G14 -> 111734575000000 | I14: 688489442000000 | J14: =688489442000000-99965000000-57235500000000-2985052000000-14900956000000-185019000000-5341440000000-203054000000-2183403000000 -> 605355053000000 | K14: =2183403000000+2985052000000+57235500000000+99965000000 -> 62503920000000 | L14: =(D14-E14-H14) -> 50355868000000 | M14: =I14-J14-K14 -> 20630469000000 | N14: =L14-M14 -> 29725399000000 | O14: =N14-N13 -> -11968999012536
A15: 14 | B15: BBNI | C15: 2020 | D15: 891337425000000 | E15: 698136164000000 | F15: =29686597000000+8666091000000+90659318000000+813087000000 -> 129825093000000 | G15: 2807092000000 | H15: =F15+G15 -> 132632185000000 | I15: 746235663000000 | J15: =746235663000000-99979000000-44114314000000-2985011000000-18280485000000-1421914000000-5500360000000-2590268000000-414280000000 -> 670829052000000 | K15: =2590268000000+2985011000000+44114314000000+99975000000 -> 49789568000000 | L15: =(D15-E15-H15) -> 60569076000000 | M15: =I15-J15-K15 -> 25617043000000 | N15: =L15-M15 -> 34952033000000 | O15: =N15-N14 -> 5226634000000
A16: 15 | B16: BBNI | C16: 2021 | D16: 964837692000000 | E16: 735846646000000 | F16: =8688406000000+111428330000000+22010968000000+25802962000000+829763000000 -> 168760429000000 | G16: 3095927000000 | H16: =F16+G16 -> 171856356000000 | I16: 838317715000000 | J16: =838317715000000-15764682000000-32457936000000-2986530000000-20542001000000-2276397000000-5588069000000-1828652000000-109948000000 -> 756763500000000 | K16: =1828652000000+2986530000000+32457936000000+15764682000000 -> 53037800000000 | L16: =(D16-E16-H16) -> 57134690000000 | M16: =I16-J16-K16 -> 28516415000000 | N16: =L16-M16 -> 28618275000000 | O16: =N16-N15 -> -6333758000000
A17: 16 | B17: BBTN | C17: 2017 | D17: 261365267000000 | E17: 235478618000000 | F17: =7706031000000+8183973000000 -> 15890004000000 | G17: =769454000000+413079000000 -> 1182533000000 | H17: =F17+G17 -> 17072537000000 | I17: 223937463000000 | J17: =223937463000000-2999319000000-5612462000000-7991053000000-20480459000000-8081000000-1385000000000-85481932000000 -> 99979157000000 | K17: =85481932000000+7991053000000+2999319000000 -> 96472304000000 | L17: =(D17-E17-H17) -> 8814112000000 | M17: =I17-J17-K17 -> 27486002000000 | N17: =L17-M17 -> -18671890000000
A18: 17 | B18: BBTN | C18: 2018 | D18: 306436194000000 | E18: 279700978000000 | F18: =5848485000000+9393138000000 -> 15241623000000 | G18: =1270875000000+409138000000 -> 1680013000000 | H18: =F18+G18 -> 16921636000000 | I18: 263784017000000 | J18: =263784017000000-2999519000000-6217814000000-15499493000000-20644760000000-528148000000-935000000000-115462283000000 -> 101497000000000 | K18: =115462283000000+15499493000000+2999519000000 -> 133961295000000 | L18: =(D18-E18-H18) -> 9813580000000 | M18: =I18-J18-K18 -> 28325722000000 | N18: =L18-M18 -> -18512142000000 | O18: =N18-N17 -> 159748000000
A19: 18 | B19: BBTN | C19: 2019 | D19: 311776828000000 | E19: 264961513000000 | F19: =8084671000000+11053601000000+1875221000000 -> 21013493000000 | G19: =402428000000+803479000000 -> 1205907000000 | H19: =F19+G19 -> 22219400000000 | I19: 269451682000000 | J19: =269451682000000-5999669000000-5736637000000-19783552000000-22465657000000-487052000000-935000000000-113929798000000 -> 100114317000000 | K19: =113929768000000+22465657000000+5999669000000 -> 142395094000000 | L19: =(D19-E19-H19) -> 24595915000000 | M19: =I19-J19-K19 -> 26942271000000 | N19: =L19-M19 -> -2346356000000 | O19: =N19-N18 -> 16165786000000
A20: 19 | B20: BBTN | C20: 2020 | D20: 361208406000000 | E20: 282901116000000 | F20: =3203966000000+56287751000000+954955000000 -> 60446672000000 | G20: =402428000000+386848000000 -> 789276000000 | H20: =F20+G20 -> 61235948000000 | I20: 321376142000000 | J20: =321376142000000-10194432000000-6666875000000-6489000000-15810466000000-23807138000000-22787000000-196071000000-147858608000000 -> 116813276000000 | K20: =147858608000000+23807138000000+10194432000000 -> 181860178000000 | L20: =(D20-E20-H20) -> 17071342000000 | M20: =I20-J20-K20 -> 22702688000000 | N20: =L20-M20 -> -5631346000000 | O20: =N20-N19 -> -3284990000000
A21: 20 | B21: BBTN | C21: 2021 | D21: 371868311000000 | E21: 302112274000000 | F21: =2230905000000+46080298000000+1598325000000 -> 49909528000000 | G21: =402428000000+367925000000 -> 770353000000 | H21: =F21+G21 -> 50679881000000 | I21: 327693592000000 | J21: =327693592000000-8759744000000-6618300000000-3644000000-12371708000000-22062291000000-17741000000-454140000000-146520589000000 -> 130885435000000 | K21: =146520589000000+22062291000000+8759744000000 -> 177342624000000 | L21: =(D21-E21-H21) -> 19076156000000 | M21: =I21-J21-K21 -> 19465533000000 | N21: =L21-M21 -> -389377000000 | O21: =N21-N20 -> 5241969000000
A22: 21 | B22: BCAP | C22: 2017 | D22: 19883263000000 | E22: 6553454000000 | F22: =7012000000+269888000000+3998739000000 -> 4275639000000 | G22: =20083000000+40830000000 -> 60913000000 | H22: =F22+G22 -> 4336552000000 | I22: 14255743000000 | J22: =533534000000+8443515000000+197257000000+14726000000+172534000000+27056000000 -> 9388622000000 | K22: =288999000000+2002729000000+556018000000+105067000000+294208000000+47394000000 -> 3294415000000 | L22: =(D22-E22-H22) -> 8993257000000 | M22: =I22-J22-K22 -> 1572706000000 | N22: =L22-M22 -> 7420551000000
A23: 22 | B23: BCAP | C23: 2018 | D23: 18762724000000 | E23: 5246022000000 | F23: =254124000000+3951878000000 -> 4206002000000 | G23: =20689000000+37985000000 -> 58674000000 | H23: =F23+G23 -> 4264676000000 | I23: 13015396000000 | J23: =823273000000+7604794000000+740092000000+37937000000+113873000000+22277000000 -> 9342246000000 | K23: =149244000000+1442761000000+393305000000+12605000000+365566000000+56620000000 -> 2420101000000 | L23: =(D23-E23-H23) -> 9252026000000 | M23: =I23-J23-K23 -> 1253049000000 | N23: =L23-M23 -> 7998977000000 | O23: =N23-N22 -> 578426000000
A24: 23 | B24: BCAP | C24: 2019 | D24: 18385005000000 | E24: 4131645000000 | F24: =419938000000+3601868000000 -> 4021806000000 | G24: =32263000000+40517000000 -> 72780000000 | H24: =F24+G24 -> 4094586000000 | I24: 12839026000000 | J24: =409096000000+7895637000000+393715000000+48486000000+201472000000+313175000000+32272000000 -> 9293853000000 | K24: =165766000000+1264045000000+287209000000+5339000000+318093000000+35360000000 -> 2075812000000 | L24: =(D24-E24-H24) -> 10158774000000 | M24: =I24-J24-K24 -> 1469361000000 | N24: =L24-M24 -> 8689413000000 | O24: =N24-N23 -> 690436000000
A25: 24 | B25: BCAP | C25: 2020 | D25: 19101546000000 | E25: 4672634000000 | F25: =349897000000+3695181000000 -> 4045078000000 | G25: =44891000000+27870000000 -> 72761000000 | H25: =F25+G25 -> 4117839000000 | I25: 14007712000000 | J25: =753682000000+8315127000000+490103000000+173797000000+421663000000+498855000000+25398000000 -> 10678625000000 | K25: =232033000000+976791000000+194891000000+1000000000+298673000000+9523000000 -> 1712911000000 | L25: =(D25-E25-H25) -> 10311073000000 | M25: =I25-J25-K25 -> 1616176000000 | N25: =L25-M25 -> 8694897000000 | O25: =N25-N24 -> 5484000000
A26: 25 | B26: BCAP | C26: 2021 | D26: 21653968000000 | E26: 5431154000000 | F26: 4582657000000 | G26: =46791000000+2878000000 -> 49669000000 | H26: =F26+G26 -> 4632326000000 | I26: 15646157000000 | J26: =11123446000000+130675000000+69299000000+385506000000+347083000000+29696000000 -> 12085705000000 | K26: =926766000000+248233000000+179253000000+3065000000+299155000000+13705000000 -> 1670177000000 | L26: =(D26-E26-H26) -> 11590488000000 | M26: =I26-J26-K26 -> 1890275000000 | N26: =L26-M26 -> 9700213000000 | O26: =N26-N25 -> 1005316000000
A27: 26 | B27: BDMN | C27: 2017 | D27: 178257092000000 | E27: 140368274000000 | F27: =19949000000+16039713000000+10974343000000+296028000000+122669000000 -> 27452702000000 | G27: 270146000000 | H27: =F27+G27 -> 27722848000000 | I27: 139084940000000 | J27: =129971000000+101766847000000+4634513000000+116526000000 -> 106647857000000 | K27: =10434000000+214100000000+9296065000000+661000000000+3047182000000+6747104000000 -> 19975885000000 | L27: =(D27-E27-H27) -> 10165970000000 | M27: =I27-J27-K27 -> 12461198000000 | N27: =L27-M27 -> -2295228000000
A28: 27 | B28: BDMN | C28: 2018 | D28: 186762189000000 | E28: 143923553000000 | F28: =767000000+9147993000000+10972634000000+126763000000 -> 20248157000000 | G28: 352833000000 | H28: =F28+G28 -> 20600990000000 | I28: 144822368000000 | J28: =118980000000+107576816000000+3152422000000+87011000000 -> 110935229000000 | K28: =93000000000+8818907000000+728000000000+11828091000000+87011000000+25000000000+248145000000 -> 21828154000000 | L28: =(D28-E28-H28) -> 22237646000000 | M28: =I28-J28-K28 -> 12058985000000 | N28: =L28-M28 -> 10178661000000 | O28: =N28-N27 -> 12473889000000
A29: 28 | B29: BDMN | C29: 2019 | D29: 193533970000000 | E29: 154362647000000 | F29: =9405926000000+14227098000000+3732413000000+115592000000+908858000000 -> 28389887000000 | G29: 444931000000 | H29: =F29+G29 -> 28834818000000 | I29: 148116943000000 | J29: =590957000000+109200953000000+266031000000+4215474000000+473076000000 -> 114746491000000 | K29: =490000000000+12319342000000+40000000000+597000000000+10350058000000+25000000 -> 23796425000000 | L29: =(D29-E29-H29) -> 10336505000000 | M29: =I29-J29-K29 -> 9574027000000 | N29: =L29-M29 -> 762478000000 | O29: =N29-N28 -> -9416183000000
A30: 29 | B30: BDMN | C30: 2020 | D30: 200890068000000 | E30: 145488655000000 | F30: =4689271000000+25534635000000+12126419000000+107213000000+924518000000 -> 43382056000000 | G30: 253386000000 | H30: =F30+G30 -> 43635442000000 | I30: 157314569000000 | J30: =298081000000+123435123000000+78494000000+2399231000000+300857000000 -> 126511786000000 | K30: =430000000000+7483559000000+478000000000+8952442000000 -> 17344001000000 | L30: =(D30-E30-H30) -> 11765971000000 | M30: =I30-J30-K30 -> 13458782000000 | N30: =L30-M30 -> -1692811000000 | O30: =N30-N29 -> -2455289000000
A31: 30 | B31: BDMN | C31: 2021 | D31: 192239698000000 | E31: 141166331000000 | F31: =5514043000000+30337737000000+82078000000+949009000000 -> 36882867000000 | G31: 281055000000 | H31: =F31+G31 -> 37163922000000 | I31: 147156640000000 | J31: =962547000000+120106770000000+65813000000+2218774000000+212184000000 -> 123566088000000 | K31: =270000000000+6078234000000+402000000000+666667000000+3608879000000+25000000000 -> 11050780000000 | L31: =(D31-E31-H31) -> 13909445000000 | M31: =I31-J31-K31 -> 12539772000000 | N31: =L31-M31 -> 1369673000000 | O31: =N31-N30 -> 3062484000000
A32: 31 | B32: BFIN | C32: 2017 | D32: 16483273000000 | E32: 15814055000000 | F32: 0 | G32: 43071000000 | H32: =F32+G32 -> 43071000000 | I32: 11579007000000 | J32: =6819052000000+140151000000+293527000000+199716000000 -> 7452446000000 | K32: =3909411000000+1612000000 -> 3911023000000 | L32: =(D32-E32-H32) -> 626147000000 | M32: =I32-J32-K32 -> 215538000000 | N32: =L32-M32 -> 410609000000
A33: 32 | B33: BFIN | C33: 2018 | D33: 19117305000000 | E33: 18234081000000 | F33: 0 | G33: 53430000000 | H33: =F33+G33 -> 53430000000 | I33: 12913509000000 | J33: =6899860000000+67063000000+287878000000+202498000000 -> 7457299000000 | K33: =5196220000000+1758000000 -> 5197978000000 | L33: =(D33-E33-H33) -> 829794000000 | M33: =I33-J33-K33 -> 258232000000 | N33: =L33-M33 -> 571562000000 | O33: =N33-N32 -> 160953000000
A34: 33 | B34: BFIN | C34: 2019 | D34: 19089633000000 | E34: 18211551000000 | F34: 0 | G34: 73133000000 | H34: =F34+G34 -> 73133000000 | I34: 13009453000000 | J34: =7730021000000+73271000000+796709000000+258337000000 -> 8858338000000 | K34: =3758283000000+2261000000 -> 3760544000000 | L34: =(D34-E34-H34) -> 804949000000 | M34: =I34-J34-K34 -> 390571000000 | N34: =L34-M34 -> 414378000000 | O34: =N34-N33 -> -157184000000
A35: 34 | B35: BFIN | C35: 2020 | D35: 15200531000000 | E35: 14248625000000 | F35: 0 | G35: 24412000000 | H35: =F35+G35 -> 24412000000 | I35: 8594377000000 | J35: =4794844000000+101719000000+194038000000+154211000000 -> 5244812000000 | K35: =2978631000000+1318000000 -> 2979949000000 | L35: =(D35-E35-H35) -> 927494000000 | M35: =I35-J35-K35 -> 369616000000 | N35: =L35-M35 -> 557878000000 | O35: =N35-N34 -> 143500000000
A36: 35 | B36: BFIN | C36: 2021 | D36: 15635739000000 | E36: 14733402000000 | F36: 0 | G36: 30847000000 | H36: =F36+G36 -> 30847000000 | I36: 8205513000000 | J36: =4789422000000+120131000000+338442000000+115457000000 -> 5363452000000 | K36: =2487483000000+1376000000 -> 2488859000000 | L36: =(D36-E36-H36) -> 871490000000 | M36: =I36-J36-K36 -> 353202000000 | N36: =L36-M36 -> 518288000000 | O36: =N36-N35 -> -39590000000
A37: 36 | B37: BNGA | C37: 2017 | D37: 266305455000000 | E37: 221847408000000 | F37: =13442054000000+24971486000000+3659000000 -> 38417199000000 | G37: =1814214000000+1325541000000 -> 3139755000000 | H37: =F37+G37 -> 41556954000000 | I37: 229354449000000 | J37: =1946166000000+49281023000000+50214272000000+6884335000000+445502000000+2986666000000+1289985000000 -> 113047949000000 | K37: =89821901000000+9478703000000+5403613000000+5809723000000+1596772000000 -> 112110712000000 | L37: =(D37-E37-H37) -> 2901093000000 | M37: =I37-J37-K37 -> 4195788000000 | N37: =L37-M37 -> -1294695000000
A38: 37 | B38: BNGA | C38: 2018 | D38: 266781498000000 | E38: 214889787000000 | F38: =10676225000000+23999772000000+593593000000+3659000000 -> 35273249000000 | G38: =1892270000000+1294384000000 -> 3186654000000 | H38: =F38+G38 -> 38459903000000 | I38: 227200919000000 | J38: =2240191000000+45857151000000+54495883000000+2928693000000+461141000000+3594738000000+930196000000 -> 110507993000000 | K38: =90397184000000+11940900000000+5269757000000+2195916000000+1742417000000 -> 111546174000000 | L38: =(D38-E38-H38) -> 13431808000000 | M38: =I38-J38-K38 -> 5146752000000 | N38: =L38-M38 -> 8285056000000 | O38: =N38-N37 -> 9579751000000
A39: 38 | B39: BNGA | C39: 2019 | D39: 274467227000000 | E39: 224000336000000 | F39: =11962665000000+22160303000000+522857000000+3659000000 -> 34649484000000 | G39: =1644089000000+1373464000000 -> 3017553000000 | H39: =F39+G39 -> 37667037000000 | I39: 231173061000000 | J39: =1781962000000+48943913000000+59316069000000+1364586000000+498541000000+4038684000000+1131727000000 -> 117075482000000 | K39: =87340318000000+10470737000000+7503112000000+2647013000000+1821175000000 -> 109782355000000 | L39: =(D39-E39-H39) -> 12799854000000 | M39: =I39-J39-K39 -> 4315224000000 | N39: =L39-M39 -> 8484630000000 | O39: =N39-N38 -> 199574000000
A40: 39 | B40: BNGA | C40: 2020 | D40: 280943605000000 | E40: 194242397000000 | F40: =9310186000000+55828799000000+2305523000000+3659000000 -> 67448167000000 | G40: =1930704000000+1024632000000 -> 2955336000000 | H40: =F40+G40 -> 70403503000000 | I40: 239890554000000 | J40: =3636684000000+55862547000000+67861369000000+2901556000000+301192000000+5151393000000+1098334000000 -> 136813075000000 | K40: =83805508000000+8656643000000+6565604000000+933433000000+224184000000 -> 100185372000000 | L40: =(D40-E40-H40) -> 16297705000000 | M40: =I40-J40-K40 -> 2892107000000 | N40: =L40-M40 -> 13405598000000 | O40: =N40-N39 -> 4920968000000
A41: 40 | B41: BNGA | C41: 2021 | D41: 310786960000000 | E41: 218958935000000 | F41: =10175922000000+60520764000000+3659000000+1589656000000 -> 72290001000000 | G41: =1461282000000+1138706000000 -> 2599988000000 | H41: =F41+G41 -> 74889989000000 | I41: 267398602000000 | J41: =3239391000000+75477306000000+72565133000000+3059451000000+584187000000+6082833000000+1355055000000 -> 162363356000000 | K41: =93306071000000+1262232000000+5369228000000+1973306000000+226143000000 -> 102136980000000 | L41: =(D41-E41-H41) -> 16938036000000 | M41: =I41-J41-K41 -> 2898266000000 | N41: =L41-M41 -> 14039770000000 | O41: =N41-N40 -> 634172000000
A42: 41 | B42: BNII | C42: 2017 | D42: 173253491000000 | E42: 142245644000000 | F42: =3700535000000+18203948000000+1603591000000 -> 23508074000000 | G42: =51368000000+38434000000+12341000000 -> 102143000000 | H42: =F42+G42 -> 23610217000000 | I42: 152478451000000 | J42: =1176239000000+121291560000000+3861373000000+198800000000+3781938000000 -> 130309910000000 | K42: =595088000000+9426084000000+5054291000000+5290905000000 -> 20366368000000 | L42: =(D42-E42-H42) -> 7397630000000 | M42: =I42-J42-K42 -> 1802173000000 | N42: =L42-M42 -> 5595457000000
A43: 42 | B43: BNII | C43: 2018 | D43: 177532858000000 | E43: 152861374000000 | F43: =188033000000+16539984000000+44457000000 -> 16772474000000 | G43: =88616000000+68328000000+17634000000 -> 174578000000 | H43: =F43+G43 -> 16947052000000 | I43: 152442167000000 | J43: =859282000000+116812388000000+4217922000000+168883000000+3870431000000 -> 125928906000000 | K43: =9805245000000+10558656000000+3293966000000 -> 23657867000000 | L43: =(D43-E43-H43) -> 7724432000000 | M43: =I43-J43-K43 -> 2855394000000 | N43: =L43-M43 -> 4869038000000 | O43: =N43-N42 -> -726419000000
A44: 43 | B44: BNII | C44: 2019 | D44: 169082830000000 | E44: 140755959000000 | F44: =1599041000000+16509217000000+2454895000000 -> 20563153000000 | G44: =62406000000+67546000000+10147000000 -> 140099000000 | H44: =F44+G44 -> 20703252000000 | I44: 142397914000000 | J44: =949936000000+110601006000000+3134059000000+193017000000+3283357000000 -> 118161375000000 | K44: =725580000000+9605315000000+9189435000000+2296054000000 -> 21816384000000 | L44: =(D44-E44-H44) -> 7623619000000 | M44: =I44-J44-K44 -> 2420155000000 | N44: =L44-M44 -> 5203464000000 | O44: =N44-N43 -> 334426000000
A45: 44 | B45: BNII | C45: 2020 | D45: 173224412000000 | E45: 129038323000000 | F45: =1134802000000+24266764000000+10766459000000 -> 36168025000000 | G45: =95657000000+64437000000 -> 160094000000 | H45: =F45+G45 -> 36328119000000 | I45: 146000782000000 | J45: =1172326000000+115003047000000+8236126000000+221494000000+3840214000000 -> 128473207000000 | K45: =608383000000+6393160000000+6041622000000+2297856000000 -> 15341021000000 | L45: =(D45-E45-H45) -> 7857970000000 | M45: =I45-J45-K45 -> 2186554000000 | N45: =L45-M45 -> 5671416000000 | O45: =N45-N44 -> 467952000000
A46: 45 | B46: BNII | C46: 2021 | D46: 168758476000000 | E46: 124990261000000 | F46: =1897444000000+29269256000000+3538336000000 -> 34705036000000 | G46: =75690000000+59602000000 -> 135292000000 | H46: =F46+G46 -> 34840328000000 | I46: 140033353000000 | J46: =809999000000+114898775000000+5162363000000+222417000000+3642641000000 -> 124736195000000 | K46: =274049000000+5305250000000+6917309000000+799174000000 -> 13295782000000 | L46: =(D46-E46-H46) -> 8927887000000 | M46: =I46-J46-K46 -> 2001376000000 | N46: =L46-M46 -> 6926511000000 | O46: =N46-N45 -> 1255095000000
A47: 46 | B47: BNLI | C47: 2017 | D47: 148328370000000 | E47: 112708769000000 | F47: =22802021000000+18887000000+976045000000 -> 23796953000000 | G47: =440287000000+205260000000 -> 645547000000 | H47: =F47+G47 -> 24442500000000 | I47: 126817628000000 | J47: =384169000000+23481197000000+6553603000000+27393067000000+429648000000+2552273000000+145270000000+11338000000+610000000+1032000000+1184496000000+138159000000 -> 62274862000000 | K47: =36017000000+5346400000000+1185243000000+47539650000000+5890842000000 -> 59998152000000 | L47: =(D47-E47-H47) -> 11177101000000 | M47: =I47-J47-K47 -> 4544614000000 | N47: =L47-M47 -> 6632487000000
A48: 47 | B48: BNLI | C48: 2018 | D48: 152892866000000 | E48: 128117544000000 | F48: =14989712000000 -> 14989712000000 | G48: =736804000000+206350000000 -> 943154000000 | H48: =F48+G48 -> 15932866000000 | I48: 130440930000000 | J48: =130440930000000-1068985000000-3715302000000-59465000000--621315000000-17740000000-2747942000000-54219868000000-7026154000000 -> 62206789000000 | K48: =54219868000000+7026154000000+16971000000+3715302000000+1068985000000 -> 66047280000000 | L48: =(D48-E48-H48) -> 8842456000000 | M48: =I48-J48-K48 -> 2186861000000 | N48: =L48-M48 -> 6655595000000 | O48: =N48-N47 -> 23108000000
A49: 48 | B49: BNLI | C49: 2019 | D49: 161451259000000 | E49: 134263488000000 | F49: =16229868000000+1534574000000 -> 17764442000000 | G49: =1241571000000+170723000000 -> 1412294000000 | H49: =F49+G49 -> 19176736000000 | I49: 137413908000000 | J49: =137413908000000-992138000000-1286680000000-56017000000--562970000000-1695446000000-19872000000-55010089000000-5890381000000-12881000000 -> 73013374000000 | K49: =55010089000000+5890381000000+12881000000+1286680000000+992138000000 -> 63192169000000 | L49: =(D49-E49-H49) -> 8011035000000 | M49: =I49-J49-K49 -> 1208365000000 | N49: =L49-M49 -> 6802670000000 | O49: =N49-N48 -> 147075000000
A50: 49 | B50: BNLI | C50: 2020 | D50: 197726097000000 | E50: 142626559000000 | F50: =23256980000000+22272459000000 -> 45529439000000 | G50: =1002530000000+197868000000 -> 1200398000000 | H50: =F50+G50 -> 46729837000000 | I50: 162654644000000 | J50: =162654644000000-9106068000000-105197000000-609738000000-67667000000-1141112000000-8000000-1460535000000-71191551000000-63166000000 -> 78909602000000 | K50: =71191551000000+63166000000+8000000+609738000000+105197000000+9106068000000 -> 81075728000000 | L50: =(D50-E50-H50) -> 8369701000000 | M50: =I50-J50-K50 -> 2669314000000 | N50: =L50-M50 -> 5700387000000 | O50: =N50-N49 -> -1102283000000
A51: 50 | B51: BNLI | C51: 2021 | D51: 234379042000000 | E51: 167969662000000 | F51: =138001000000+40964611000000+14245191000000 -> 55347803000000 | G51: =312857000000+77612000000 -> 390469000000 | H51: =F51+G51 -> 55738272000000 | I51: 197765327000000 | J51: =197765327000000-9329879000000-67200000000-756454000000-1350000000-2011886000000-82778671000000-57224000000 -> 102762663000000 | K51: =82778671000000+57224000000+1350000000+9329879000000 -> 92167124000000 | L51: =(D51-E51-H51) -> 10671108000000 | M51: =I51-J51-K51 -> 2835540000000 | N51: =L51-M51 -> 7835568000000 | O51: =N51-N50 -> 2135181000000
A52: 51 | B52: ADMF | C52: 2017 | D52: 29492933000000 | E52: 28461735000000 | F52: =650000000 -> 650000000 | G52: 43447000000 | H52: =F52+G52 -> 44097000000 | I52: 23747518000000 | J52: =6697104000000+3847182000000+657757000000+72968000000+30178000000+967689000000 -> 12272878000000 | K52: =9296065000000+465100000000+661000000000+40000000000 -> 10462165000000 | L52: =(D52-E52-H52) -> 987101000000 | M52: =I52-J52-K52 -> 1012475000000 | N52: =L52-M52 -> -25374000000
A53: 52 | B53: ADMF | C53: 2018 | D53: 31496441000000 | E53: 29757520000000 | F53: =650000000 -> 650000000 | G53: 68363000000 | H53: =F53+G53 -> 69013000000 | I53: 24468242000000 | J53: =11778092000000+793217000000+35451000000+30174000000+864883000000 -> 13501817000000 | K53: =8818907000000+603000000000+728000000000+40000000000 -> 10189907000000 | L53: =(D53-E53-H53) -> 1669908000000 | M53: =I53-J53-K53 -> 776518000000 | N53: =L53-M53 -> 893390000000 | O53: =N53-N52 -> 918764000000
A54: 53 | B54: ADMF | C54: 2019 | D54: 35116853000000 | E54: 33504454000000 | F54: =650000000 -> 650000000 | G54: 33746000000 | H54: =F54+G54 -> 34396000000 | I54: 27038058000000 | J54: =10350058000000+1500000000000+973379000000+38616000000+364455000000+1058152000000 -> 14284660000000 | K54: =9825860000000+572800000000+597000000000+40000000000 -> 11035660000000 | L54: =(D54-E54-H54) -> 1578003000000 | M54: =I54-J54-K54 -> 1717738000000 | N54: =L54-M54 -> -139735000000 | O54: =N54-N53 -> -1033125000000
A55: 54 | B55: ADMF | C55: 2020 | D55: 29230513000000 | E55: 27477745000000 | F55: 650000000 | G55: 3584000000 | H55: =F55+G55 -> 4234000000 | I55: 21305238000000 | J55: =8952441000000+187500000000+1012886000000+38330000000+185896000000+946096000000 -> 11323149000000 | K55: =6824636000000+323690000000+478000000000 -> 7626326000000 | L55: =(D55-E55-H55) -> 1748534000000 | M55: =I55-J55-K55 -> 2355763000000 | N55: =L55-M55 -> -607229000000 | O55: =N55-N54 -> -467494000000
A56: 55 | B56: ADMF | C56: 2021 | D56: 23725885000000 | E56: 21356445000000 | F56: 650000000 | G56: 762000000 | H56: =F56+G56 -> 1412000000 | I56: 14838879000000 | J56: =3608879000000+1345834000000+1034561000000+40461000000+173686000000+953468000000 -> 7156889000000 | K56: =5417918000000+155350000000+402000000000 -> 5975268000000 | L56: =(D56-E56-H56) -> 2368028000000 | M56: =I56-J56-K56 -> 1706722000000 | N56: =L56-M56 -> 661306000000 | O56: =N56-N55 -> 1268535000000
A57: 56 | B57: BVIC | C57: 2017 | D57: 28825608648000 | E57: 19725075731000 | F57: =7897783120000 -> 7897783120000 | G57: 1797400000 | H57: =F57+G57 -> 7899580520000 | I57: 24483975280000 | J57: =4494773000+20774972177000+2236882484000+41968503000+76384504000 -> 23134702441000 | K57: =1140423161000 -> 1140423161000 | L57: =(D57-E57-H57) -> 1200952397000 | M57: =I57-J57-K57 -> 208849678000 | N57: =L57-M57 -> 992102719000
A58: 57 | B58: BVIC | C58: 2018 | D58: 30172315337000 | E58: 19797069229000 | F58: =6724520646000+1000011192000 -> 7724531838000 | G58: 0 | H58: =F58+G58 -> 7724531838000 | I58: 25808570240000 | J58: =4393198000+20636380394000+1835799330000+65331129000+73621459000 -> 22615525510000 | K58: =1302663597000+1585722555000 -> 2888386152000 | L58: =(D58-E58-H58) -> 2650714270000 | M58: =I58-J58-K58 -> 304658578000 | N58: =L58-M58 -> 2346055692000 | O58: =N58-N57 -> 1353952973000
A59: 58 | B59: BVIC | C59: 2019 | D59: 30456458802000 | E59: 19404658911000 | F59: =7900239715000+1000005891 -> 7901239720891 | G59: 10334090000 | H59: =F59+G59 -> 7911573810891 | I59: 25782313852000 | J59: =2077421000+21791637063000+909309808000+29976241000+65755469000 -> 22798756002000 | K59: =1000000721000+1780135010000 -> 2780135731000 | L59: =(D59-E59-H59) -> 3140226080109 | M59: =I59-J59-K59 -> 203422119000 | N59: =L59-M59 -> 2936803961109 | O59: =N59-N58 -> 590748269109
A60: 59 | B60: BVIC | C60: 2020 | D60: 26221407472000 | E60: 16797468234000 | F60: =6406670842000+447804800000 -> 6854475642000 | G60: 11557440000 | H60: =F60+G60 -> 6866033082000 | I60: 22197849857000 | J60: =22197849857000-1544029002000-179217199000 -> 20474603656000 | K60: 1544029002000 | L60: =(D60-E60-H60) -> 2557906156000 | M60: =I60-J60-K60 -> 179217199000 | N60: =L60-M60 -> 2378688957000 | O60: =N60-N59 -> -558115004109
A61: 60 | B61: BVIC | C61: 2021 | D61: 24947143045000 | E61: 16671877148000 | F61: =5175486652000+690714570000 -> 5866201222000 | G61: 19155501000 | H61: =F61+G61 -> 5885356723000 | I61: 20702225559000 | J61: =335926000+18084871983000+1037173068000+12584904000+43884161000 -> 19178850042000 | K61: =1348520029000+50000000000 -> 1398520029000 | L61: =(D61-E61-H61) -> 2389909174000 | M61: =I61-J61-K61 -> 124855488000 | N61: =L61-M61 -> 2265053686000 | O61: =N61-N60 -> -113635271000
A62: 61 | B62: CFIN | C62: 2017 | D62: 9890847326000 | E62: 9648151869000 | F62: =10866000000+10437000000 -> 21303000000 | G62: 16126392000 | H62: =F62+G62 -> 37429392000 | I62: 5861316507000 | J62: =4777179002000+88531344000+39943197000+31438617000 -> 4937092160000 | K62: =42039556000+699651044000 -> 741690600000 | L62: =(D62-E62-H62) -> 205266065000 | M62: =I62-J62-K62 -> 182533747000 | N62: =L62-M62 -> 22732318000
A63: 62 | B63: CFIN | C63: 2018 | D63: 11103279117000 | E63: 10785637226000 | F63: =10392000000+12457000000 -> 22849000000 | G63: 14594837000 | H63: =F63+G63 -> 37443837000 | I63: 6729921689000 | J63: =4312284028000+53243540000+54418060000+40007144000 -> 4459952772000 | K63: =48640775000+1986155439000 -> 2034796214000 | L63: =(D63-E63-H63) -> 280198054000 | M63: =I63-J63-K63 -> 235172703000 | N63: =L63-M63 -> 45025351000 | O63: =N63-N62 -> 22293033000
A64: 63 | B64: CFIN | C64: 2019 | D64: 12117478069000 | E64: 11824160110000 | F64: 12457000000 | G64: 21583548000 | H64: =F64+G64 -> 34040548000 | I64: 7411804923000 | J64: =4956259274000+68766612000+57884367000+21524555000 -> 5104434808000 | K64: =10341128000+1991992312000 -> 2002333440000 | L64: =(D64-E64-H64) -> 259277411000 | M64: =I64-J64-K64 -> 305036675000 | N64: =L64-M64 -> -45759264000 | O64: =N64-N63 -> -90784615000
A65: 64 | B65: CFIN | C65: 2020 | D65: 10917456216000 | E65: 10644136835000 | F65: 12457000000 | G65: 3662276000 | H65: =F65+G65 -> 16119276000 | I65: 6172266324000 | J65: =3893526206000+17887435000+4029525000+61302666000 -> 3976745832000 | K65: =10750732000+1998407472000 -> 2009158204000 | L65: =(D65-E65-H65) -> 257200105000 | M65: =I65-J65-K65 -> 186362288000 | N65: =L65-M65 -> 70837817000 | O65: =N65-N64 -> 116597081000
A66: 65 | B66: CFIN | C66: 2021 | D66: 7123904019000 | E66: 6535206225000 | F66: 13224000000 | G66: 1345238000 | H66: =F66+G66 -> 14569238000 | I66: 2317783818000 | J66: =1992299748000+55702975000+37155561000+38618480000 -> 2123776764000 | K66: =21086782000 -> 21086782000 | L66: =(D66-E66-H66) -> 574128556000 | M66: =I66-J66-K66 -> 172920272000 | N66: =L66-M66 -> 401208284000 | O66: =N66-N65 -> 330370467000
A67: 66 | B67: HDFA | C67: 2017 | D67: 3850636684000 | E67: 3759856401000 | F67: 13400000000 | G67: =3638297000+15568939000 -> 19207236000 | H67: =F67+G67 -> 32607236000 | I67: 3325880986000 | J67: =2278431361000+5067916000+20732488000 -> 2304231765000 | K67: =37128903000+5125166000+102000000000 -> 144254069000 | L67: =(D67-E67-H67) -> 58173047000 | M67: =I67-J67-K67 -> 877395152000 | N67: =L67-M67 -> -819222105000
A68: 67 | B68: HDFA | C68: 2018 | D68: 2260886445000 | E68: 1929809609000 | F68: 193200454000 | G68: 7005987000 | H68: =F68+G68 -> 200206441000 | I68: 2028696565000 | J68: =1253447628000+996007000+20133766000 -> 1274577401000 | K68: =237000000000 -> 237000000000 | L68: =(D68-E68-H68) -> 130870395000 | M68: =I68-J68-K68 -> 517119164000 | N68: =L68-M68 -> -386248769000 | O68: =N68-N67 -> 432973336000
A69: 68 | B69: HDFA | C69: 2019 | D69: 1191295498000 | E69: 1017146669000 | F69: 52745444000 | G69: 6812982000 | H69: =F69+G69 -> 59558426000 | I69: 597001340000 | J69: =474112492000+350266000+52854105000 -> 527316863000 | K69: =231521000 -> 231521000 | L69: =(D69-E69-H69) -> 114590403000 | M69: =I69-J69-K69 -> 69452956000 | N69: =L69-M69 -> 45137447000 | O69: =N69-N68 -> 431386216000
A70: 69 | B70: HDFA | C70: 2020 | D70: 772208525000 | E70: 624950495000 | F70: 22267157000 | G70: 983366000 | H70: =F70+G70 -> 23250523000 | I70: 265703138000 | J70: =185543806000+15534000+204672000+24797857000 -> 210561869000 | K70: =15534000+81807000+9980352000 -> 10077693000 | L70: =(D70-E70-H70) -> 124007507000 | M70: =I70-J70-K70 -> 45063576000 | N70: =L70-M70 -> 78943931000 | O70: =N70-N69 -> 33806484000
A71: 70 | B71: HDFA | C71: 2021 | D71: 1279780398000 | E71: 1116346993000 | F71: 12250000000 | G71: 1063463000 | H71: =F71+G71 -> 13313463000 | I71: 650558755000 | J71: =545484500000+518376000+8398769000 -> 554401645000 | K71: =79569000+10947708000 -> 11027277000 | L71: =(D71-E71-H71) -> 150119942000 | M71: =I71-J71-K71 -> 85129833000 | N71: =L71-M71 -> 64990109000 | O71: =N71-N70 -> -13953822000
A72: 71 | B72: MAYA | C72: 2017 | D72: 74745570167000 | E72: 62549456000000 | F72: =4274738000000+6274738000000+676653000000+526886000000 -> 11753015000000 | G72: =46802000000 -> 46802000000 | H72: =F72+G72 -> 11799817000000 | I72: 66202194000000 | J72: =360322000000+1123803000000+61509693000000+4202000000+80831000000+301712000000 -> 63380563000000 | K72: =669355000000+1933309000000 -> 2602664000000 | L72: =(D72-E72-H72) -> 396297167000 | M72: =I72-J72-K72 -> 218967000000 | N72: =L72-M72 -> 177330167000
A73: 72 | B73: MAYA | C73: 2018 | D73: 86971893000000 | E73: 70315020000000 | F73: =4231414000000+3532751000000+1110919000000+1110919000000 -> 9986003000000 | G73: 93088000000 | H73: =F73+G73 -> 10079091000000 | I73: 76183319000000 | J73: =379174000000+1413974000000+70096562000000+6167000000+128770000000+301433000000 -> 72326080000000 | K73: =713008000000+2731782000000 -> 3444790000000 | L73: =(D73-E73-H73) -> 6577782000000 | M73: =I73-J73-K73 -> 412449000000 | N73: =L73-M73 -> 6165333000000 | O73: =N73-N72 -> 5988002833000
A74: 73 | B74: MAYA | C74: 2019 | D74: 93408831000000 | E74: 77587817000000 | F74: =4143380000000+6832693000000+1636641000000 -> 12612714000000 | G74: 247386000000 | H74: =F74+G74 -> 12860100000000 | I74: 81066862000000 | J74: =368475000000+77009109000000+2800000000+170402000000+366965000000 -> 77917751000000 | K74: 2738334000000 | L74: =(D74-E74-H74) -> 2960914000000 | M74: =I74-J74-K74 -> 410777000000 | N74: =L74-M74 -> 2550137000000 | O74: =N74-N73 -> -3615196000000
A75: 74 | B75: MAYA | C75: 2020 | D75: 92518025000000 | E75: 64369231000000 | F75: =4947062000000 -> 4947062000000 | G75: 372551000000 | H75: =F75+G75 -> 5319613000000 | I75: 79603549000000 | J75: =319304000000+72357421000000+2769865000000+108617000000+447323000000 -> 76002530000000 | K75: =1220635000000+2043642000000 -> 3264277000000 | L75: =(D75-E75-H75) -> 22829181000000 | M75: =I75-J75-K75 -> 336742000000 | N75: =L75-M75 -> 22492439000000 | O75: =N75-N74 -> 19942302000000
A76: 75 | B76: MAYA | C76: 2021 | D76: 119104185000000 | E76: 74269770000000 | F76: =125500000000+8246664000000+7006212000000 -> 15378376000000 | G76: 821393000000 | H76: =F76+G76 -> 16199769000000 | I76: 105125905000000 | J76: =334117000000+98720992000000+3459974000000+105401000000+385456000000 -> 103005940000000 | K76: 1791503000000 | L76: =(D76-E76-H76) -> 28634646000000 | M76: =I76-J76-K76 -> 328462000000 | N76: =L76-M76 -> 28306184000000 | O76: =N76-N75 -> 5813745000000
A77: 76 | B77: PADI | C77: 2017 | D77: 507913387670 | E77: 69456523574 | F77: =3601740164+240828642736+89574752786+5710000000+39005072485 -> 378720208171 | G77: 256664169 | H77: =F77+G77 -> 378976872340 | I77: 22758936367 | J77: 21883000000 | K77: 875936367 | L77: =(D77-E77-H77) -> 59479991756 | M77: =I77-J77-K77 -> 0 | N77: =L77-M77 -> 59479991756 | P77: =K77+M77 -> 875936367
A78: 77 | B78: PADI | C78: 2018 | D78: 543334863433 | E78: 35443615175 | F78: =3781333780+314821824092+137577440350+5710000000+5620837089 -> 467511435311 | G78: 566230079 | H78: =F78+G78 -> 468077665390 | I78: 19272423025 | J78: 18396000000 | K78: =I78-J78 -> 876423025 | L78: =(D78-E78-H78) -> 39813582868 | M78: =I78-J78-K78 -> 0 | N78: =L78-M78 -> 39813582868 | O78: =N78-N77 -> -19666408888
A79: 78 | B79: PADI | C79: 2019 | D79: 418394702709 | E79: 24185104415 | F79: =3962340531+204803802832+123389424000+5710000000+30453762534 -> 368319329897 | G79: 223238451 | H79: =F79+G79 -> 368542568348 | I79: 35709910993 | J79: 11557000000 | K79: =I79-J79 -> 24152910993 | L79: =(D79-E79-H79) -> 25667029946 | M79: =I79-J79-K79 -> 0 | N79: =L79-M79 -> 25667029946 | O79: =N79-N78 -> -14146552922
A80: 79 | B80: PADI | C80: 2020 | D80: 334609310613 | E80: 27824172197 | F80: =143386538233+109969099194+5710000000+28780223005 -> 287845860432 | G80: 54827368 | H80: =F80+G80 -> 287900687800 | I80: 39785627279 | J80: 19252000000 | K80: =I80-J80 -> 20533627279 | L80: =(D80-E80-H80) -> 18884450616 | M80: =I80-J80-K80 -> 0 | N80: =L80-M80 -> 18884450616 | O80: =N80-N79 -> -6782579330
A81: 80 | B81: PADI | C81: 2021 | D81: 266587854693 | E81: 18258620939 | F81: =164301883990+35312397684+5710000000+27106683476 -> 232430965150 | G81: 55604319 | H81: =F81+G81 -> 232486569469 | I81: 24621827763 | J81: 8897000000 | K81: =I81-J81 -> 15724827763 | L81: =(D81-E81-H81) -> 15842664285 | M81: =I81-J81-K81 -> 0 | N81: =L81-M81 -> 15842664285 | O81: =N81-N80 -> -3041786331
A82: 81 | B82: PNLF | C82: 2017 | D82: 26471320000000 | E82: 3635822000000 | F82: =6734117000000+15612699000000 -> 22346816000000 | G82: 7983000000 | H82: =F82+G82 -> 22354799000000 | I82: 4404630000000 | J82: =132865000000+13973000000+55100000000+39604000000 -> 241542000000 | K82: 3893351000000 | L82: =(D82-E82-H82) -> 480699000000 | M82: =I82-J82-K82 -> 269737000000 | N82: =L82-M82 -> 210962000000
A83: 82 | B83: PNLF | C83: 2018 | D83: 28252725000000 | E83: 3988086000000 | F83: =6624954000000+17162320000000 -> 23787274000000 | G83: 7107000000 | H83: =F83+G83 -> 23794381000000 | I83: 4419322000000 | J83: =160354000000+3467000000+40448000000+45745000000+40236000000 -> 290250000000 | K83: 3892945000000 | L83: =(D83-E83-H83) -> 470258000000 | M83: =I83-J83-K83 -> 236127000000 | N83: =L83-M83 -> 234131000000 | O83: =N83-N82 -> 23169000000
A84: 83 | B84: PNLF | C84: 2019 | D84: 30289386000000 | E84: 4132189000000 | F84: =6948019000000+18767609000000 -> 25715628000000 | G84: 6290000000 | H84: =F84+G84 -> 25721918000000 | I84: 4338029000000 | J84: =206457000000+3596000000+52931000000+50325000000 -> 313309000000 | K84: 3763769000000 | L84: =(D84-E84-H84) -> 435279000000 | M84: =I84-J84-K84 -> 260951000000 | N84: =L84-M84 -> 174328000000 | O84: =N84-N83 -> -59803000000
A85: 84 | B85: PNLF | C85: 2020 | D85: 32381721000000 | E85: 6003987000000 | F85: =5831427000000+20128239000000 -> 25959666000000 | G85: 6553000000 | H85: =F85+G85 -> 25966219000000 | I85: 4484512000000 | J85: =301744000000+3477000000+53090000000+53328000000 -> 411639000000 | K85: 3791003000000 | L85: =(D85-E85-H85) -> 411515000000 | M85: =I85-J85-K85 -> 281870000000 | N85: =L85-M85 -> 129645000000 | O85: =N85-N84 -> -44683000000
A86: 85 | B86: PNLF | C86: 2021 | D86: 33192581000000 | E86: 6403757000000 | F86: =5695993000000+20685901000000 -> 26381894000000 | G86: 17324000000 | H86: =F86+G86 -> 26399218000000 | I86: 4364736000000 | J86: =199177000000+4413000000+62717000000+43370000000 -> 309677000000 | K86: 3999226000000 | L86: =(D86-E86-H86) -> 389606000000 | M86: =I86-J86-K86 -> 55833000000 | N86: =L86-M86 -> 333773000000 | O86: =N86-N85 -> 204128000000
A87: 86 | B87: SDRA | C87: 2017 | D87: 27086504000000 | E87: 22070684000000 | F87: =1976168000000+404303000000+449000000 -> 2380920000000 | G87: 92121000000 | H87: =F87+G87 -> 2473041000000 | I87: 20979506000000 | J87: =16928615000000+87126000000+42004000000+16888000000+50822000000 -> 17125455000000 | K87: =205400000000+2035125000000 -> 2240525000000 | L87: =(D87-E87-H87) -> 2542779000000 | M87: =I87-J87-K87 -> 1613526000000 | N87: =L87-M87 -> 929253000000
A88: 87 | B88: SDRA | C88: 2018 | D88: 29631693000000 | E88: 24849398000000 | F88: =1311851000000+449000000 -> 1312300000000 | G88: 27052000000 | H88: =F88+G88 -> 1339352000000 | I88: 23081225000000 | J88: =15391187000000+84576000000+1664000000+17828000000+45790000000 -> 15541045000000 | K88: =206201000000+4745400000000 -> 4951601000000 | L88: =(D88-E88-H88) -> 3442943000000 | M88: =I88-J88-K88 -> 2588579000000 | N88: =L88-M88 -> 854364000000 | O88: =N88-N87 -> -74889000000
A89: 88 | B89: SDRA | C89: 2019 | D89: 36940436000000 | E89: 32396746000000 | F89: =1832381000000+449000000 -> 1832830000000 | G89: 13555000000 | H89: =F89+G89 -> 1846385000000 | I89: 30000672000000 | J89: =19065370000000+153093000000+2285000000+24398000000+41440000000 -> 19286586000000 | K89: =8024775000000 -> 8024775000000 | L89: =(D89-E89-H89) -> 2697305000000 | M89: =I89-J89-K89 -> 2689311000000 | N89: =L89-M89 -> 7994000000 | O89: =N89-N88 -> -846370000000
A90: 89 | B90: SDRA | C90: 2020 | D90: 38053939000000 | E90: 32984592000000 | F90: =1989822000000+190571000000+449000000 -> 2180842000000 | G90: 17027000000 | H90: =F90+G90 -> 2197869000000 | I90: 30782968000000 | J90: =18492074000000+104339000000+31525000000+18104000000+47129000000 -> 18693171000000 | K90: 10858500000000 | L90: =(D90-E90-H90) -> 2871478000000 | M90: =I90-J90-K90 -> 1231297000000 | N90: =L90-M90 -> 1640181000000 | O90: =N90-N89 -> 1632187000000
A91: 90 | B91: SDRA | C91: 2021 | D91: 43801571000000 | E91: 37679601000000 | F91: =2758839000000+595245000000+449000000 -> 3354533000000 | G91: 19741000000 | H91: =F91+G91 -> 3374274000000 | I91: 34544380000000 | J91: =23848020000000+66983000000+36120000000+17623000000+47129000000 -> 24015875000000 | K91: 8941200000000 | L91: =(D91-E91-H91) -> 2747696000000 | M91: =I91-J91-K91 -> 1587305000000 | N91: =L91-M91 -> 1160391000000 | O91: =N91-N90 -> -479790000000
A92: 91 | B92: SMMA | C92: 2017 | D92: 89086788000000 | E92: 31297311000000 | F92: =918460000000+166213000000+50581061000000 -> 51665734000000 | G92: =75800000000+33080000000+105500000000 -> 214380000000 | H92: =F92+G92 -> 51880114000000 | I92: 66140481000000 | J92: =23744668000000+152099000000+221840000000+2705859000000 -> 26824466000000 | K92: =691536000000+4306280000000+2705859000000 -> 7703675000000 | L92: =(D92-E92-H92) -> 5909363000000 | M92: =I92-J92-K92 -> 31612340000000 | N92: =L92-M92 -> -25702977000000
A93: 92 | B93: SMMA | C93: 2018 | D93: 100663451000000 | E93: 34542046000000 | F93: =422677000000+965224000000+59247522000000 -> 60635423000000 | G93: =186568000000+16119000000+500000000 -> 203187000000 | H93: =F93+G93 -> 60838610000000 | I93: 75550211000000 | J93: =24457183000000+95891000000+194613000000+3090368000000 -> 27838055000000 | K93: =804738000000+1005251000000+3090368000000 -> 4900357000000 | L93: =(D93-E93-H93) -> 5282795000000 | M93: =I93-J93-K93 -> 42811799000000 | N93: =L93-M93 -> -37529004000000 | O93: =N93-N92 -> -11826027000000
A94: 93 | B94: SMMA | C94: 2019 | D94: 99624857000000 | E94: 37117536000000 | F94: =54859930000000+2951424000000+514310000000 -> 58325664000000 | G94: =257153000000+12469000000+4999000000 -> 274621000000 | H94: =F94+G94 -> 58600285000000 | I94: 77460250000000 | J94: =28911530000000+98609000000+195530000000+3140301000000 -> 32345970000000 | K94: =1328087000000+446581000000+3140301000000 -> 4914969000000 | L94: =(D94-E94-H94) -> 3907036000000 | M94: =I94-J94-K94 -> 40199311000000 | N94: =L94-M94 -> -36292275000000 | O94: =N94-N93 -> 1236729000000
A95: 94 | B95: SMMA | C95: 2020 | D95: 108456227000000 | E95: 35519474000000 | F95: =506252000000+2911162000000+56069446000000 -> 59486860000000 | G95: =111485000000+2336000000 -> 113821000000 | H95: =F95+G95 -> 59600681000000 | I95: 85533983000000 | J95: =35177072000000+143900000000+253640000000+3013529000000 -> 38588141000000 | K95: =4053356000000+882257000000+3013529000000 -> 7949142000000 | L95: =(D95-E95-H95) -> 13336072000000 | M95: =I95-J95-K95 -> 38996700000000 | N95: =L95-M95 -> -25660628000000 | O95: =N95-N94 -> 10631647000000
A96: 95 | B96: SMMA | C96: 2021 | D96: 117509999000000 | E96: 34553205000000 | F96: =2980272000000+433791000000+69015423000000 -> 72429486000000 | G96: =141665000000+2421000000 -> 144086000000 | H96: =F96+G96 -> 72573572000000 | I96: 94727715000000 | J96: =42257556000000+119985000000+237008000000+3485895000000 -> 46100444000000 | K96: =585618000000+306591000000+3485895000000 -> 4378104000000 | L96: =(D96-E96-H96) -> 10383222000000 | M96: =I96-J96-K96 -> 44249167000000 | N96: =L96-M96 -> -33865945000000 | O96: =N96-N95 -> -8205317000000
A97: 96 | B97: WOMF | C97: 2017 | D97: 7745732000000 | E97: 7538515000000 | F97: 0 | G97: 101642000000 | H97: =F97+G97 -> 101642000000 | I97: 6755920000000 | J97: =3082884000000+69022000000+30000000+148307000000 -> 3300243000000 | K97: =3062543000000+100000000000 -> 3162543000000 | L97: =(D97-E97-H97) -> 105575000000 | M97: =I97-J97-K97 -> 293134000000 | N97: =L97-M97 -> -187559000000
A98: 97 | B98: WOMF | C98: 2018 | D98: 8827307000000 | E98: 8558988000000 | F98: 3150000000 | G98: 119014000000 | H98: =F98+G98 -> 122164000000 | I98: 7655464000000 | J98: =4559701000000+96114000000+3093000000+128944000000 -> 4787852000000 | K98: =2528597000000+100000000000 -> 2628597000000 | L98: =(D98-E98-H98) -> 146155000000 | M98: =I98-J98-K98 -> 239015000000 | N98: =L98-M98 -> -92860000000 | O98: =N98-N97 -> 94699000000
A99: 98 | B99: WOMF | C99: 2019 | D99: 8271170000000 | E99: 8003350000000 | F99: 3572000000 | G99: 76904000000 | H99: =F99+G99 -> 80476000000 | I99: 6900593000000 | J99: =3622876000000+92563000000+39337000000+135970000000 -> 3890746000000 | K99: =2651540000000+200000000000 -> 2851540000000 | L99: =(D99-E99-H99) -> 187344000000 | M99: =I99-J99-K99 -> 158307000000 | N99: =L99-M99 -> 29037000000 | O99: =N99-N98 -> 121897000000
A100: 99 | B100: WOMF | C100: 2020 | D100: 5283702000000 | E100: 4996069000000 | F100: 2817000000 | G100: 6218000000 | H100: =F100+G100 -> 9035000000 | I100: 4070357000000 | J100: =1743411000000+40470000000+2564000000+126636000000 -> 1913081000000 | K100: =1799567000000+200000000000 -> 1999567000000 | L100: =(D100-E100-H100) -> 278598000000 | M100: =I100-J100-K100 -> 157709000000 | N100: =L100-M100 -> 120889000000 | O100: =N100-N99 -> 91852000000
...

Sheet FIN
A1: No | B1: Kode Emiten | C1: Tahun | D1: Total Investment | E1: Total Liabilities | F1: FIN | G1: ∆FIN
A2: 1 | B2: ASTJ | C2: 2017 | D2: =NCO!F2 -> 170613115220 | E2: =NCO!I2 -> 234660000000 | F2: =D2-E2 -> -64046884780
A3: 2 | B3: ASTJ | C3: 2018 | D3: =NCO!F3 -> 160955833563 | E3: =NCO!I3 -> 258810000000 | F3: =D3-E3 -> -97854166437 | G3: =F3-F2 -> -33807281657
A4: 3 | B4: ASTJ | C4: 2019 | D4: =NCO!F4 -> 76763750283 | E4: =NCO!I4 -> 238310000000 | F4: =D4-E4 -> -161546249717 | G4: =F4-F3 -> -63692083280
A5: 4 | B5: ASTJ | C5: 2020 | D5: =NCO!F5 -> 98673273669 | E5: =NCO!I5 -> 156230000000 | F5: =D5-E5 -> -57556726331 | G5: =F5-F4 -> 103989523386
A6: 5 | B6: ASTJ | C6: 2021 | D6: =NCO!F6 -> 185282040833 | E6: =NCO!I6 -> 219400000000 | F6: =D6-E6 -> -34117959167 | G6: =F6-F5 -> 23438767164
A7: 6 | B7: ASMI | C7: 2017 | D7: =NCO!F7 -> 533517793928 | E7: =NCO!I7 -> 403521972590 | F7: =D7-E7 -> 129995821338
A8: 7 | B8: ASMI | C8: 2018 | D8: =NCO!F8 -> 592283745811 | E8: =NCO!I8 -> 450272263738 | F8: =D8-E8 -> 142011482073 | G8: =F8-F7 -> 12015660735
A9: 8 | B9: ASMI | C9: 2019 | D9: =NCO!F9 -> 593869589863 | E9: =NCO!I9 -> 445392630259 | F9: =D9-E9 -> 148476959604 | G9: =F9-F8 -> 6465477531
A10: 9 | B10: ASMI | C10: 2020 | D10: =NCO!F10 -> 384429667667 | E10: =NCO!I10 -> 547541424689 | F10: =D10-E10 -> -163111757022 | G10: =F10-F9 -> -311588716626
A11: 10 | B11: ASMI | C11: 2021 | D11: =NCO!F11 -> 461141938897 | E11: =NCO!I11 -> 518209589004 | F11: =D11-E11 -> -57067650107 | G11: =F11-F10 -> 106044106915
A12: 11 | B12: BBNI | C12: 2017 | D12: =NCO!F12 -> 117291896000000 | E12: =NCO!I12 -> 584086818000000 | F12: =D12-E12 -> -466794922000000
A13: 12 | B13: BBNI | C13: 2018 | D13: =NCO!F13 -> 119439595000000 | E13: =NCO!I13 -> 671237546000000 | F13: =D13-E13 -> -551797951000000 | G13: =(F13-F12) -> -85003029000000
A14: 13 | B14: BBNI | C14: 2019 | D14: =NCO!F14 -> 109125316000000 | E14: =NCO!I14 -> 688489442000000 | F14: =D14-E14 -> -579364126000000 | G14: =(F14-F13) -> -27566175000000
A15: 14 | B15: BBNI | C15: 2020 | D15: =NCO!F15 -> 129825093000000 | E15: =NCO!I15 -> 746235663000000 | F15: =D15-E15 -> -616410570000000 | G15: =(F15-F14) -> -37046444000000
A16: 15 | B16: BBNI | C16: 2021 | D16: =NCO!F16 -> 168760429000000 | E16: =NCO!I16 -> 838317715000000 | F16: =D16-E16 -> -669557286000000 | G16: =(F16-F15) -> -53146716000000
A17: 16 | B17: BBTN | C17: 2017 | D17: =NCO!F17 -> 15890004000000 | E17: =NCO!I17 -> 223937463000000 | F17: =D17-E17 -> -208047459000000
A18: 17 | B18: BBTN | C18: 2018 | D18: =NCO!F18 -> 15241623000000 | E18: =NCO!I18 -> 263784017000000 | F18: =D18-E18 -> -248542394000000 | G18: =F18-F17 -> -40494935000000
A19: 18 | B19: BBTN | C19: 2019 | D19: =NCO!F19 -> 21013493000000 | E19: =NCO!I19 -> 269451682000000 | F19: =D19-E19 -> -248438189000000 | G19: =F19-F18 -> 104205000000
A20: 19 | B20: BBTN | C20: 2020 | D20: =NCO!F20 -> 60446672000000 | E20: =NCO!I20 -> 321376142000000 | F20: =D20-E20 -> -260929470000000 | G20: =F20-F19 -> -12491281000000
A21: 20 | B21: BBTN | C21: 2021 | D21: =NCO!F21 -> 49909528000000 | E21: =NCO!I21 -> 327693592000000 | F21: =D21-E21 -> -277784064000000 | G21: =F21-F20 -> -16854594000000
A22: 21 | B22: BCAP | C22: 2017 | D22: =NCO!F22 -> 4275639000000 | E22: =NCO!I22 -> 14255743000000 | F22: =D22-E22 -> -9980104000000
A23: 22 | B23: BCAP | C23: 2018 | D23: =NCO!F23 -> 4206002000000 | E23: =NCO!I23 -> 13015396000000 | F23: =D23-E23 -> -8809394000000 | G23: =F23-F22 -> 1170710000000
A24: 23 | B24: BCAP | C24: 2019 | D24: =NCO!F24 -> 4021806000000 | E24: =NCO!I24 -> 12839026000000 | F24: =D24-E24 -> -8817220000000 | G24: =F24-F23 -> -7826000000
A25: 24 | B25: BCAP | C25: 2020 | D25: =NCO!F25 -> 4045078000000 | E25: =NCO!I25 -> 14007712000000 | F25: =D25-E25 -> -9962634000000 | G25: =F25-F24 -> -1145414000000
A26: 25 | B26: BCAP | C26: 2021 | D26: =NCO!F26 -> 4582657000000 | E26: =NCO!I26 -> 15646157000000 | F26: =D26-E26 -> -11063500000000 | G26: =F26-F25 -> -1100866000000
A27: 26 | B27: BDMN | C27: 2017 | D27: =NCO!F27 -> 27452702000000 | E27: =NCO!I27 -> 139084940000000 | F27: =D27-E27 -> -111632238000000
A28: 27 | B28: BDMN | C28: 2018 | D28: =NCO!F28 -> 20248157000000 | E28: =NCO!I28 -> 144822368000000 | F28: =D28-E28 -> -124574211000000 | G28: =F28-F27 -> -12941973000000
A29: 28 | B29: BDMN | C29: 2019 | D29: =NCO!F29 -> 28389887000000 | E29: =NCO!I29 -> 148116943000000 | F29: =D29-E29 -> -119727056000000 | G29: =F29-F28 -> 4847155000000
A30: 29 | B30: BDMN | C30: 2020 | D30: =NCO!F30 -> 43382056000000 | E30: =NCO!I30 -> 157314569000000 | F30: =D30-E30 -> -113932513000000 | G30: =F30-F29 -> 5794543000000
A31: 30 | B31: BDMN | C31: 2021 | D31: =NCO!F31 -> 36882867000000 | E31: =NCO!I31 -> 147156640000000 | F31: =D31-E31 -> -110273773000000 | G31: =F31-F30 -> 3658740000000
A32: 31 | B32: BFIN | C32: 2017 | D32: =NCO!F32 -> 0 | E32: =NCO!I32 -> 11579007000000 | F32: =-(D32-E32) -> 11579007000000
A33: 32 | B33: BFIN | C33: 2018 | D33: =NCO!F33 -> 0 | E33: =NCO!I33 -> 12913509000000 | F33: =-(D33-E33) -> 12913509000000 | G33: =F33-F32 -> 1334502000000
A34: 33 | B34: BFIN | C34: 2019 | D34: =NCO!F34 -> 0 | E34: =NCO!I34 -> 13009453000000 | F34: =-(D34-E34) -> 13009453000000 | G34: =F34-F33 -> 95944000000
A35: 34 | B35: BFIN | C35: 2020 | D35: =NCO!F35 -> 0 | E35: =NCO!I35 -> 8594377000000 | F35: =-(D35-E35) -> 8594377000000 | G35: =F35-F34 -> -4415076000000
A36: 35 | B36: BFIN | C36: 2021 | D36: =NCO!F36 -> 0 | E36: =NCO!I36 -> 8205513000000 | F36: =-(D36-E36) -> 8205513000000 | G36: =F36-F35 -> -388864000000
A37: 36 | B37: BNGA | C37: 2017 | D37: =NCO!F37 -> 38417199000000 | E37: =NCO!I37 -> 229354449000000 | F37: =D37-E37 -> -190937250000000
A38: 37 | B38: BNGA | C38: 2018 | D38: =NCO!F38 -> 35273249000000 | E38: =NCO!I38 -> 227200919000000 | F38: =D38-E38 -> -191927670000000 | G38: =F38-F37 -> -990420000000
A39: 38 | B39: BNGA | C39: 2019 | D39: =NCO!F39 -> 34649484000000 | E39: =NCO!I39 -> 231173061000000 | F39: =D39-E39 -> -196523577000000 | G39: =F39-F38 -> -4595907000000
A40: 39 | B40: BNGA | C40: 2020 | D40: =NCO!F40 -> 67448167000000 | E40: =NCO!I40 -> 239890554000000 | F40: =D40-E40 -> -172442387000000 | G40: =F40-F39 -> 24081190000000
A41: 40 | B41: BNGA | C41: 2021 | D41: =NCO!F41 -> 72290001000000 | E41: =NCO!I41 -> 267398602000000 | F41: =D41-E41 -> -195108601000000 | G41: =F41-F40 -> -22666214000000
A42: 41 | B42: BNII | C42: 2017 | D42: =NCO!F42 -> 23508074000000 | E42: =NCO!I42 -> 152478451000000 | F42: =D42-E42 -> -128970377000000
A43: 42 | B43: BNII | C43: 2018 | D43: =NCO!F43 -> 16772474000000 | E43: =NCO!I43 -> 152442167000000 | F43: =D43-E43 -> -135669693000000 | G43: =F43-F42 -> -6699316000000
A44: 43 | B44: BNII | C44: 2019 | D44: =NCO!F44 -> 20563153000000 | E44: =NCO!I44 -> 142397914000000 | F44: =D44-E44 -> -121834761000000 | G44: =F44-F43 -> 13834932000000
A45: 44 | B45: BNII | C45: 2020 | D45: =NCO!F45 -> 36168025000000 | E45: =NCO!I45 -> 146000782000000 | F45: =D45-E45 -> -109832757000000 | G45: =F45-F44 -> 12002004000000
A46: 45 | B46: BNII | C46: 2021 | D46: =NCO!F46 -> 34705036000000 | E46: =NCO!I46 -> 140033353000000 | F46: =D46-E46 -> -105328317000000 | G46: =F46-F45 -> 4504440000000
A47: 46 | B47: BNLI | C47: 2017 | D47: =NCO!F47 -> 23796953000000 | E47: =NCO!I47 -> 126817628000000 | F47: =D47-E47 -> -103020675000000
A48: 47 | B48: BNLI | C48: 2018 | D48: =NCO!F48 -> 14989712000000 | E48: =NCO!I48 -> 130440930000000 | F48: =D48-E48 -> -115451218000000 | G48: =F48-F47 -> -12430543000000
A49: 48 | B49: BNLI | C49: 2019 | D49: =NCO!F49 -> 17764442000000 | E49: =NCO!I49 -> 137413908000000 | F49: =D49-E49 -> -119649466000000 | G49: =F49-F48 -> -4198248000000
A50: 49 | B50: BNLI | C50: 2020 | D50: =NCO!F50 -> 45529439000000 | E50: =NCO!I50 -> 162654644000000 | F50: =D50-E50 -> -117125205000000 | G50: =F50-F49 -> 2524261000000
A51: 50 | B51: BNLI | C51: 2021 | D51: =NCO!F51 -> 55347803000000 | E51: =NCO!I51 -> 197765327000000 | F51: =D51-E51 -> -142417524000000 | G51: =F51-F50 -> -25292319000000
A52: 51 | B52: ADMF | C52: 2017 | D52: =NCO!F52 -> 650000000 | E52: =NCO!I52 -> 23747518000000 | F52: =D52-E52 -> -23746868000000
A53: 52 | B53: ADMF | C53: 2018 | D53: =NCO!F53 -> 650000000 | E53: =NCO!I53 -> 24468242000000 | F53: =D53-E53 -> -24467592000000 | G53: =F53-F52 -> -720724000000
A54: 53 | B54: ADMF | C54: 2019 | D54: =NCO!F54 -> 650000000 | E54: =NCO!I54 -> 27038058000000 | F54: =D54-E54 -> -27037408000000 | G54: =F54-F53 -> -2569816000000
A55: 54 | B55: ADMF | C55: 2020 | D55: =NCO!F55 -> 650000000 | E55: =NCO!I55 -> 21305238000000 | F55: =D55-E55 -> -21304588000000 | G55: =F55-F54 -> 5732820000000
A56: 55 | B56: ADMF | C56: 2021 | D56: =NCO!F56 -> 650000000 | E56: =NCO!I56 -> 14838879000000 | F56: =D56-E56 -> -14838229000000 | G56: =F56-F55 -> 6466359000000
A57: 56 | B57: BVIC | C57: 2017 | D57: =NCO!F57 -> 7897783120000 | E57: =NCO!I57 -> 24483975280000 | F57: =D57-E57 -> -16586192160000
A58: 57 | B58: BVIC | C58: 2018 | D58: =NCO!F58 -> 7724531838000 | E58: =NCO!I58 -> 25808570240000 | F58: =D58-E58 -> -18084038402000 | G58: =F58-F57 -> -1497846242000
A59: 58 | B59: BVIC | C59: 2019 | D59: =NCO!F59 -> 7901239720891 | E59: =NCO!I59 -> 25782313852000 | F59: =D59-E59 -> -17881074131109 | G59: =F59-F58 -> 202964270891
A60: 59 | B60: BVIC | C60: 2020 | D60: =NCO!F60 -> 6854475642000 | E60: =NCO!I60 -> 22197849857000 | F60: =D60-E60 -> -15343374215000 | G60: =F60-F59 -> 2537699916109
A61: 60 | B61: BVIC | C61: 2021 | D61: =NCO!F61 -> 5866201222000 | E61: =NCO!I61 -> 20702225559000 | F61: =D61-E61 -> -14836024337000 | G61: =F61-F60 -> 507349878000
A62: 61 | B62: CFIN | C62: 2017 | D62: =NCO!F62 -> 21303000000 | E62: =NCO!I62 -> 5861316507000 | F62: =D62-E62 -> -5840013507000
A63: 62 | B63: CFIN | C63: 2018 | D63: =NCO!F63 -> 22849000000 | E63: =NCO!I63 -> 6729921689000 | F63: =D63-E63 -> -6707072689000 | G63: =F63-F62 -> -867059182000
A64: 63 | B64: CFIN | C64: 2019 | D64: =NCO!F64 -> 12457000000 | E64: =NCO!I64 -> 7411804923000 | F64: =D64-E64 -> -7399347923000 | G64: =F64-F63 -> -692275234000
A65: 64 | B65: CFIN | C65: 2020 | D65: =NCO!F65 -> 12457000000 | E65: =NCO!I65 -> 6172266324000 | F65: =D65-E65 -> -6159809324000 | G65: =F65-F64 -> 1239538599000
A66: 65 | B66: CFIN | C66: 2021 | D66: =NCO!F66 -> 13224000000 | E66: =NCO!I66 -> 2317783818000 | F66: =D66-E66 -> -2304559818000 | G66: =F66-F65 -> 3855249506000
A67: 66 | B67: HDFA | C67: 2017 | D67: =NCO!F67 -> 13400000000 | E67: =NCO!I67 -> 3325880986000 | F67: =D67-E67 -> -3312480986000
A68: 67 | B68: HDFA | C68: 2018 | D68: =NCO!F68 -> 193200454000 | E68: =NCO!I68 -> 2028696565000 | F68: =D68-E68 -> -1835496111000 | G68: =F68-F67 -> 1476984875000
A69: 68 | B69: HDFA | C69: 2019 | D69: =NCO!F69 -> 52745444000 | E69: =NCO!I69 -> 597001340000 | F69: =D69-E69 -> -544255896000 | G69: =F69-F68 -> 1291240215000
A70: 69 | B70: HDFA | C70: 2020 | D70: =NCO!F70 -> 22267157000 | E70: =NCO!I70 -> 265703138000 | F70: =D70-E70 -> -243435981000 | G70: =F70-F69 -> 300819915000
A71: 70 | B71: HDFA | C71: 2021 | D71: =NCO!F71 -> 12250000000 | E71: =NCO!I71 -> 650558755000 | F71: =D71-E71 -> -638308755000 | G71: =F71-F70 -> -394872774000
A72: 71 | B72: MAYA | C72: 2017 | D72: =NCO!F72 -> 11753015000000 | E72: =NCO!I72 -> 66202194000000 | F72: =D72-E72 -> -54449179000000
A73: 72 | B73: MAYA | C73: 2018 | D73: =NCO!F73 -> 9986003000000 | E73: =NCO!I73 -> 76183319000000 | F73: =D73-E73 -> -66197316000000 | G73: =(F73-F72) -> -11748137000000
A74: 73 | B74: MAYA | C74: 2019 | D74: =NCO!F74 -> 12612714000000 | E74: =NCO!I74 -> 81066862000000 | F74: =D74-E74 -> -68454148000000 | G74: =(F74-F73) -> -2256832000000
A75: 74 | B75: MAYA | C75: 2020 | D75: =NCO!F75 -> 4947062000000 | E75: =NCO!I75 -> 79603549000000 | F75: =D75-E75 -> -74656487000000 | G75: =(F75-F74) -> -6202339000000
A76: 75 | B76: MAYA | C76: 2021 | D76: =NCO!F76 -> 15378376000000 | E76: =NCO!I76 -> 105125905000000 | F76: =D76-E76 -> -89747529000000 | G76: =(F76-F75) -> -15091042000000
A77: 76 | B77: PADI | C77: 2017 | D77: =NCO!F77 -> 378720208171 | E77: =NCO!I77 -> 22758936367 | F77: =D77-E77 -> 355961271804
A78: 77 | B78: PADI | C78: 2018 | D78: =NCO!F78 -> 467511435311 | E78: =NCO!I78 -> 19272423025 | F78: =D78-E78 -> 448239012286 | G78: =F78-F77 -> 92277740482
A79: 78 | B79: PADI | C79: 2019 | D79: =NCO!F79 -> 368319329897 | E79: =NCO!I79 -> 35709910993 | F79: =D79-E79 -> 332609418904 | G79: =F79-F78 -> -115629593382
A80: 79 | B80: PADI | C80: 2020 | D80: =NCO!F80 -> 287845860432 | E80: =NCO!I80 -> 39785627279 | F80: =D80-E80 -> 248060233153 | G80: =F80-F79 -> -84549185751
A81: 80 | B81: PADI | C81: 2021 | D81: =NCO!F81 -> 232430965150 | E81: =NCO!I81 -> 24621827763 | F81: =D81-E81 -> 207809137387 | G81: =F81-F80 -> -40251095766
A82: 81 | B82: PNLF | C82: 2017 | D82: =NCO!F82 -> 22346816000000 | E82: =NCO!I82 -> 4404630000000 | F82: =D82-E82 -> 17942186000000
A83: 82 | B83: PNLF | C83: 2018 | D83: =NCO!F83 -> 23787274000000 | E83: =NCO!I83 -> 4419322000000 | F83: =D83-E83 -> 19367952000000 | G83: =F83-F82 -> 1425766000000
A84: 83 | B84: PNLF | C84: 2019 | D84: =NCO!F84 -> 25715628000000 | E84: =NCO!I84 -> 4338029000000 | F84: =D84-E84 -> 21377599000000 | G84: =F84-F83 -> 2009647000000
A85: 84 | B85: PNLF | C85: 2020 | D85: =NCO!F85 -> 25959666000000 | E85: =NCO!I85 -> 4484512000000 | F85: =D85-E85 -> 21475154000000 | G85: =F85-F84 -> 97555000000
A86: 85 | B86: PNLF | C86: 2021 | D86: =NCO!F86 -> 26381894000000 | E86: =NCO!I86 -> 4364736000000 | F86: =D86-E86 -> 22017158000000 | G86: =F86-F85 -> 542004000000
A87: 86 | B87: SDRA | C87: 2017 | D87: =NCO!F87 -> 2380920000000 | E87: =NCO!I87 -> 20979506000000 | F87: =D87-E87 -> -18598586000000
A88: 87 | B88: SDRA | C88: 2018 | D88: =NCO!F88 -> 1312300000000 | E88: =NCO!I88 -> 23081225000000 | F88: =D88-E88 -> -21768925000000 | G88: =(F88-F87) -> -3170339000000
A89: 88 | B89: SDRA | C89: 2019 | D89: =NCO!F89 -> 1832830000000 | E89: =NCO!I89 -> 30000672000000 | F89: =D89-E89 -> -28167842000000 | G89: =(F89-F88) -> -6398917000000
A90: 89 | B90: SDRA | C90: 2020 | D90: =NCO!F90 -> 2180842000000 | E90: =NCO!I90 -> 30782968000000 | F90: =D90-E90 -> -28602126000000 | G90: =(F90-F89) -> -434284000000
A91: 90 | B91: SDRA | C91: 2021 | D91: =NCO!F91 -> 3354533000000 | E91: =NCO!I91 -> 34544380000000 | F91: =D91-E91 -> -31189847000000 | G91: =(F91-F90) -> -2587721000000
A92: 91 | B92: SMMA | C92: 2017 | D92: =NCO!F92 -> 51665734000000 | E92: =NCO!I92 -> 66140481000000 | F92: =D92-E92 -> -14474747000000
A93: 92 | B93: SMMA | C93: 2018 | D93: =NCO!F93 -> 60635423000000 | E93: =NCO!I93 -> 75550211000000 | F93: =D93-E93 -> -14914788000000 | G93: =F93-F92 -> -440041000000
A94: 93 | B94: SMMA | C94: 2019 | D94: =NCO!F94 -> 58325664000000 | E94: =NCO!I94 -> 77460250000000 | F94: =D94-E94 -> -19134586000000 | G94: =F94-F93 -> -4219798000000
A95: 94 | B95: SMMA | C95: 2020 | D95: =NCO!F95 -> 59486860000000 | E95: =NCO!I95 -> 85533983000000 | F95: =D95-E95 -> -26047123000000 | G95: =F95-F94 -> -6912537000000
A96: 95 | B96: SMMA | C96: 2021 | D96: =NCO!F96 -> 72429486000000 | E96: =NCO!I96 -> 94727715000000 | F96: =D96-E96 -> -22298229000000 | G96: =F96-F95 -> 3748894000000
A97: 96 | B97: WOMF | C97: 2017 | D97: =NCO!F97 -> 0 | E97: =NCO!I97 -> 6755920000000 | F97: =D97-E97 -> -6755920000000
A98: 97 | B98: WOMF | C98: 2018 | D98: =NCO!F98 -> 3150000000 | E98: =NCO!I98 -> 7655464000000 | F98: =D98-E98 -> -7652314000000 | G98: =F98-F97 -> -896394000000
A99: 98 | B99: WOMF | C99: 2019 | D99: =NCO!F99 -> 3572000000 | E99: =NCO!I99 -> 6900593000000 | F99: =D99-E99 -> -6897021000000 | G99: =F99-F98 -> 755293000000
A100: 99 | B100: WOMF | C100: 2020 | D100: =NCO!F100 -> 2817000000 | E100: =NCO!I100 -> 4070357000000 | F100: =D100-E100 -> -4067540000000 | G100: =F100-F99 -> 2829481000000
...

Sheet RRST ACCRUAL
A1: No | B1: Kode Emiten | C1: Tahun | D1: ∆WC | E1: ∆NCO | F1: ∆FIN | G1: Total | H1: Average Total Asset | I1: RSST
A2: 1 | B2: ASTJ | C2: 2017 | D2: =WC!G2 -> 0 | E2: =NCO!O2 -> 0 | F2: =FIN!G2 -> 0 | G2: =D2+E2+F2 -> 0 | H2: ='Average Total Assets'!F2 -> 436601081601 | I2: =G2/H2 -> 0
A3: 2 | B3: ASTJ | C3: 2018 | D3: =WC!G3 -> 1521413070 | E3: =NCO!O3 -> 12628175399 | F3: =FIN!G3 -> -33807281657 | G3: =D3+E3+F3 -> -19657693188 | H3: ='Average Total Assets'!F3 -> 4.6227375e+11 | I3: =G3/H3 -> -0.042523923
A4: 3 | B4: ASTJ | C4: 2019 | D4: =WC!G4 -> -672457793 | E4: =NCO!O4 -> 64457514184 | F4: =FIN!G4 -> -63692083280 | G4: =D4+E4+F4 -> 92973111 | H4: ='Average Total Assets'!F4 -> 4.6305483e+11 | I4: =G4/H4 -> 0.00020078208
A5: 4 | B5: ASTJ | C5: 2020 | D5: =WC!G5 -> 43244267692 | E5: =NCO!O5 -> -57080103247 | F5: =FIN!G5 -> 103989523386 | G5: =D5+E5+F5 -> 90153687831 | H5: ='Average Total Assets'!F5 -> 406717116516 | I5: =G5/H5 -> 0.2216619
A6: 5 | B6: ASTJ | C6: 2021 | D6: =WC!G6 -> 24914326988 | E6: =NCO!O6 -> -2228098267 | F6: =FIN!G6 -> 23438767164 | G6: =D6+E6+F6 -> 46124995885 | H6: ='Average Total Assets'!F6 -> 4.4680808e+11 | I6: =G6/H6 -> 0.10323223
A7: 6 | B7: ASMI | C7: 2017 | D7: =WC!G7 -> 0 | E7: =NCO!O7 -> 0 | F7: =FIN!G7 -> 0 | G7: =D7+E7+F7 -> 0 | H7: ='Average Total Assets'!F7 -> 7.3807072e+11 | I7: =G7/H7 -> 0
A8: 7 | B8: ASMI | C8: 2018 | D8: =WC!G8 -> 29454981653 | E8: =NCO!O8 -> -28350108816 | F8: =FIN!G8 -> 12015660735 | G8: =D8+E8+F8 -> 13120533572 | H8: ='Average Total Assets'!F8 -> 914178422228 | I8: =G8/H8 -> 0.014352268
A9: 8 | B9: ASMI | C9: 2019 | D9: =WC!G9 -> 27253775692 | E9: =NCO!O9 -> 3105491375 | F9: =FIN!G9 -> 6465477531 | G9: =D9+E9+F9 -> 36824744598 | H9: ='Average Total Assets'!F9 -> 9.7277701e+11 | I9: =G9/H9 -> 0.037855278
A10: 9 | B10: ASMI | C10: 2020 | D10: =WC!G10 -> 244470213658 | E10: =NCO!O10 -> -129198815692 | F10: =FIN!G10 -> -311588716626 | G10: =D10+E10+F10 -> -196317318660 | H10: ='Average Total Assets'!F10 -> 9.833396e+11 | I10: =G10/H10 -> -0.19964346
A11: 10 | B11: ASMI | C11: 2021 | D11: =WC!G11 -> -91687444705 | E11: =NCO!O11 -> -6657574909 | F11: =FIN!G11 -> 106044106915 | G11: =D11+E11+F11 -> 7699087301 | H11: ='Average Total Assets'!F11 -> 986040658507 | I11: =G11/H11 -> 0.007808083
A12: 11 | B12: BBNI | C12: 2017 | D12: =WC!G12 -> 0 | E12: =NCO!O12 -> 0 | F12: =FIN!G12 -> 0 | G12: =D12+E12+F12 -> 0 | H12: ='Average Total Assets'!F12 -> 656180982000000 | I12: =G12/H12 -> 0
A13: 12 | B13: BBNI | C13: 2018 | D13: =WC!G13 -> 28347174409800 | E13: =NCO!O13 -> 8166604590200 | F13: =FIN!G13 -> -85003029000000 | G13: =D13+E13+F13 -> -48489250000000 | H13: ='Average Total Assets'!F13 -> 758951047500000 | I13: =G13/H13 -> -0.063889826
... A80: 79 | B80: PADI | C80: 2020 | D80: =WC!G80 -> -4055932218 | E80: =NCO!O80 -> -6782579330 | F80: =FIN!G80 -> -84549185751 | G80: =D80+E80+F80 -> -95387697299 | H80: ='Average Total Assets'!F80 -> 376502006661 | I80: =G80/H80 -> -0.25335243
A81: 80 | B81: PADI | C81: 2021 | D81: =WC!G81 -> 789448742 | E81: =-NCO!O81 -> 3041786331 | F81: =-FIN!G81 -> 40251095766 | G81: =D81+E81+F81 -> 44082330839 | H81: ='Average Total Assets'!F81 -> 300598582653 | I81: =G81/H81 -> 0.1466485
A82: 81 | B82: PNLF | C82: 2017 | D82: =WC!G82 -> 0 | E82: =NCO!O82 -> 0 | F82: =FIN!G82 -> 0 | G82: =D82+E82+F82 -> 0 | H82: ='Average Total Assets'!F82 -> 25722439000000 | I82: =G82/H82 -> 0
A83: 82 | B83: PNLF | C83: 2018 | D83: =WC!G83 -> 303556000000 | E83: =NCO!O83 -> 23169000000 | F83: =FIN!G83 -> 1425766000000 | G83: =D83+E83+F83 -> 1752491000000 | H83: ='Average Total Assets'!F83 -> 27362022500000 | I83: =G83/H83 -> 0.064048299
A84: 83 | B84: PNLF | C84: 2019 | D84: =WC!G84 -> 121044000000 | E84: =NCO!O84 -> -59803000000 | F84: =FIN!G84 -> 2009647000000 | G84: =D84+E84+F84 -> 2070888000000 | H84: ='Average Total Assets'!F84 -> 29271055500000 | I84: =G84/H84 -> 0.070748662
A85: 84 | B85: PNLF | C85: 2020 | D85: =WC!G85 -> 1773468000000 | E85: =NCO!O85 -> -44683000000 | F85: =FIN!G85 -> 97555000000 | G85: =D85+E85+F85 -> 1826340000000 | H85: ='Average Total Assets'!F85 -> 31335553500000 | I85: =G85/H85 -> 0.058283317
A86: 85 | B86: PNLF | C86: 2021 | D86: =WC!G86 -> 501732000000 | E86: =NCO!O86 -> 204128000000 | F86: =FIN!G86 -> 542004000000 | G86: =D86+E86+F86 -> 1247864000000 | H86: ='Average Total Assets'!F86 -> 32787151000000 | I86: =G86/H86 -> 0.038059544
A87: 86 | B87: SDRA | C87: 2017 | D87: =WC!G87 -> 0 | E87: =NCO!O87 -> 0 | F87: =FIN!G87 -> 0 | G87: =D87+E87+F87 -> 0 | H87: ='Average Total Assets'!F87 -> 24858569000000 | I87: =G87/H87 -> 0
A88: 87 | B88: SDRA | C88: 2018 | D88: =WC!G88 -> 3687974000000 | E88: =NCO!O88 -> -74889000000 | F88: =FIN!G88 -> -3170339000000 | G88: =D88+E88+F88 -> 442746000000 | H88: ='Average Total Assets'!F88 -> 28359098500000 | I88: =G88/H88 -> 0.015612132
A89: 88 | B89: SDRA | C89: 2019 | D89: =WC!G89 -> 522432000000 | E89: =NCO!O89 -> -846370000000 | F89: =FIN!G89 -> -6398917000000 | G89: =D89+E89+F89 -> -6722855000000 | H89: ='Average Total Assets'!F89 -> 33286064500000 | I89: =G89/H89 -> -0.20197206
A90: 89 | B90: SDRA | C90: 2020 | D90: =WC!G90 -> -1652464000000 | E90: =NCO!O90 -> 1632187000000 | F90: =FIN!G90 -> -434284000000 | G90: =D90+E90+F90 -> -454561000000 | H90: ='Average Total Assets'!F90 -> 37497187500000 | I90: =G90/H90 -> -0.012122536
A91: 90 | B91: SDRA | C91: 2021 | D91: =WC!G91 -> 1289605000000 | E91: =NCO!O91 -> -479790000000 | F91: =FIN!G91 -> -2587721000000 | G91: =D91+E91+F91 -> -1777906000000 | H91: ='Average Total Assets'!F91 -> 40927755000000 | I91: =G91/H91 -> -0.043440106
A92: 91 | B92: SMMA | C92: 2017 | D92: =WC!G92 -> 0 | E92: =NCO!O92 -> 0 | F92: =FIN!G92 -> 0 | G92: =D92+E92+F92 -> 0 | H92: ='Average Total Assets'!F92 -> 81540954500000 | I92: =G92/H92 -> 0
A93: 92 | B93: SMMA | C93: 2018 | D93: =WC!G93 -> 2231146000000 | E93: =NCO!O93 -> -11826027000000 | F93: =FIN!G93 -> -440041000000 | G93: =D93+E93+F93 -> -10034922000000 | H93: ='Average Total Assets'!F93 -> 94875119500000 | I93: =G93/H93 -> -0.1057698
... A102: 101 | B102: ASDM | C102: 2017 | D102: =WC!G102 -> 0 | E102: =NCO!O102 -> 0 | F102: =FIN!G102 -> 0 | G102: =D102+E102+F102 -> 0 | H102: ='Average Total Assets'!F102 -> 1070215752000 | I102: =G102/H102 -> 0
A103: 102 | C103: 2018 | D103: =WC!G103 -> 19145463000 | E103: =NCO!O103 -> -7828071000 | F103: =FIN!G103 -> 69419395000 | G103: =D103+E103+F103 -> 80736787000 | H103: ='Average Total Assets'!F103 -> 1068987124000 | I103: =G103/H103 -> 0.075526435
A104: 103 | C104: 2019 | D104: =WC!G104 -> -17091272000 | E104: =NCO!O104 -> -5361082000 | F104: =FIN!G104 -> -51204153000 | G104: =D104+E104+F104 -> -73656507000 | H104: ='Average Total Assets'!F104 -> 1109718793500 | I104: =G104/H104 -> -0.066374029
A105: 104 | C105: 2020 | D105: =WC!G105 -> -190178543000 | E105: =NCO!O105 -> 7574080000 | F105: =FIN!G105 -> 293586909000 | G105: =D105+E105+F105 -> 110982446000 | H105: ='Average Total Assets'!F105 -> 1008957633000 | I105: =G105/H105 -> 0.10999713
A106: 105 | C106: 2021 | D106: =WC!G106 -> -45255715000 | E106: =NCO!O106 -> 729454000 | F106: =FIN!G106 -> 65348114000 | G106: =D106+E106+F106 -> 20821853000 | H106: ='Average Total Assets'!F106 -> 841308440000 | I106: =G106/H106 -> 0.024749369
A107: 106 | B107: BBKP | C107: 2017 | D107: =WC!G107 -> 0 | E107: =NCO!O107 -> 0 | F107: =FIN!G107 -> 0 | G107: =D107+E107+F107 -> 0 | H107: ='Average Total Assets'!F107 -> 105924500500000 | I107: =G107/H107 -> 0
A108: 107 | C108: 2018 | D108: =WC!G108 -> 6400862000000 | E108: =NCO!O108 -> -1687504000000 | F108: =FIN!G108 -> 10277627000000 | G108: =D108+E108+F108 -> 14990985000000 | H108: ='Average Total Assets'!F108 -> 101043461000000 | I108: =G108/H108 -> 0.14836175
A109: 108 | C109: 2019 | D109: =WC!G109 -> -795069000000 | E109: =NCO!O109 -> 617802000000 | F109: =FIN!G109 -> -4083437000000 | G109: =D109+E109+F109 -> -4260704000000 | H109: ='Average Total Assets'!F109 -> 97954085500000 | I109: =G109/H109 -> -0.04349695
A110: 109 | C110: 2020 | D110: =WC!G110 -> 7617242000000 | E110: =NCO!O110 -> -2273240000000 | F110: =FIN!G110 -> 16843249000000 | G110: =D110+E110+F110 -> 22187251000000 | H110: ='Average Total Assets'!F110 -> 90101413000000 | I110: =G110/H110 -> 0.24624754
A111: 110 | C111: 2021 | D111: =WC!G111 -> 801496000000 | E111: =NCO!O111 -> 146176000000 | F111: =FIN!G111 -> -2170185000000 | G111: =D111+E111+F111 -> -1222513000000 | H111: ='Average Total Assets'!F111 -> 84577126000000 | I111: =G111/H111 -> -0.014454416
A112: 111 | B112: BBMD | C112: 2017 | D112: =WC!G112 -> 0 | E112: =NCO!O112 -> 0 | F112: =FIN!G112 -> 0 | G112: =D112+E112+F112 -> 0 | H112: ='Average Total Assets'!F112 -> 1.1203034e+13 | I112: =G112/H112 -> 0
A113: 112 | C113: 2018 | D113: =WC!G113 -> 1005308489997 | E113: =NCO!O113 -> -241277765591 | F113: =FIN!G113 -> -692654449345 | G113: =D113+E113+F113 -> 71376275061 | H113: ='Average Total Assets'!F113 -> 11955461912645 | I113: =G113/H113 -> 0.0059701813
A114: 113 | C114: 2019 | D114: =WC!G114 -> -386855006632 | E114: =NCO!O114 -> 137302123970 | F114: =FIN!G114 -> 115083278697 | G114: =D114+E114+F114 -> -134469603965 | H114: ='Average Total Assets'!F114 -> 1.2496649e+13 | I114: =G114/H114 -> -0.010760453
A115: 114 | C115: 2020 | D115: =WC!G115 -> -1984973678055 | E115: =NCO!O115 -> -83377412353 | F115: =FIN!G115 -> 1629050430988 | G115: =D115+E115+F115 -> -439300659420 | H115: ='Average Total Assets'!F115 -> 13529987003898 | I115: =G115/H115 -> -0.032468668
A116: 115 | C116: 2021 | D116: =WC!G116 -> -401335442325 | E116: =NCO!O116 -> 36458889880 | F116: =FIN!G116 -> -802662733863 | G116: =D116+E116+F116 -> -1167539286308 | H116: ='Average Total Assets'!F116 -> 1.5071454e+13 | I116: =G116/H116 -> -0.077466932
A117: 116 | B117: BBRI | C117: 2017 | D117: =WC!G117 -> 0 | E117: =NCO!O117 -> 0 | F117: =FIN!G117 -> 0 | G117: =D117+E117+F117 -> 0 | H117: ='Average Total Assets'!F117 -> 1.0029369e+15 | I117: =G117/H117 -> 0
A118: 117 | C118: 2018 | D118: =WC!G118 -> 74342062000000 | E118: =NCO!O118 -> -33278293000000 | F118: =FIN!G118 -> -164888080000000 | G118: =D118+E118+F118 -> -123824311000000 | H118: ='Average Total Assets'!F118 -> 1.2121729e+15 | I118: =G118/H118 -> -0.1021507
A119: 118 | C119: 2019 | D119: =WC!G119 -> -65755398000000 | E119: =NCO!O119 -> 77836267000000 | F119: =FIN!G119 -> -46880656000000 | G119: =D119+E119+F119 -> -34799787000000 | H119: ='Average Total Assets'!F119 -> 1.3568286e+15 | I119: =G119/H119 -> -0.025647888
A120: 119 | C120: 2020 | D120: =WC!G120 -> -156424373000000 | E120: =NCO!O120 -> 102811965000000 | F120: =FIN!G120 -> 60086449000000 | G120: =D120+E120+F120 -> 6474041000000 | H120: ='Average Total Assets'!F120 -> 1.5134121e+15 | I120: =G120/H120 -> 0.004277778
A121: 120 | C121: 2021 | D121: =WC!G121 -> 106109521000000 | E121: =NCO!O121 -> -117320494800000 | F121: =FIN!G121 -> -100238931200000 | G121: =D121+E121+F121 -> -111449905000000 | H121: ='Average Total Assets'!F121 -> 1.6440815e+15 | I121: =G121/H121 -> -0.067788551
A122: 121 | B122: BBYB | C122: 2017 | D122: =WC!G122 -> 0 | E122: =NCO!O122 -> 0 | F122: =FIN!G122 -> 0 | G122: =D122+E122+F122 -> 0 | H122: ='Average Total Assets'!F122 -> 4.9256617e+12 | I122: =G122/H122 -> 0
A123: 122 | C123: 2018 | D123: =WC!G123 -> -15587480618 | E123: =NCO!O123 -> 32443608458 | F123: =FIN!G123 -> 307967475838 | G123: =D123+E123+F123 -> 324823603678 | H123: ='Average Total Assets'!F123 -> 4.7692621e+12 | I123: =G123/H123 -> 0.068107728
A124: 123 | C124: 2019 | D124: =WC!G124 -> -368275264999 | E124: =NCO!O124 -> 380398038553 | F124: =FIN!G124 -> 91620644127 | G124: =D124+E124+F124 -> 103743417681 | H124: ='Average Total Assets'!F124 -> 4.8287319e+12 | I124: =G124/H124 -> 0.021484609
A125: 124 | C125: 2020 | D125: =WC!G125 -> -150979956553 | E125: =NCO!O125 -> -23595078174 | F125: =FIN!G125 -> 186772678619 | G125: =D125+E125+F125 -> 12197643892 | H125: ='Average Total Assets'!F125 -> 5.2725295e+12 | I125: =G125/H125 -> 0.002313433
A126: 125 | C126: 2021 | D126: =WC!G126 -> -5649264401529 | E126: =NCO!O126 -> 4950073690799 | F126: =FIN!G126 -> -1645653827402 | G126: =D126+E126+F126 -> -2344844538132 | H126: ='Average Total Assets'!F126 -> 8.3795665e+12 | I126: =G126/H126 -> -0.27982886
A127: 126 | B127: BINA | C127: 2017 | D127: =WC!G127 -> 0 | E127: =NCO!O127 -> 0 | F127: =FIN!G127 -> 0 | G127: =D127+E127+F127 -> 0 | H127: ='Average Total Assets'!F127 -> 2741217000000 | I127: =G127/H127 -> 0
A128: 127 | C128: 2018 | D128: =WC!G128 -> 50170000000 | E128: =NCO!O128 -> 46354803788 | F128: =FIN!G128 -> -817989000000 | G128: =D128+E128+F128 -> -721464196212 | H128: ='Average Total Assets'!F128 -> 3488759500000 | I128: =G128/H128 -> -0.20679677
A129: 128 | C129: 2019 | D129: =WC!G129 -> -647791000000 | E129: =NCO!O129 -> 15448320218 | F129: =FIN!G129 -> -737947000000 | G129: =D129+E129+F129 -> -1370289679782 | H129: ='Average Total Assets'!F129 -> 4558301500000 | I129: =G129/H129 -> -0.30061409
A130: 129 | C130: 2020 | D130: =WC!G130 -> -1677133000000 | E130: =NCO!O130 -> -29482000000 | F130: =FIN!G130 -> -1476545000000 | G130: =D130+E130+F130 -> -3183160000000 | H130: ='Average Total Assets'!F130 -> 6850057000000 | I130: =G130/H130 -> -0.46469102
A131: 130 | C131: 2021 | D131: =WC!G131 -> -1576559000000 | E131: =NCO!O131 -> 185265000000 | F131: =FIN!G131 -> -2882175000000 | G131: =D131+E131+F131 -> -4273469000000 | H131: ='Average Total Assets'!F131 -> 11746767500000 | I131: =G131/H131 -> -0.36379957
A132: 131 | B132: BJTM | C132: 2017 | D132: =WC!G132 -> 0 | E132: =NCO!O132 -> 0 | F132: =FIN!G132 -> 0 | G132: =D132+E132+F132 -> 0 | H132: ='Average Total Assets'!F132 -> 47275765500000 | I132: =G132/H132 -> 0
A133: 132 | C133: 2018 | D133: =WC!G133 -> -3006644000000 | E133: =NCO!O133 -> -524631000000 | F133: =FIN!G133 -> -6898653000000 | G133: =D133+E133+F133 -> -10429928000000 | H133: ='Average Total Assets'!F133 -> 57103849500000 | I133: =G133/H133 -> -0.18264842
A134: 133 | C134: 2019 | D134: =WC!G134 -> 140413000000 | E134: =NCO!O134 -> 349157000000 | F134: =FIN!G134 -> -12312838000000 | G134: =D134+E134+F134 -> -11823268000000 | H134: ='Average Total Assets'!F134 -> 69722715500000 | I134: =G134/H134 -> -0.16957555
A135: 134 | C135: 2020 | D135: =WC!G135 -> -5846242000000 | E135: =NCO!O135 -> 495193000000 | F135: =FIN!G135 -> -784201000000 | G135: =D135+E135+F135 -> -6135250000000 | H135: ='Average Total Assets'!F135 -> 80187882500000 | I135: =G135/H135 -> -0.076510937
A136: 135 | C136: 2021 | D136: =WC!G136 -> -16595632000000 | E136: =NCO!O136 -> -199248000000 | F136: =FIN!G136 -> 1526117000000 | G136: =D136+E136+F136 -> -15268763000000 | H136: ='Average Total Assets'!F136 -> 92171391000000 | I136: =G136/H136 -> -0.16565621
A137: 136 | B137: BMRI | C137: 2017 | D137: =WC!G137 -> 0 | E137: =NCO!O137 -> 0 | F137: =FIN!G137 -> 0 | G137: =D137+E137+F137 -> 0 | H137: ='Average Total Assets'!F137 -> 1.0817034e+15 | I137: =G137/H137 -> 0
A138: 137 | C138: 2018 | D138: =WC!G138 -> 21192963000000 | E138: =NCO!O138 -> 2709100000000 | F138: =FIN!G138 -> -37804971000000 | G138: =D138+E138+F138 -> -13902908000000 | H138: ='Average Total Assets'!F138 -> 1.1634765e+15 | I138: =G138/H138 -> -0.011949454
A139: 138 | C139: 2019 | D139: =WC!G139 -> 14647041000000 | E139: =NCO!O139 -> -2098282000000 | F139: =FIN!G139 -> -61740738000000 | G139: =D139+E139+F139 -> -49191979000000 | H139: ='Average Total Assets'!F139 -> 1.2602492e+15 | I139: =G139/H139 -> -0.039033533
A140: 139 | C140: 2020 | D140: =WC!G140 -> -52138637669696 | E140: =NCO!O140 -> -3562198330304 | F140: =FIN!G140 -> -84071153000000 | G140: =D140+E140+F140 -> -139771989000000 | H140: ='Average Total Assets'!F140 -> 1.3737904e+15 | I140: =G140/H140 -> -0.10174186
A141: 140 | C141: 2021 | D141: =WC!G141 -> -26903500330304 | E141: =NCO!O141 -> -2555933669696 | F141: =FIN!G141 -> -26403628000000 | G141: =D141+E141+F141 -> -55863062000000 | H141: ='Average Total Assets'!F141 -> 1.5774728e+15 | I141: =G141/H141 -> -0.035413011
A142: 141 | B142: BNBA | C142: 2017 | D142: =WC!G142 -> 0 | E142: =NCO!O142 -> 0 | F142: =FIN!G142 -> 0 | G142: =D142+E142+F142 -> 0 | H142: ='Average Total Assets'!F142 -> 7.0679253e+12 | I142: =G142/H142 -> 0
A143: 142 | C143: 2018 | D143: =WC!G143 -> 87227254387 | E143: =NCO!O143 -> 57665648483 | F143: =FIN!G143 -> -156838811640 | G143: =D143+E143+F143 -> -11945908770 | H143: ='Average Total Assets'!F143 -> 7.1559754e+12 | I143: =G143/H143 -> -0.0016693614
A144: 143 | C144: 2019 | D144: =WC!G144 -> 160308019075 | E144: =NCO!O144 -> 568884970 | F144: =FIN!G144 -> -422117457981 | G144: =D144+E144+F144 -> -261240553936 | H144: ='Average Total Assets'!F144 -> 7452463591318 | I144: =G144/H144 -> -0.035054254
A145: 144 | C145: 2020 | D145: =WC!G145 -> -1183799284889 | E145: =NCO!O145 -> 29636770245 | F145: =FIN!G145 -> 1101962831080 | G145: =D145+E145+F145 -> -52199683564 | H145: ='Average Total Assets'!F145 -> 7622589020615 | I145: =G145/H145 -> -0.0068480254
A146: 145 | C146: 2021 | D146: =WC!G146 -> -319395985941 | E146: =NCO!O146 -> 78017708290 | F146: =FIN!G146 -> 655769254357 | G146: =D146+E146+F146 -> 414390976706 | H146: ='Average Total Assets'!F146 -> 8152025077227 | I146: =G146/H146 -> 0.050832888
A147: 146 | B147: AGRO | C147: 2017 | D147: =WC!G147 -> 0 | E147: =NCO!O147 -> 0 | F147: =FIN!G147 -> 0 | G147: =D147+E147+F147 -> 0 | H147: ='Average Total Assets'!F147 -> 13850277046500 | I147: =G147/H147 -> 0
A148: 147 | C148: 2018 | D148: =WC!G148 -> -1060833420502 | E148: =NCO!O148 -> -362688175000 | F148: =FIN!G148 -> -6795807222000 | G148: =D148+E148+F148 -> -8219328817502 | H148: ='Average Total Assets'!F148 -> 19818132312000 | I148: =G148/H148 -> -0.41473781
A149: 148 | C149: 2019 | D149: =WC!G149 -> -417423450498 | E149: =NCO!O149 -> 3132810236502 | F149: =FIN!G149 -> 161058770000 | G149: =D149+E149+F149 -> 2876445556004 | H149: ='Average Total Assets'!F149 -> 25190797082000 | I149: =G149/H149 -> 0.11418637
A150: 149 | C150: 2020 | D150: =WC!G150 -> -1098659311000 | E150: =NCO!O150 -> -309620471000 | F150: =FIN!G150 -> -522294535000 | G150: =D150+E150+F150 -> -1930574317000 | H150: ='Average Total Assets'!F150 -> 27541707587000 | I150: =G150/H150 -> -0.070096391
A151: 150 | C151: 2021 | D151: =WC!G151 -> 254651794000 | E151: =NCO!O151 -> -7089477000 | F151: =FIN!G151 -> 7052484100000 | G151: =D151+E151+F151 -> 7300046417000 | H151: ='Average Total Assets'!F151 -> 22441007458500 | I151: =G151/H151 -> 0.32529941
A152: 151 | B152: BSIM | C152: 2017 | D152: =WC!G152 -> 0 | E152: =NCO!O152 -> 0 | F152: =FIN!G152 -> 0 | G152: =D152+E152+F152 -> 0 | H152: ='Average Total Assets'!F152 -> 30798352000000 | I152: =G152/H152 -> 0
